package com.tencent.bitapp.compression;

public class Zip
  extends AbstractCompression
{
  /* Error */
  private boolean compress(java.util.zip.ZipOutputStream paramZipOutputStream, java.io.File paramFile, String paramString, java.io.BufferedOutputStream paramBufferedOutputStream)
  {
    // Byte code:
    //   0: iconst_0
    //   1: istore 13
    //   3: aconst_null
    //   4: astore 9
    //   6: aconst_null
    //   7: astore 7
    //   9: aconst_null
    //   10: astore 10
    //   12: aconst_null
    //   13: astore 8
    //   15: aconst_null
    //   16: astore 6
    //   18: aload 10
    //   20: astore 4
    //   22: aload 9
    //   24: astore 5
    //   26: sipush 8192
    //   29: newarray <illegal type>
    //   31: astore 11
    //   33: aload 10
    //   35: astore 4
    //   37: aload 9
    //   39: astore 5
    //   41: new 15	java/io/FileInputStream
    //   44: dup
    //   45: aload_2
    //   46: invokespecial 18	java/io/FileInputStream:<init>	(Ljava/io/File;)V
    //   49: astore_2
    //   50: new 20	java/io/BufferedInputStream
    //   53: dup
    //   54: aload_2
    //   55: sipush 8192
    //   58: invokespecial 23	java/io/BufferedInputStream:<init>	(Ljava/io/InputStream;I)V
    //   61: astore 4
    //   63: aload_1
    //   64: new 25	java/util/zip/ZipEntry
    //   67: dup
    //   68: aload_3
    //   69: invokespecial 28	java/util/zip/ZipEntry:<init>	(Ljava/lang/String;)V
    //   72: invokevirtual 34	java/util/zip/ZipOutputStream:putNextEntry	(Ljava/util/zip/ZipEntry;)V
    //   75: aload 4
    //   77: aload 11
    //   79: iconst_0
    //   80: sipush 8192
    //   83: invokevirtual 38	java/io/BufferedInputStream:read	([BII)I
    //   86: istore 12
    //   88: iload 12
    //   90: iconst_m1
    //   91: if_icmpne +27 -> 118
    //   94: iconst_1
    //   95: istore 13
    //   97: aload 4
    //   99: ifnull +8 -> 107
    //   102: aload 4
    //   104: invokevirtual 41	java/io/BufferedInputStream:close	()V
    //   107: aload_2
    //   108: ifnull +123 -> 231
    //   111: aload_2
    //   112: invokevirtual 42	java/io/FileInputStream:close	()V
    //   115: iload 13
    //   117: ireturn
    //   118: aload_1
    //   119: aload 11
    //   121: iconst_0
    //   122: iload 12
    //   124: invokevirtual 46	java/util/zip/ZipOutputStream:write	([BII)V
    //   127: goto -52 -> 75
    //   130: astore_3
    //   131: aload_2
    //   132: astore_1
    //   133: aload 4
    //   135: astore_2
    //   136: aload_2
    //   137: astore 4
    //   139: aload_1
    //   140: astore 5
    //   142: aload_3
    //   143: invokevirtual 49	java/io/IOException:printStackTrace	()V
    //   146: aload_2
    //   147: ifnull +7 -> 154
    //   150: aload_2
    //   151: invokevirtual 41	java/io/BufferedInputStream:close	()V
    //   154: aload_1
    //   155: ifnull -40 -> 115
    //   158: aload_1
    //   159: invokevirtual 42	java/io/FileInputStream:close	()V
    //   162: iconst_0
    //   163: ireturn
    //   164: astore_1
    //   165: aload_1
    //   166: invokevirtual 49	java/io/IOException:printStackTrace	()V
    //   169: iconst_0
    //   170: ireturn
    //   171: astore_2
    //   172: aload_2
    //   173: invokevirtual 49	java/io/IOException:printStackTrace	()V
    //   176: goto -22 -> 154
    //   179: astore_1
    //   180: aload 4
    //   182: ifnull +8 -> 190
    //   185: aload 4
    //   187: invokevirtual 41	java/io/BufferedInputStream:close	()V
    //   190: aload 5
    //   192: ifnull +8 -> 200
    //   195: aload 5
    //   197: invokevirtual 42	java/io/FileInputStream:close	()V
    //   200: aload_1
    //   201: athrow
    //   202: astore_2
    //   203: aload_2
    //   204: invokevirtual 49	java/io/IOException:printStackTrace	()V
    //   207: goto -17 -> 190
    //   210: astore_2
    //   211: aload_2
    //   212: invokevirtual 49	java/io/IOException:printStackTrace	()V
    //   215: goto -15 -> 200
    //   218: astore_1
    //   219: aload_1
    //   220: invokevirtual 49	java/io/IOException:printStackTrace	()V
    //   223: goto -116 -> 107
    //   226: astore_1
    //   227: aload_1
    //   228: invokevirtual 49	java/io/IOException:printStackTrace	()V
    //   231: iconst_1
    //   232: ireturn
    //   233: astore_1
    //   234: aload 8
    //   236: astore 4
    //   238: aload_2
    //   239: astore 5
    //   241: goto -61 -> 180
    //   244: astore_1
    //   245: aload_2
    //   246: astore 5
    //   248: goto -68 -> 180
    //   251: astore_3
    //   252: aload 6
    //   254: astore_2
    //   255: aload 7
    //   257: astore_1
    //   258: goto -122 -> 136
    //   261: astore_3
    //   262: aload_2
    //   263: astore_1
    //   264: aload 6
    //   266: astore_2
    //   267: goto -131 -> 136
    // Local variable table:
    //   start	length	slot	name	signature
    //   0	270	0	this	Zip
    //   0	270	1	paramZipOutputStream	java.util.zip.ZipOutputStream
    //   0	270	2	paramFile	java.io.File
    //   0	270	3	paramString	String
    //   0	270	4	paramBufferedOutputStream	java.io.BufferedOutputStream
    //   24	223	5	localObject1	Object
    //   16	249	6	localObject2	Object
    //   7	249	7	localObject3	Object
    //   13	222	8	localObject4	Object
    //   4	34	9	localObject5	Object
    //   10	24	10	localObject6	Object
    //   31	89	11	arrayOfByte	byte[]
    //   86	37	12	i	int
    //   1	115	13	bool	boolean
    // Exception table:
    //   from	to	target	type
    //   63	75	130	java/io/IOException
    //   75	88	130	java/io/IOException
    //   118	127	130	java/io/IOException
    //   158	162	164	java/io/IOException
    //   150	154	171	java/io/IOException
    //   26	33	179	finally
    //   41	50	179	finally
    //   142	146	179	finally
    //   185	190	202	java/io/IOException
    //   195	200	210	java/io/IOException
    //   102	107	218	java/io/IOException
    //   111	115	226	java/io/IOException
    //   50	63	233	finally
    //   63	75	244	finally
    //   75	88	244	finally
    //   118	127	244	finally
    //   26	33	251	java/io/IOException
    //   41	50	251	java/io/IOException
    //   50	63	261	java/io/IOException
  }
  
  /* Error */
  protected boolean compress(java.util.List<String> paramList, String paramString1, String paramString2)
  {
    // Byte code:
    //   0: iconst_0
    //   1: istore 11
    //   3: iload 11
    //   5: istore 10
    //   7: aload_1
    //   8: ifnull +156 -> 164
    //   11: iload 11
    //   13: istore 10
    //   15: aload_3
    //   16: ifnull +148 -> 164
    //   19: iload 11
    //   21: istore 10
    //   23: aload_3
    //   24: invokevirtual 58	java/lang/String:length	()I
    //   27: ifle +137 -> 164
    //   30: iconst_1
    //   31: istore 10
    //   33: iconst_1
    //   34: istore 11
    //   36: iconst_1
    //   37: istore 13
    //   39: iconst_1
    //   40: istore 12
    //   42: new 60	java/util/HashSet
    //   45: dup
    //   46: invokespecial 61	java/util/HashSet:<init>	()V
    //   49: astore 9
    //   51: aload_0
    //   52: aload_1
    //   53: aload 9
    //   55: invokevirtual 65	com/tencent/bitapp/compression/Zip:listFiles	(Ljava/util/List;Ljava/util/Set;)Z
    //   58: ifeq +106 -> 164
    //   61: aconst_null
    //   62: astore 5
    //   64: aconst_null
    //   65: astore 8
    //   67: aconst_null
    //   68: astore 4
    //   70: aconst_null
    //   71: astore 7
    //   73: aconst_null
    //   74: astore 6
    //   76: new 30	java/util/zip/ZipOutputStream
    //   79: dup
    //   80: new 67	java/io/FileOutputStream
    //   83: dup
    //   84: aload_3
    //   85: invokespecial 68	java/io/FileOutputStream:<init>	(Ljava/lang/String;)V
    //   88: invokespecial 71	java/util/zip/ZipOutputStream:<init>	(Ljava/io/OutputStream;)V
    //   91: astore_1
    //   92: new 73	java/io/BufferedOutputStream
    //   95: dup
    //   96: aload_1
    //   97: invokespecial 74	java/io/BufferedOutputStream:<init>	(Ljava/io/OutputStream;)V
    //   100: astore_3
    //   101: iload 13
    //   103: istore 11
    //   105: aload 9
    //   107: invokeinterface 80 1 0
    //   112: astore 4
    //   114: iload 12
    //   116: istore 10
    //   118: iload 10
    //   120: istore 11
    //   122: aload 4
    //   124: invokeinterface 86 1 0
    //   129: istore 12
    //   131: iload 12
    //   133: ifne +34 -> 167
    //   136: iload 10
    //   138: istore 11
    //   140: aload_3
    //   141: ifnull +7 -> 148
    //   144: aload_3
    //   145: invokevirtual 87	java/io/BufferedOutputStream:close	()V
    //   148: iload 11
    //   150: istore 10
    //   152: aload_1
    //   153: ifnull +11 -> 164
    //   156: aload_1
    //   157: invokevirtual 88	java/util/zip/ZipOutputStream:close	()V
    //   160: iload 11
    //   162: istore 10
    //   164: iload 10
    //   166: ireturn
    //   167: iload 10
    //   169: istore 11
    //   171: new 90	java/io/File
    //   174: dup
    //   175: aload 4
    //   177: invokeinterface 94 1 0
    //   182: checkcast 54	java/lang/String
    //   185: invokespecial 95	java/io/File:<init>	(Ljava/lang/String;)V
    //   188: astore 5
    //   190: iload 10
    //   192: ifeq +48 -> 240
    //   195: iload 10
    //   197: istore 11
    //   199: aload_0
    //   200: aload_1
    //   201: aload 5
    //   203: aload 5
    //   205: invokevirtual 99	java/io/File:getAbsolutePath	()Ljava/lang/String;
    //   208: aload_2
    //   209: ldc 101
    //   211: invokevirtual 105	java/lang/String:replace	(Ljava/lang/CharSequence;Ljava/lang/CharSequence;)Ljava/lang/String;
    //   214: aload_3
    //   215: invokespecial 107	com/tencent/bitapp/compression/Zip:compress	(Ljava/util/zip/ZipOutputStream;Ljava/io/File;Ljava/lang/String;Ljava/io/BufferedOutputStream;)Z
    //   218: istore 10
    //   220: iload 10
    //   222: ifeq +18 -> 240
    //   225: iconst_1
    //   226: istore 11
    //   228: iload 11
    //   230: istore 10
    //   232: iload 11
    //   234: ifne -116 -> 118
    //   237: goto -97 -> 140
    //   240: iconst_0
    //   241: istore 11
    //   243: goto -15 -> 228
    //   246: astore_3
    //   247: aload 8
    //   249: astore_1
    //   250: aload 6
    //   252: astore_2
    //   253: aload_2
    //   254: astore 4
    //   256: aload_1
    //   257: astore 5
    //   259: aload_3
    //   260: invokevirtual 108	java/io/FileNotFoundException:printStackTrace	()V
    //   263: aload_2
    //   264: ifnull +7 -> 271
    //   267: aload_2
    //   268: invokevirtual 87	java/io/BufferedOutputStream:close	()V
    //   271: iload 11
    //   273: istore 10
    //   275: aload_1
    //   276: ifnull -112 -> 164
    //   279: aload_1
    //   280: invokevirtual 88	java/util/zip/ZipOutputStream:close	()V
    //   283: iload 11
    //   285: ireturn
    //   286: astore_1
    //   287: aload_1
    //   288: invokevirtual 49	java/io/IOException:printStackTrace	()V
    //   291: iload 11
    //   293: ireturn
    //   294: astore_2
    //   295: aload_2
    //   296: invokevirtual 49	java/io/IOException:printStackTrace	()V
    //   299: goto -28 -> 271
    //   302: astore_1
    //   303: aload 4
    //   305: ifnull +8 -> 313
    //   308: aload 4
    //   310: invokevirtual 87	java/io/BufferedOutputStream:close	()V
    //   313: aload 5
    //   315: ifnull +8 -> 323
    //   318: aload 5
    //   320: invokevirtual 88	java/util/zip/ZipOutputStream:close	()V
    //   323: aload_1
    //   324: athrow
    //   325: astore_2
    //   326: aload_2
    //   327: invokevirtual 49	java/io/IOException:printStackTrace	()V
    //   330: goto -17 -> 313
    //   333: astore_2
    //   334: aload_2
    //   335: invokevirtual 49	java/io/IOException:printStackTrace	()V
    //   338: goto -15 -> 323
    //   341: astore_2
    //   342: aload_2
    //   343: invokevirtual 49	java/io/IOException:printStackTrace	()V
    //   346: goto -198 -> 148
    //   349: astore_1
    //   350: aload_1
    //   351: invokevirtual 49	java/io/IOException:printStackTrace	()V
    //   354: iload 11
    //   356: ireturn
    //   357: astore_2
    //   358: aload 7
    //   360: astore 4
    //   362: aload_1
    //   363: astore 5
    //   365: aload_2
    //   366: astore_1
    //   367: goto -64 -> 303
    //   370: astore_2
    //   371: aload_3
    //   372: astore 4
    //   374: aload_1
    //   375: astore 5
    //   377: aload_2
    //   378: astore_1
    //   379: goto -76 -> 303
    //   382: astore_3
    //   383: aload 6
    //   385: astore_2
    //   386: goto -133 -> 253
    //   389: astore 4
    //   391: aload_3
    //   392: astore_2
    //   393: aload 4
    //   395: astore_3
    //   396: goto -143 -> 253
    // Local variable table:
    //   start	length	slot	name	signature
    //   0	399	0	this	Zip
    //   0	399	1	paramList	java.util.List<String>
    //   0	399	2	paramString1	String
    //   0	399	3	paramString2	String
    //   68	305	4	localObject1	Object
    //   389	5	4	localFileNotFoundException	java.io.FileNotFoundException
    //   62	314	5	localObject2	Object
    //   74	310	6	localObject3	Object
    //   71	288	7	localObject4	Object
    //   65	183	8	localObject5	Object
    //   49	57	9	localHashSet	java.util.HashSet
    //   5	269	10	bool1	boolean
    //   1	354	11	bool2	boolean
    //   40	92	12	bool3	boolean
    //   37	65	13	bool4	boolean
    // Exception table:
    //   from	to	target	type
    //   76	92	246	java/io/FileNotFoundException
    //   279	283	286	java/io/IOException
    //   267	271	294	java/io/IOException
    //   76	92	302	finally
    //   259	263	302	finally
    //   308	313	325	java/io/IOException
    //   318	323	333	java/io/IOException
    //   144	148	341	java/io/IOException
    //   156	160	349	java/io/IOException
    //   92	101	357	finally
    //   105	114	370	finally
    //   122	131	370	finally
    //   171	190	370	finally
    //   199	220	370	finally
    //   92	101	382	java/io/FileNotFoundException
    //   105	114	389	java/io/FileNotFoundException
    //   122	131	389	java/io/FileNotFoundException
    //   171	190	389	java/io/FileNotFoundException
    //   199	220	389	java/io/FileNotFoundException
  }
  
  /* Error */
  protected boolean compressFile(String paramString1, String paramString2)
  {
    // Byte code:
    //   0: iconst_0
    //   1: istore 9
    //   3: new 90	java/io/File
    //   6: dup
    //   7: aload_1
    //   8: invokespecial 95	java/io/File:<init>	(Ljava/lang/String;)V
    //   11: astore 8
    //   13: aconst_null
    //   14: astore 4
    //   16: aconst_null
    //   17: astore 7
    //   19: aconst_null
    //   20: astore_3
    //   21: aconst_null
    //   22: astore 5
    //   24: aconst_null
    //   25: astore 6
    //   27: new 30	java/util/zip/ZipOutputStream
    //   30: dup
    //   31: new 67	java/io/FileOutputStream
    //   34: dup
    //   35: aload_2
    //   36: invokespecial 68	java/io/FileOutputStream:<init>	(Ljava/lang/String;)V
    //   39: invokespecial 71	java/util/zip/ZipOutputStream:<init>	(Ljava/io/OutputStream;)V
    //   42: astore_1
    //   43: new 73	java/io/BufferedOutputStream
    //   46: dup
    //   47: aload_1
    //   48: invokespecial 74	java/io/BufferedOutputStream:<init>	(Ljava/io/OutputStream;)V
    //   51: astore_2
    //   52: aload_0
    //   53: aload_1
    //   54: aload 8
    //   56: aload 8
    //   58: invokevirtual 115	java/io/File:getName	()Ljava/lang/String;
    //   61: aload_2
    //   62: invokespecial 107	com/tencent/bitapp/compression/Zip:compress	(Ljava/util/zip/ZipOutputStream;Ljava/io/File;Ljava/lang/String;Ljava/io/BufferedOutputStream;)Z
    //   65: istore 10
    //   67: iload 10
    //   69: istore 9
    //   71: aload_2
    //   72: ifnull +7 -> 79
    //   75: aload_2
    //   76: invokevirtual 87	java/io/BufferedOutputStream:close	()V
    //   79: aload_1
    //   80: ifnull +111 -> 191
    //   83: aload_1
    //   84: invokevirtual 88	java/util/zip/ZipOutputStream:close	()V
    //   87: iload 9
    //   89: ireturn
    //   90: astore 5
    //   92: aload 7
    //   94: astore_1
    //   95: aload 6
    //   97: astore_2
    //   98: aload_2
    //   99: astore_3
    //   100: aload_1
    //   101: astore 4
    //   103: aload 5
    //   105: invokevirtual 108	java/io/FileNotFoundException:printStackTrace	()V
    //   108: aload_2
    //   109: ifnull +7 -> 116
    //   112: aload_2
    //   113: invokevirtual 87	java/io/BufferedOutputStream:close	()V
    //   116: aload_1
    //   117: ifnull -30 -> 87
    //   120: aload_1
    //   121: invokevirtual 88	java/util/zip/ZipOutputStream:close	()V
    //   124: iconst_0
    //   125: ireturn
    //   126: astore_1
    //   127: aload_1
    //   128: invokevirtual 49	java/io/IOException:printStackTrace	()V
    //   131: iconst_0
    //   132: ireturn
    //   133: astore_2
    //   134: aload_2
    //   135: invokevirtual 49	java/io/IOException:printStackTrace	()V
    //   138: goto -22 -> 116
    //   141: astore_1
    //   142: aload_3
    //   143: ifnull +7 -> 150
    //   146: aload_3
    //   147: invokevirtual 87	java/io/BufferedOutputStream:close	()V
    //   150: aload 4
    //   152: ifnull +8 -> 160
    //   155: aload 4
    //   157: invokevirtual 88	java/util/zip/ZipOutputStream:close	()V
    //   160: aload_1
    //   161: athrow
    //   162: astore_2
    //   163: aload_2
    //   164: invokevirtual 49	java/io/IOException:printStackTrace	()V
    //   167: goto -17 -> 150
    //   170: astore_2
    //   171: aload_2
    //   172: invokevirtual 49	java/io/IOException:printStackTrace	()V
    //   175: goto -15 -> 160
    //   178: astore_2
    //   179: aload_2
    //   180: invokevirtual 49	java/io/IOException:printStackTrace	()V
    //   183: goto -104 -> 79
    //   186: astore_1
    //   187: aload_1
    //   188: invokevirtual 49	java/io/IOException:printStackTrace	()V
    //   191: iload 9
    //   193: ireturn
    //   194: astore_2
    //   195: aload 5
    //   197: astore_3
    //   198: aload_1
    //   199: astore 4
    //   201: aload_2
    //   202: astore_1
    //   203: goto -61 -> 142
    //   206: astore 5
    //   208: aload_2
    //   209: astore_3
    //   210: aload_1
    //   211: astore 4
    //   213: aload 5
    //   215: astore_1
    //   216: goto -74 -> 142
    //   219: astore 5
    //   221: aload 6
    //   223: astore_2
    //   224: goto -126 -> 98
    //   227: astore 5
    //   229: goto -131 -> 98
    // Local variable table:
    //   start	length	slot	name	signature
    //   0	232	0	this	Zip
    //   0	232	1	paramString1	String
    //   0	232	2	paramString2	String
    //   20	190	3	localObject1	Object
    //   14	198	4	str	String
    //   22	1	5	localObject2	Object
    //   90	106	5	localFileNotFoundException1	java.io.FileNotFoundException
    //   206	8	5	localObject3	Object
    //   219	1	5	localFileNotFoundException2	java.io.FileNotFoundException
    //   227	1	5	localFileNotFoundException3	java.io.FileNotFoundException
    //   25	197	6	localObject4	Object
    //   17	76	7	localObject5	Object
    //   11	46	8	localFile	java.io.File
    //   1	191	9	bool1	boolean
    //   65	3	10	bool2	boolean
    // Exception table:
    //   from	to	target	type
    //   27	43	90	java/io/FileNotFoundException
    //   120	124	126	java/io/IOException
    //   112	116	133	java/io/IOException
    //   27	43	141	finally
    //   103	108	141	finally
    //   146	150	162	java/io/IOException
    //   155	160	170	java/io/IOException
    //   75	79	178	java/io/IOException
    //   83	87	186	java/io/IOException
    //   43	52	194	finally
    //   52	67	206	finally
    //   43	52	219	java/io/FileNotFoundException
    //   52	67	227	java/io/FileNotFoundException
  }
  
  /* Error */
  public boolean decompress(String paramString1, String paramString2)
  {
    // Byte code:
    //   0: iconst_0
    //   1: istore 8
    //   3: sipush 8192
    //   6: newarray <illegal type>
    //   8: astore 4
    //   10: aload_2
    //   11: astore_3
    //   12: iload 8
    //   14: istore 7
    //   16: aload_2
    //   17: ldc 120
    //   19: invokevirtual 124	java/lang/String:endsWith	(Ljava/lang/String;)Z
    //   22: ifne +27 -> 49
    //   25: iload 8
    //   27: istore 7
    //   29: new 126	java/lang/StringBuilder
    //   32: dup
    //   33: aload_2
    //   34: invokestatic 130	java/lang/String:valueOf	(Ljava/lang/Object;)Ljava/lang/String;
    //   37: invokespecial 131	java/lang/StringBuilder:<init>	(Ljava/lang/String;)V
    //   40: ldc 120
    //   42: invokevirtual 135	java/lang/StringBuilder:append	(Ljava/lang/String;)Ljava/lang/StringBuilder;
    //   45: invokevirtual 138	java/lang/StringBuilder:toString	()Ljava/lang/String;
    //   48: astore_3
    //   49: iload 8
    //   51: istore 7
    //   53: new 90	java/io/File
    //   56: dup
    //   57: aload_3
    //   58: invokespecial 95	java/io/File:<init>	(Ljava/lang/String;)V
    //   61: astore_2
    //   62: iload 8
    //   64: istore 7
    //   66: aload_2
    //   67: invokevirtual 141	java/io/File:isDirectory	()Z
    //   70: ifne +12 -> 82
    //   73: iload 8
    //   75: istore 7
    //   77: aload_2
    //   78: invokevirtual 144	java/io/File:mkdirs	()Z
    //   81: pop
    //   82: iload 8
    //   84: istore 7
    //   86: new 146	java/util/zip/ZipInputStream
    //   89: dup
    //   90: new 20	java/io/BufferedInputStream
    //   93: dup
    //   94: new 15	java/io/FileInputStream
    //   97: dup
    //   98: aload_1
    //   99: invokespecial 147	java/io/FileInputStream:<init>	(Ljava/lang/String;)V
    //   102: sipush 8192
    //   105: invokespecial 23	java/io/BufferedInputStream:<init>	(Ljava/io/InputStream;I)V
    //   108: invokespecial 150	java/util/zip/ZipInputStream:<init>	(Ljava/io/InputStream;)V
    //   111: astore_1
    //   112: aload_1
    //   113: invokevirtual 154	java/util/zip/ZipInputStream:getNextEntry	()Ljava/util/zip/ZipEntry;
    //   116: astore 5
    //   118: aload 5
    //   120: ifnonnull +12 -> 132
    //   123: iconst_1
    //   124: istore 7
    //   126: aload_1
    //   127: invokevirtual 155	java/util/zip/ZipInputStream:close	()V
    //   130: iconst_1
    //   131: ireturn
    //   132: new 90	java/io/File
    //   135: dup
    //   136: new 126	java/lang/StringBuilder
    //   139: dup
    //   140: aload_3
    //   141: invokestatic 130	java/lang/String:valueOf	(Ljava/lang/Object;)Ljava/lang/String;
    //   144: invokespecial 131	java/lang/StringBuilder:<init>	(Ljava/lang/String;)V
    //   147: aload 5
    //   149: invokevirtual 156	java/util/zip/ZipEntry:getName	()Ljava/lang/String;
    //   152: invokevirtual 135	java/lang/StringBuilder:append	(Ljava/lang/String;)Ljava/lang/StringBuilder;
    //   155: invokevirtual 138	java/lang/StringBuilder:toString	()Ljava/lang/String;
    //   158: invokespecial 95	java/io/File:<init>	(Ljava/lang/String;)V
    //   161: astore_2
    //   162: aload 5
    //   164: invokevirtual 157	java/util/zip/ZipEntry:isDirectory	()Z
    //   167: ifeq +41 -> 208
    //   170: aload_2
    //   171: invokevirtual 141	java/io/File:isDirectory	()Z
    //   174: ifne -62 -> 112
    //   177: aload_2
    //   178: invokevirtual 144	java/io/File:mkdirs	()Z
    //   181: pop
    //   182: goto -70 -> 112
    //   185: astore_2
    //   186: iload 8
    //   188: istore 7
    //   190: aload_1
    //   191: invokevirtual 155	java/util/zip/ZipInputStream:close	()V
    //   194: iload 8
    //   196: istore 7
    //   198: aload_2
    //   199: athrow
    //   200: astore_1
    //   201: aload_1
    //   202: invokevirtual 158	java/lang/Exception:printStackTrace	()V
    //   205: iload 7
    //   207: ireturn
    //   208: aload_2
    //   209: invokevirtual 162	java/io/File:getParentFile	()Ljava/io/File;
    //   212: astore 5
    //   214: aload 5
    //   216: ifnull +17 -> 233
    //   219: aload 5
    //   221: invokevirtual 141	java/io/File:isDirectory	()Z
    //   224: ifne +9 -> 233
    //   227: aload 5
    //   229: invokevirtual 144	java/io/File:mkdirs	()Z
    //   232: pop
    //   233: new 73	java/io/BufferedOutputStream
    //   236: dup
    //   237: new 67	java/io/FileOutputStream
    //   240: dup
    //   241: aload_2
    //   242: iconst_0
    //   243: invokespecial 165	java/io/FileOutputStream:<init>	(Ljava/io/File;Z)V
    //   246: sipush 8192
    //   249: invokespecial 168	java/io/BufferedOutputStream:<init>	(Ljava/io/OutputStream;I)V
    //   252: astore_2
    //   253: aload_1
    //   254: aload 4
    //   256: iconst_0
    //   257: sipush 8192
    //   260: invokevirtual 169	java/util/zip/ZipInputStream:read	([BII)I
    //   263: istore 6
    //   265: iload 6
    //   267: iconst_m1
    //   268: if_icmpne +18 -> 286
    //   271: aload_1
    //   272: invokevirtual 172	java/util/zip/ZipInputStream:closeEntry	()V
    //   275: aload_2
    //   276: invokevirtual 175	java/io/BufferedOutputStream:flush	()V
    //   279: aload_2
    //   280: invokevirtual 87	java/io/BufferedOutputStream:close	()V
    //   283: goto -171 -> 112
    //   286: aload_2
    //   287: aload 4
    //   289: iconst_0
    //   290: iload 6
    //   292: invokevirtual 176	java/io/BufferedOutputStream:write	([BII)V
    //   295: goto -42 -> 253
    //   298: astore_3
    //   299: aload_2
    //   300: invokevirtual 175	java/io/BufferedOutputStream:flush	()V
    //   303: aload_2
    //   304: invokevirtual 87	java/io/BufferedOutputStream:close	()V
    //   307: aload_3
    //   308: athrow
    // Local variable table:
    //   start	length	slot	name	signature
    //   0	309	0	this	Zip
    //   0	309	1	paramString1	String
    //   0	309	2	paramString2	String
    //   11	130	3	str	String
    //   298	10	3	localObject1	Object
    //   8	280	4	arrayOfByte	byte[]
    //   116	112	5	localObject2	Object
    //   263	28	6	i	int
    //   14	192	7	bool1	boolean
    //   1	194	8	bool2	boolean
    // Exception table:
    //   from	to	target	type
    //   112	118	185	finally
    //   132	182	185	finally
    //   208	214	185	finally
    //   219	233	185	finally
    //   233	253	185	finally
    //   275	283	185	finally
    //   299	309	185	finally
    //   16	25	200	java/lang/Exception
    //   29	49	200	java/lang/Exception
    //   53	62	200	java/lang/Exception
    //   66	73	200	java/lang/Exception
    //   77	82	200	java/lang/Exception
    //   86	112	200	java/lang/Exception
    //   126	130	200	java/lang/Exception
    //   190	194	200	java/lang/Exception
    //   198	200	200	java/lang/Exception
    //   253	265	298	finally
    //   271	275	298	finally
    //   286	295	298	finally
  }
}


/* Location:              E:\apk\QQ_91\classes5-dex2jar.jar!\com\tencent\bitapp\compression\Zip.class
 * Java compiler version: 6 (50.0)
 * JD-Core Version:       0.7.1
 */