package com.tencent.mapsdk.a.e;

import android.graphics.Bitmap;
import java.net.URL;
import java.util.Locale;

public final class e
  implements Runnable
{
  private static String c = Locale.getDefault().getLanguage() + "-" + Locale.getDefault().getCountry();
  public Bitmap a = null;
  public b b;
  private c d;
  private URL e;
  
  public e(c paramc, URL paramURL, b paramb)
  {
    this.d = paramc;
    this.e = paramURL;
    this.b = paramb;
  }
  
  /* Error */
  public final void run()
  {
    // Byte code:
    //   0: aconst_null
    //   1: astore_2
    //   2: aload_0
    //   3: getfield 54	com/tencent/mapsdk/a/e/e:d	Lcom/tencent/mapsdk/a/e/c;
    //   6: ifnull +11 -> 17
    //   9: aload_0
    //   10: getfield 54	com/tencent/mapsdk/a/e/e:d	Lcom/tencent/mapsdk/a/e/c;
    //   13: aload_0
    //   14: invokevirtual 68	com/tencent/mapsdk/a/e/c:b	(Lcom/tencent/mapsdk/a/e/e;)V
    //   17: iconst_0
    //   18: istore 7
    //   20: aconst_null
    //   21: astore_1
    //   22: aconst_null
    //   23: astore 4
    //   25: iload 7
    //   27: iconst_3
    //   28: if_icmpge +464 -> 492
    //   31: aload_2
    //   32: astore_3
    //   33: aload_1
    //   34: astore 5
    //   36: invokestatic 73	android/net/Proxy:getDefaultHost	()Ljava/lang/String;
    //   39: ifnull +450 -> 489
    //   42: aload_2
    //   43: astore_3
    //   44: aload_1
    //   45: astore 5
    //   47: new 75	java/net/Proxy
    //   50: dup
    //   51: getstatic 81	java/net/Proxy$Type:HTTP	Ljava/net/Proxy$Type;
    //   54: new 83	java/net/InetSocketAddress
    //   57: dup
    //   58: invokestatic 73	android/net/Proxy:getDefaultHost	()Ljava/lang/String;
    //   61: invokestatic 87	android/net/Proxy:getDefaultPort	()I
    //   64: invokespecial 90	java/net/InetSocketAddress:<init>	(Ljava/lang/String;I)V
    //   67: invokespecial 93	java/net/Proxy:<init>	(Ljava/net/Proxy$Type;Ljava/net/SocketAddress;)V
    //   70: astore 4
    //   72: aload 4
    //   74: ifnull +187 -> 261
    //   77: aload_2
    //   78: astore_3
    //   79: aload_1
    //   80: astore 5
    //   82: aload_0
    //   83: getfield 56	com/tencent/mapsdk/a/e/e:e	Ljava/net/URL;
    //   86: aload 4
    //   88: invokevirtual 99	java/net/URL:openConnection	(Ljava/net/Proxy;)Ljava/net/URLConnection;
    //   91: checkcast 101	java/net/HttpURLConnection
    //   94: astore 6
    //   96: aload 6
    //   98: astore_1
    //   99: aload_1
    //   100: sipush 5000
    //   103: invokevirtual 105	java/net/HttpURLConnection:setConnectTimeout	(I)V
    //   106: aload_1
    //   107: sipush 15000
    //   110: invokevirtual 108	java/net/HttpURLConnection:setReadTimeout	(I)V
    //   113: aload_1
    //   114: ldc 110
    //   116: ldc 112
    //   118: invokevirtual 116	java/net/HttpURLConnection:setRequestProperty	(Ljava/lang/String;Ljava/lang/String;)V
    //   121: aload_1
    //   122: ldc 118
    //   124: getstatic 47	com/tencent/mapsdk/a/e/e:c	Ljava/lang/String;
    //   127: invokevirtual 116	java/net/HttpURLConnection:setRequestProperty	(Ljava/lang/String;Ljava/lang/String;)V
    //   130: aload_1
    //   131: invokevirtual 122	java/net/HttpURLConnection:getInputStream	()Ljava/io/InputStream;
    //   134: astore 5
    //   136: new 124	java/io/ByteArrayOutputStream
    //   139: dup
    //   140: invokespecial 125	java/io/ByteArrayOutputStream:<init>	()V
    //   143: astore_3
    //   144: sipush 2048
    //   147: newarray <illegal type>
    //   149: astore_2
    //   150: aload 5
    //   152: aload_2
    //   153: iconst_0
    //   154: aload_2
    //   155: arraylength
    //   156: invokevirtual 131	java/io/InputStream:read	([BII)I
    //   159: istore 8
    //   161: iload 8
    //   163: iconst_m1
    //   164: if_icmpeq +120 -> 284
    //   167: aload_3
    //   168: aload_2
    //   169: iconst_0
    //   170: iload 8
    //   172: invokevirtual 135	java/io/ByteArrayOutputStream:write	([BII)V
    //   175: goto -25 -> 150
    //   178: astore 4
    //   180: aload_3
    //   181: astore_2
    //   182: aload_2
    //   183: astore_3
    //   184: aload_1
    //   185: astore 5
    //   187: new 20	java/lang/StringBuilder
    //   190: dup
    //   191: ldc -119
    //   193: invokespecial 140	java/lang/StringBuilder:<init>	(Ljava/lang/String;)V
    //   196: aload 4
    //   198: invokevirtual 143	java/lang/Exception:getMessage	()Ljava/lang/String;
    //   201: invokevirtual 37	java/lang/StringBuilder:append	(Ljava/lang/String;)Ljava/lang/StringBuilder;
    //   204: pop
    //   205: aload_1
    //   206: ifnull +7 -> 213
    //   209: aload_1
    //   210: invokevirtual 146	java/net/HttpURLConnection:disconnect	()V
    //   213: aload_0
    //   214: getfield 54	com/tencent/mapsdk/a/e/e:d	Lcom/tencent/mapsdk/a/e/c;
    //   217: ifnull +11 -> 228
    //   220: aload_0
    //   221: getfield 54	com/tencent/mapsdk/a/e/e:d	Lcom/tencent/mapsdk/a/e/c;
    //   224: aload_0
    //   225: invokevirtual 148	com/tencent/mapsdk/a/e/c:a	(Lcom/tencent/mapsdk/a/e/e;)V
    //   228: aload_0
    //   229: getfield 52	com/tencent/mapsdk/a/e/e:a	Landroid/graphics/Bitmap;
    //   232: ifnull +20 -> 252
    //   235: aload_0
    //   236: getfield 52	com/tencent/mapsdk/a/e/e:a	Landroid/graphics/Bitmap;
    //   239: invokevirtual 154	android/graphics/Bitmap:isRecycled	()Z
    //   242: ifne +10 -> 252
    //   245: aload_0
    //   246: getfield 52	com/tencent/mapsdk/a/e/e:a	Landroid/graphics/Bitmap;
    //   249: invokevirtual 157	android/graphics/Bitmap:recycle	()V
    //   252: aload_2
    //   253: ifnull +7 -> 260
    //   256: aload_2
    //   257: invokevirtual 160	java/io/ByteArrayOutputStream:close	()V
    //   260: return
    //   261: aload_2
    //   262: astore_3
    //   263: aload_1
    //   264: astore 5
    //   266: aload_0
    //   267: getfield 56	com/tencent/mapsdk/a/e/e:e	Ljava/net/URL;
    //   270: invokevirtual 163	java/net/URL:openConnection	()Ljava/net/URLConnection;
    //   273: checkcast 101	java/net/HttpURLConnection
    //   276: astore 6
    //   278: aload 6
    //   280: astore_1
    //   281: goto -182 -> 99
    //   284: aload_3
    //   285: invokevirtual 166	java/io/ByteArrayOutputStream:flush	()V
    //   288: aload_3
    //   289: invokevirtual 170	java/io/ByteArrayOutputStream:toByteArray	()[B
    //   292: astore_2
    //   293: aload_2
    //   294: ifnull +91 -> 385
    //   297: aload_0
    //   298: aload_2
    //   299: iconst_0
    //   300: aload_2
    //   301: arraylength
    //   302: invokestatic 176	android/graphics/BitmapFactory:decodeByteArray	([BII)Landroid/graphics/Bitmap;
    //   305: putfield 52	com/tencent/mapsdk/a/e/e:a	Landroid/graphics/Bitmap;
    //   308: aload_0
    //   309: getfield 52	com/tencent/mapsdk/a/e/e:a	Landroid/graphics/Bitmap;
    //   312: ifnull +73 -> 385
    //   315: invokestatic 181	com/tencent/mapsdk/a/e/a:a	()Lcom/tencent/mapsdk/a/e/a;
    //   318: aload_2
    //   319: aload_0
    //   320: getfield 58	com/tencent/mapsdk/a/e/e:b	Lcom/tencent/mapsdk/a/e/b;
    //   323: invokevirtual 184	com/tencent/mapsdk/a/e/a:a	([BLcom/tencent/mapsdk/a/e/b;)Z
    //   326: pop
    //   327: aload_1
    //   328: ifnull +7 -> 335
    //   331: aload_1
    //   332: invokevirtual 146	java/net/HttpURLConnection:disconnect	()V
    //   335: aload_0
    //   336: getfield 54	com/tencent/mapsdk/a/e/e:d	Lcom/tencent/mapsdk/a/e/c;
    //   339: ifnull +11 -> 350
    //   342: aload_0
    //   343: getfield 54	com/tencent/mapsdk/a/e/e:d	Lcom/tencent/mapsdk/a/e/c;
    //   346: aload_0
    //   347: invokevirtual 148	com/tencent/mapsdk/a/e/c:a	(Lcom/tencent/mapsdk/a/e/e;)V
    //   350: aload_0
    //   351: getfield 52	com/tencent/mapsdk/a/e/e:a	Landroid/graphics/Bitmap;
    //   354: ifnull +20 -> 374
    //   357: aload_0
    //   358: getfield 52	com/tencent/mapsdk/a/e/e:a	Landroid/graphics/Bitmap;
    //   361: invokevirtual 154	android/graphics/Bitmap:isRecycled	()Z
    //   364: ifne +10 -> 374
    //   367: aload_0
    //   368: getfield 52	com/tencent/mapsdk/a/e/e:a	Landroid/graphics/Bitmap;
    //   371: invokevirtual 157	android/graphics/Bitmap:recycle	()V
    //   374: aload_3
    //   375: ifnull -115 -> 260
    //   378: aload_3
    //   379: invokevirtual 160	java/io/ByteArrayOutputStream:close	()V
    //   382: return
    //   383: astore_1
    //   384: return
    //   385: iload 7
    //   387: iconst_1
    //   388: iadd
    //   389: istore 7
    //   391: aload_3
    //   392: astore_2
    //   393: goto -368 -> 25
    //   396: astore 4
    //   398: aload_3
    //   399: astore_2
    //   400: aload_1
    //   401: ifnull +7 -> 408
    //   404: aload_1
    //   405: invokevirtual 146	java/net/HttpURLConnection:disconnect	()V
    //   408: aload_0
    //   409: getfield 54	com/tencent/mapsdk/a/e/e:d	Lcom/tencent/mapsdk/a/e/c;
    //   412: ifnull +11 -> 423
    //   415: aload_0
    //   416: getfield 54	com/tencent/mapsdk/a/e/e:d	Lcom/tencent/mapsdk/a/e/c;
    //   419: aload_0
    //   420: invokevirtual 148	com/tencent/mapsdk/a/e/c:a	(Lcom/tencent/mapsdk/a/e/e;)V
    //   423: aload_0
    //   424: getfield 52	com/tencent/mapsdk/a/e/e:a	Landroid/graphics/Bitmap;
    //   427: ifnull +20 -> 447
    //   430: aload_0
    //   431: getfield 52	com/tencent/mapsdk/a/e/e:a	Landroid/graphics/Bitmap;
    //   434: invokevirtual 154	android/graphics/Bitmap:isRecycled	()Z
    //   437: ifne +10 -> 447
    //   440: aload_0
    //   441: getfield 52	com/tencent/mapsdk/a/e/e:a	Landroid/graphics/Bitmap;
    //   444: invokevirtual 157	android/graphics/Bitmap:recycle	()V
    //   447: aload_2
    //   448: ifnull +7 -> 455
    //   451: aload_2
    //   452: invokevirtual 160	java/io/ByteArrayOutputStream:close	()V
    //   455: aload 4
    //   457: athrow
    //   458: astore_1
    //   459: return
    //   460: astore_1
    //   461: goto -6 -> 455
    //   464: astore 4
    //   466: aload 5
    //   468: astore_1
    //   469: aload_3
    //   470: astore_2
    //   471: goto -71 -> 400
    //   474: astore 4
    //   476: goto -76 -> 400
    //   479: astore 4
    //   481: goto -299 -> 182
    //   484: astore 4
    //   486: goto -304 -> 182
    //   489: goto -417 -> 72
    //   492: aload_2
    //   493: astore_3
    //   494: goto -167 -> 327
    // Local variable table:
    //   start	length	slot	name	signature
    //   0	497	0	this	e
    //   21	311	1	localObject1	Object
    //   383	22	1	localIOException1	java.io.IOException
    //   458	1	1	localIOException2	java.io.IOException
    //   460	1	1	localIOException3	java.io.IOException
    //   468	1	1	localObject2	Object
    //   1	492	2	localObject3	Object
    //   32	462	3	localObject4	Object
    //   23	64	4	localProxy	java.net.Proxy
    //   178	19	4	localException1	Exception
    //   396	60	4	localObject5	Object
    //   464	1	4	localObject6	Object
    //   474	1	4	localObject7	Object
    //   479	1	4	localException2	Exception
    //   484	1	4	localException3	Exception
    //   34	433	5	localObject8	Object
    //   94	185	6	localHttpURLConnection	java.net.HttpURLConnection
    //   18	372	7	i	int
    //   159	12	8	j	int
    // Exception table:
    //   from	to	target	type
    //   144	150	178	java/lang/Exception
    //   150	161	178	java/lang/Exception
    //   167	175	178	java/lang/Exception
    //   284	293	178	java/lang/Exception
    //   297	327	178	java/lang/Exception
    //   378	382	383	java/io/IOException
    //   144	150	396	finally
    //   150	161	396	finally
    //   167	175	396	finally
    //   284	293	396	finally
    //   297	327	396	finally
    //   256	260	458	java/io/IOException
    //   451	455	460	java/io/IOException
    //   36	42	464	finally
    //   47	72	464	finally
    //   82	96	464	finally
    //   187	205	464	finally
    //   266	278	464	finally
    //   99	144	474	finally
    //   36	42	479	java/lang/Exception
    //   47	72	479	java/lang/Exception
    //   82	96	479	java/lang/Exception
    //   266	278	479	java/lang/Exception
    //   99	144	484	java/lang/Exception
  }
}


/* Location:              E:\apk\QQ_91\classes3-dex2jar.jar!\com\tencent\mapsdk\a\e\e.class
 * Java compiler version: 6 (50.0)
 * JD-Core Version:       0.7.1
 */