import android.os.Bundle;
import com.tencent.mobileqq.emosm.Client.onRemoteRespObserver;
import com.tencent.mobileqq.hotpatch.NotVerifyClass;
import com.tencent.mobileqq.jsp.DataApiPlugin;

public class sxk
  extends Client.onRemoteRespObserver
{
  public sxk(DataApiPlugin paramDataApiPlugin)
  {
    boolean bool = NotVerifyClass.DO_VERIFY_CLASS;
  }
  
  public void onBindedToClient() {}
  
  public void onDisconnectWithService() {}
  
  public void onPushMsg(Bundle paramBundle) {}
  
  /* Error */
  public void onResponse(Bundle paramBundle)
  {
    // Byte code:
    //   0: iconst_1
    //   1: istore 6
    //   3: aload_1
    //   4: ifnull +209 -> 213
    //   7: aload_1
    //   8: ldc 33
    //   10: iconst_0
    //   11: invokevirtual 39	android/os/Bundle:getInt	(Ljava/lang/String;I)I
    //   14: aload_0
    //   15: getfield 10	sxk:a	Lcom/tencent/mobileqq/jsp/DataApiPlugin;
    //   18: getfield 44	com/tencent/mobileqq/jsp/DataApiPlugin:a	Lcom/tencent/mobileqq/emosm/Client$onRemoteRespObserver;
    //   21: getfield 48	com/tencent/mobileqq/emosm/Client$onRemoteRespObserver:key	I
    //   24: if_icmpne +189 -> 213
    //   27: aload_1
    //   28: ldc 50
    //   30: invokevirtual 54	android/os/Bundle:getString	(Ljava/lang/String;)Ljava/lang/String;
    //   33: astore_2
    //   34: aload_1
    //   35: ldc 56
    //   37: invokevirtual 54	android/os/Bundle:getString	(Ljava/lang/String;)Ljava/lang/String;
    //   40: astore_3
    //   41: aload_1
    //   42: ldc 58
    //   44: invokevirtual 62	android/os/Bundle:getBundle	(Ljava/lang/String;)Landroid/os/Bundle;
    //   47: astore_1
    //   48: invokestatic 68	com/tencent/qphone/base/util/QLog:isColorLevel	()Z
    //   51: ifeq +29 -> 80
    //   54: getstatic 72	com/tencent/mobileqq/jsp/DataApiPlugin:c	Ljava/lang/String;
    //   57: iconst_2
    //   58: new 74	java/lang/StringBuilder
    //   61: dup
    //   62: invokespecial 75	java/lang/StringBuilder:<init>	()V
    //   65: ldc 77
    //   67: invokevirtual 81	java/lang/StringBuilder:append	(Ljava/lang/String;)Ljava/lang/StringBuilder;
    //   70: aload_2
    //   71: invokevirtual 81	java/lang/StringBuilder:append	(Ljava/lang/String;)Ljava/lang/StringBuilder;
    //   74: invokevirtual 85	java/lang/StringBuilder:toString	()Ljava/lang/String;
    //   77: invokestatic 89	com/tencent/qphone/base/util/QLog:i	(Ljava/lang/String;ILjava/lang/String;)V
    //   80: aload_2
    //   81: ifnull +132 -> 213
    //   84: ldc 91
    //   86: aload_2
    //   87: invokevirtual 97	java/lang/String:equals	(Ljava/lang/Object;)Z
    //   90: ifeq +124 -> 214
    //   93: new 99	org/json/JSONObject
    //   96: dup
    //   97: invokespecial 100	org/json/JSONObject:<init>	()V
    //   100: astore_2
    //   101: aload_1
    //   102: ldc 102
    //   104: invokevirtual 105	android/os/Bundle:getInt	(Ljava/lang/String;)I
    //   107: istore 6
    //   109: aload_2
    //   110: ldc 107
    //   112: iconst_0
    //   113: invokevirtual 111	org/json/JSONObject:put	(Ljava/lang/String;I)Lorg/json/JSONObject;
    //   116: pop
    //   117: aload_2
    //   118: ldc 113
    //   120: ldc 115
    //   122: invokevirtual 118	org/json/JSONObject:put	(Ljava/lang/String;Ljava/lang/Object;)Lorg/json/JSONObject;
    //   125: pop
    //   126: new 99	org/json/JSONObject
    //   129: dup
    //   130: invokespecial 100	org/json/JSONObject:<init>	()V
    //   133: astore 4
    //   135: aload 4
    //   137: ldc 120
    //   139: aload_1
    //   140: ldc 120
    //   142: invokevirtual 54	android/os/Bundle:getString	(Ljava/lang/String;)Ljava/lang/String;
    //   145: invokevirtual 118	org/json/JSONObject:put	(Ljava/lang/String;Ljava/lang/Object;)Lorg/json/JSONObject;
    //   148: pop
    //   149: aload 4
    //   151: ldc 102
    //   153: iload 6
    //   155: invokevirtual 111	org/json/JSONObject:put	(Ljava/lang/String;I)Lorg/json/JSONObject;
    //   158: pop
    //   159: aload_2
    //   160: ldc 122
    //   162: aload 4
    //   164: invokevirtual 118	org/json/JSONObject:put	(Ljava/lang/String;Ljava/lang/Object;)Lorg/json/JSONObject;
    //   167: pop
    //   168: aload_3
    //   169: invokestatic 128	android/text/TextUtils:isEmpty	(Ljava/lang/CharSequence;)Z
    //   172: ifne +41 -> 213
    //   175: aload_0
    //   176: getfield 10	sxk:a	Lcom/tencent/mobileqq/jsp/DataApiPlugin;
    //   179: new 74	java/lang/StringBuilder
    //   182: dup
    //   183: invokespecial 75	java/lang/StringBuilder:<init>	()V
    //   186: aload_3
    //   187: invokevirtual 81	java/lang/StringBuilder:append	(Ljava/lang/String;)Ljava/lang/StringBuilder;
    //   190: ldc -126
    //   192: invokevirtual 81	java/lang/StringBuilder:append	(Ljava/lang/String;)Ljava/lang/StringBuilder;
    //   195: aload_2
    //   196: invokevirtual 131	org/json/JSONObject:toString	()Ljava/lang/String;
    //   199: invokevirtual 81	java/lang/StringBuilder:append	(Ljava/lang/String;)Ljava/lang/StringBuilder;
    //   202: ldc -123
    //   204: invokevirtual 81	java/lang/StringBuilder:append	(Ljava/lang/String;)Ljava/lang/StringBuilder;
    //   207: invokevirtual 85	java/lang/StringBuilder:toString	()Ljava/lang/String;
    //   210: invokevirtual 137	com/tencent/mobileqq/jsp/DataApiPlugin:callJs	(Ljava/lang/String;)V
    //   213: return
    //   214: ldc -117
    //   216: aload_2
    //   217: invokevirtual 97	java/lang/String:equals	(Ljava/lang/Object;)Z
    //   220: ifeq +319 -> 539
    //   223: new 99	org/json/JSONObject
    //   226: dup
    //   227: invokespecial 100	org/json/JSONObject:<init>	()V
    //   230: astore 4
    //   232: aload_1
    //   233: ifnull +292 -> 525
    //   236: aload_1
    //   237: ldc -115
    //   239: invokevirtual 54	android/os/Bundle:getString	(Ljava/lang/String;)Ljava/lang/String;
    //   242: astore_1
    //   243: new 143	java/io/File
    //   246: dup
    //   247: aload_1
    //   248: invokespecial 145	java/io/File:<init>	(Ljava/lang/String;)V
    //   251: invokevirtual 148	java/io/File:exists	()Z
    //   254: ifeq +179 -> 433
    //   257: new 150	android/graphics/BitmapFactory$Options
    //   260: dup
    //   261: invokespecial 151	android/graphics/BitmapFactory$Options:<init>	()V
    //   264: aload_1
    //   265: sipush 200
    //   268: invokestatic 156	com/tencent/mobileqq/utils/ImageUtil:a	(Landroid/graphics/BitmapFactory$Options;Ljava/lang/String;I)Landroid/graphics/BitmapFactory$Options;
    //   271: astore_2
    //   272: aload_1
    //   273: aload_2
    //   274: invokestatic 162	android/graphics/BitmapFactory:decodeFile	(Ljava/lang/String;Landroid/graphics/BitmapFactory$Options;)Landroid/graphics/Bitmap;
    //   277: astore_1
    //   278: aload_1
    //   279: invokevirtual 168	android/graphics/Bitmap:getWidth	()I
    //   282: istore 6
    //   284: aload_1
    //   285: invokevirtual 171	android/graphics/Bitmap:getHeight	()I
    //   288: istore 7
    //   290: aload_1
    //   291: iload 6
    //   293: i2f
    //   294: iload 6
    //   296: iload 7
    //   298: invokestatic 174	com/tencent/mobileqq/utils/ImageUtil:a	(Landroid/graphics/Bitmap;FII)Landroid/graphics/Bitmap;
    //   301: astore_2
    //   302: aload_2
    //   303: astore_1
    //   304: aload_2
    //   305: ifnull +23 -> 328
    //   308: aload_2
    //   309: astore_1
    //   310: aload_2
    //   311: invokevirtual 168	android/graphics/Bitmap:getWidth	()I
    //   314: sipush 200
    //   317: if_icmple +11 -> 328
    //   320: aload_2
    //   321: sipush 200
    //   324: invokestatic 178	com/tencent/mobileqq/utils/ImageUtil:b	(Landroid/graphics/Bitmap;I)Landroid/graphics/Bitmap;
    //   327: astore_1
    //   328: aload_1
    //   329: ifnonnull +111 -> 440
    //   332: aload 4
    //   334: ldc 107
    //   336: sipush 1002
    //   339: invokevirtual 111	org/json/JSONObject:put	(Ljava/lang/String;I)Lorg/json/JSONObject;
    //   342: pop
    //   343: aload_3
    //   344: invokestatic 128	android/text/TextUtils:isEmpty	(Ljava/lang/CharSequence;)Z
    //   347: ifne -134 -> 213
    //   350: aload_0
    //   351: getfield 10	sxk:a	Lcom/tencent/mobileqq/jsp/DataApiPlugin;
    //   354: new 74	java/lang/StringBuilder
    //   357: dup
    //   358: invokespecial 75	java/lang/StringBuilder:<init>	()V
    //   361: aload_3
    //   362: invokevirtual 81	java/lang/StringBuilder:append	(Ljava/lang/String;)Ljava/lang/StringBuilder;
    //   365: ldc -126
    //   367: invokevirtual 81	java/lang/StringBuilder:append	(Ljava/lang/String;)Ljava/lang/StringBuilder;
    //   370: aload 4
    //   372: invokevirtual 131	org/json/JSONObject:toString	()Ljava/lang/String;
    //   375: invokevirtual 81	java/lang/StringBuilder:append	(Ljava/lang/String;)Ljava/lang/StringBuilder;
    //   378: ldc -123
    //   380: invokevirtual 81	java/lang/StringBuilder:append	(Ljava/lang/String;)Ljava/lang/StringBuilder;
    //   383: invokevirtual 85	java/lang/StringBuilder:toString	()Ljava/lang/String;
    //   386: invokevirtual 137	com/tencent/mobileqq/jsp/DataApiPlugin:callJs	(Ljava/lang/String;)V
    //   389: return
    //   390: astore_1
    //   391: invokestatic 68	com/tencent/qphone/base/util/QLog:isColorLevel	()Z
    //   394: ifeq -181 -> 213
    //   397: getstatic 72	com/tencent/mobileqq/jsp/DataApiPlugin:c	Ljava/lang/String;
    //   400: iconst_2
    //   401: new 74	java/lang/StringBuilder
    //   404: dup
    //   405: invokespecial 75	java/lang/StringBuilder:<init>	()V
    //   408: ldc -76
    //   410: invokevirtual 81	java/lang/StringBuilder:append	(Ljava/lang/String;)Ljava/lang/StringBuilder;
    //   413: aload_1
    //   414: invokevirtual 183	java/lang/Exception:getMessage	()Ljava/lang/String;
    //   417: invokevirtual 81	java/lang/StringBuilder:append	(Ljava/lang/String;)Ljava/lang/StringBuilder;
    //   420: invokevirtual 85	java/lang/StringBuilder:toString	()Ljava/lang/String;
    //   423: invokestatic 89	com/tencent/qphone/base/util/QLog:i	(Ljava/lang/String;ILjava/lang/String;)V
    //   426: return
    //   427: astore_1
    //   428: aconst_null
    //   429: astore_1
    //   430: goto -102 -> 328
    //   433: invokestatic 186	com/tencent/mobileqq/utils/ImageUtil:a	()Landroid/graphics/Bitmap;
    //   436: astore_1
    //   437: goto -109 -> 328
    //   440: new 188	java/io/ByteArrayOutputStream
    //   443: dup
    //   444: invokespecial 189	java/io/ByteArrayOutputStream:<init>	()V
    //   447: astore_2
    //   448: aload_1
    //   449: getstatic 195	android/graphics/Bitmap$CompressFormat:PNG	Landroid/graphics/Bitmap$CompressFormat;
    //   452: bipush 100
    //   454: aload_2
    //   455: invokevirtual 199	android/graphics/Bitmap:compress	(Landroid/graphics/Bitmap$CompressFormat;ILjava/io/OutputStream;)Z
    //   458: pop
    //   459: aload_2
    //   460: invokevirtual 203	java/io/ByteArrayOutputStream:toByteArray	()[B
    //   463: iconst_2
    //   464: invokestatic 209	com/tencent/mobileqq/utils/Base64Util:encodeToString	([BI)Ljava/lang/String;
    //   467: astore 5
    //   469: aload 4
    //   471: ldc 107
    //   473: iconst_0
    //   474: invokevirtual 111	org/json/JSONObject:put	(Ljava/lang/String;I)Lorg/json/JSONObject;
    //   477: pop
    //   478: aload 4
    //   480: ldc -45
    //   482: new 74	java/lang/StringBuilder
    //   485: dup
    //   486: invokespecial 75	java/lang/StringBuilder:<init>	()V
    //   489: ldc -43
    //   491: invokevirtual 81	java/lang/StringBuilder:append	(Ljava/lang/String;)Ljava/lang/StringBuilder;
    //   494: aload 5
    //   496: invokevirtual 81	java/lang/StringBuilder:append	(Ljava/lang/String;)Ljava/lang/StringBuilder;
    //   499: invokevirtual 85	java/lang/StringBuilder:toString	()Ljava/lang/String;
    //   502: invokevirtual 118	org/json/JSONObject:put	(Ljava/lang/String;Ljava/lang/Object;)Lorg/json/JSONObject;
    //   505: pop
    //   506: aload 4
    //   508: ldc -41
    //   510: aload_1
    //   511: invokevirtual 168	android/graphics/Bitmap:getWidth	()I
    //   514: invokevirtual 111	org/json/JSONObject:put	(Ljava/lang/String;I)Lorg/json/JSONObject;
    //   517: pop
    //   518: aload_2
    //   519: invokevirtual 218	java/io/ByteArrayOutputStream:close	()V
    //   522: goto -179 -> 343
    //   525: aload 4
    //   527: ldc 107
    //   529: sipush 1002
    //   532: invokevirtual 111	org/json/JSONObject:put	(Ljava/lang/String;I)Lorg/json/JSONObject;
    //   535: pop
    //   536: goto -193 -> 343
    //   539: ldc -36
    //   541: aload_2
    //   542: invokevirtual 97	java/lang/String:equals	(Ljava/lang/Object;)Z
    //   545: ifeq -332 -> 213
    //   548: new 99	org/json/JSONObject
    //   551: dup
    //   552: invokespecial 100	org/json/JSONObject:<init>	()V
    //   555: astore_2
    //   556: aload_2
    //   557: ldc 107
    //   559: iconst_0
    //   560: invokevirtual 111	org/json/JSONObject:put	(Ljava/lang/String;I)Lorg/json/JSONObject;
    //   563: pop
    //   564: new 99	org/json/JSONObject
    //   567: dup
    //   568: invokespecial 100	org/json/JSONObject:<init>	()V
    //   571: astore 4
    //   573: aload_1
    //   574: ldc 107
    //   576: iconst_0
    //   577: invokevirtual 224	android/os/Bundle:getBoolean	(Ljava/lang/String;Z)Z
    //   580: ifeq +55 -> 635
    //   583: aload 4
    //   585: ldc -30
    //   587: iload 6
    //   589: invokevirtual 111	org/json/JSONObject:put	(Ljava/lang/String;I)Lorg/json/JSONObject;
    //   592: pop
    //   593: aload_2
    //   594: ldc 122
    //   596: aload 4
    //   598: invokevirtual 118	org/json/JSONObject:put	(Ljava/lang/String;Ljava/lang/Object;)Lorg/json/JSONObject;
    //   601: pop
    //   602: aload_3
    //   603: invokestatic 128	android/text/TextUtils:isEmpty	(Ljava/lang/CharSequence;)Z
    //   606: ifne -393 -> 213
    //   609: aload_0
    //   610: getfield 10	sxk:a	Lcom/tencent/mobileqq/jsp/DataApiPlugin;
    //   613: aload_3
    //   614: iconst_1
    //   615: anewarray 93	java/lang/String
    //   618: dup
    //   619: iconst_0
    //   620: aload_2
    //   621: invokevirtual 131	org/json/JSONObject:toString	()Ljava/lang/String;
    //   624: aastore
    //   625: invokevirtual 229	com/tencent/mobileqq/jsp/DataApiPlugin:callJs	(Ljava/lang/String;[Ljava/lang/String;)V
    //   628: return
    //   629: astore_1
    //   630: aload_1
    //   631: invokevirtual 232	org/json/JSONException:printStackTrace	()V
    //   634: return
    //   635: iconst_2
    //   636: istore 6
    //   638: goto -55 -> 583
    //   641: astore_1
    //   642: return
    // Local variable table:
    //   start	length	slot	name	signature
    //   0	643	0	this	sxk
    //   0	643	1	paramBundle	Bundle
    //   33	588	2	localObject	Object
    //   40	574	3	str1	String
    //   133	464	4	localJSONObject	org.json.JSONObject
    //   467	28	5	str2	String
    //   1	636	6	i	int
    //   288	9	7	j	int
    // Exception table:
    //   from	to	target	type
    //   223	232	390	java/lang/Exception
    //   236	272	390	java/lang/Exception
    //   272	302	390	java/lang/Exception
    //   310	328	390	java/lang/Exception
    //   332	343	390	java/lang/Exception
    //   343	389	390	java/lang/Exception
    //   433	437	390	java/lang/Exception
    //   440	522	390	java/lang/Exception
    //   525	536	390	java/lang/Exception
    //   272	302	427	java/lang/OutOfMemoryError
    //   310	328	427	java/lang/OutOfMemoryError
    //   556	583	629	org/json/JSONException
    //   583	628	629	org/json/JSONException
    //   93	213	641	org/json/JSONException
  }
}


/* Location:              E:\apk\QQ_91\classes2-dex2jar.jar!\sxk.class
 * Java compiler version: 6 (50.0)
 * JD-Core Version:       0.7.1
 */