import com.etrump.mixlayout.FontManager;
import com.tencent.mobileqq.hotpatch.NotVerifyClass;

public class tl
  implements Runnable
{
  public tl(FontManager paramFontManager)
  {
    boolean bool = NotVerifyClass.DO_VERIFY_CLASS;
  }
  
  /* Error */
  public void run()
  {
    // Byte code:
    //   0: aload_0
    //   1: getfield 12	tl:a	Lcom/etrump/mixlayout/FontManager;
    //   4: getfield 33	com/etrump/mixlayout/FontManager:c	Ljava/util/concurrent/atomic/AtomicBoolean;
    //   7: invokevirtual 39	java/util/concurrent/atomic/AtomicBoolean:get	()Z
    //   10: ifne +28 -> 38
    //   13: invokestatic 44	com/tencent/qphone/base/util/QLog:isColorLevel	()Z
    //   16: ifeq +11 -> 27
    //   19: ldc 46
    //   21: iconst_2
    //   22: ldc 48
    //   24: invokestatic 52	com/tencent/qphone/base/util/QLog:d	(Ljava/lang/String;ILjava/lang/String;)V
    //   27: aload_0
    //   28: getfield 12	tl:a	Lcom/etrump/mixlayout/FontManager;
    //   31: getstatic 56	com/etrump/mixlayout/FontManager:b	Ljava/lang/String;
    //   34: invokevirtual 59	com/etrump/mixlayout/FontManager:a	(Ljava/lang/String;)I
    //   37: pop
    //   38: getstatic 65	com/tencent/mobileqq/vas/ClubContentJsonTask:n	Lcom/tencent/mobileqq/vas/ClubContentJsonTask$TaskInfo;
    //   41: getfield 68	com/tencent/mobileqq/vas/ClubContentJsonTask$TaskInfo:b	Ljava/lang/String;
    //   44: astore_2
    //   45: new 70	java/io/File
    //   48: dup
    //   49: aload_0
    //   50: getfield 12	tl:a	Lcom/etrump/mixlayout/FontManager;
    //   53: getfield 73	com/etrump/mixlayout/FontManager:jdField_a_of_type_ComTencentMobileqqAppQQAppInterface	Lcom/tencent/mobileqq/app/QQAppInterface;
    //   56: invokevirtual 79	com/tencent/mobileqq/app/QQAppInterface:getApplication	()Lmqq/app/MobileQQ;
    //   59: invokevirtual 85	mqq/app/MobileQQ:getApplicationContext	()Landroid/content/Context;
    //   62: invokevirtual 91	android/content/Context:getFilesDir	()Ljava/io/File;
    //   65: aload_2
    //   66: invokespecial 94	java/io/File:<init>	(Ljava/io/File;Ljava/lang/String;)V
    //   69: astore_1
    //   70: aload_1
    //   71: invokevirtual 97	java/io/File:exists	()Z
    //   74: ifeq +892 -> 966
    //   77: aload_1
    //   78: invokestatic 102	com/tencent/mobileqq/utils/FileUtils:a	(Ljava/io/File;)Ljava/lang/String;
    //   81: astore_1
    //   82: aload_1
    //   83: invokestatic 108	android/text/TextUtils:isEmpty	(Ljava/lang/CharSequence;)Z
    //   86: ifne +614 -> 700
    //   89: new 110	org/json/JSONArray
    //   92: dup
    //   93: aload_1
    //   94: invokespecial 113	org/json/JSONArray:<init>	(Ljava/lang/String;)V
    //   97: astore_1
    //   98: aload_1
    //   99: ifnull +601 -> 700
    //   102: aload_0
    //   103: getfield 12	tl:a	Lcom/etrump/mixlayout/FontManager;
    //   106: getfield 73	com/etrump/mixlayout/FontManager:jdField_a_of_type_ComTencentMobileqqAppQQAppInterface	Lcom/tencent/mobileqq/app/QQAppInterface;
    //   109: invokevirtual 79	com/tencent/mobileqq/app/QQAppInterface:getApplication	()Lmqq/app/MobileQQ;
    //   112: ldc 115
    //   114: iconst_0
    //   115: invokevirtual 119	mqq/app/MobileQQ:getSharedPreferences	(Ljava/lang/String;I)Landroid/content/SharedPreferences;
    //   118: astore 4
    //   120: aload 4
    //   122: invokeinterface 125 1 0
    //   127: astore 5
    //   129: iconst_0
    //   130: istore 8
    //   132: iload 8
    //   134: aload_1
    //   135: invokevirtual 129	org/json/JSONArray:length	()I
    //   138: if_icmpge +562 -> 700
    //   141: aload_1
    //   142: iload 8
    //   144: invokevirtual 133	org/json/JSONArray:getJSONObject	(I)Lorg/json/JSONObject;
    //   147: astore_2
    //   148: aload_2
    //   149: ldc -121
    //   151: ldc -119
    //   153: invokevirtual 143	org/json/JSONObject:optString	(Ljava/lang/String;Ljava/lang/String;)Ljava/lang/String;
    //   156: astore 6
    //   158: aload 6
    //   160: invokestatic 108	android/text/TextUtils:isEmpty	(Ljava/lang/CharSequence;)Z
    //   163: ifne +17 -> 180
    //   166: aload 6
    //   168: ldc -111
    //   170: invokevirtual 151	java/lang/String:equals	(Ljava/lang/Object;)Z
    //   173: istore 11
    //   175: iload 11
    //   177: ifeq +100 -> 277
    //   180: iload 8
    //   182: iconst_1
    //   183: iadd
    //   184: istore 8
    //   186: goto -54 -> 132
    //   189: astore_1
    //   190: invokestatic 44	com/tencent/qphone/base/util/QLog:isColorLevel	()Z
    //   193: ifeq +35 -> 228
    //   196: ldc 46
    //   198: iconst_2
    //   199: new 153	java/lang/StringBuilder
    //   202: dup
    //   203: invokespecial 154	java/lang/StringBuilder:<init>	()V
    //   206: ldc -100
    //   208: invokevirtual 160	java/lang/StringBuilder:append	(Ljava/lang/String;)Ljava/lang/StringBuilder;
    //   211: aload_2
    //   212: invokevirtual 160	java/lang/StringBuilder:append	(Ljava/lang/String;)Ljava/lang/StringBuilder;
    //   215: aload_1
    //   216: invokevirtual 164	java/lang/OutOfMemoryError:getMessage	()Ljava/lang/String;
    //   219: invokevirtual 160	java/lang/StringBuilder:append	(Ljava/lang/String;)Ljava/lang/StringBuilder;
    //   222: invokevirtual 167	java/lang/StringBuilder:toString	()Ljava/lang/String;
    //   225: invokestatic 170	com/tencent/qphone/base/util/QLog:e	(Ljava/lang/String;ILjava/lang/String;)V
    //   228: aconst_null
    //   229: astore_1
    //   230: goto -148 -> 82
    //   233: astore_1
    //   234: invokestatic 44	com/tencent/qphone/base/util/QLog:isColorLevel	()Z
    //   237: ifeq +35 -> 272
    //   240: ldc 46
    //   242: iconst_2
    //   243: new 153	java/lang/StringBuilder
    //   246: dup
    //   247: invokespecial 154	java/lang/StringBuilder:<init>	()V
    //   250: ldc -84
    //   252: invokevirtual 160	java/lang/StringBuilder:append	(Ljava/lang/String;)Ljava/lang/StringBuilder;
    //   255: aload_2
    //   256: invokevirtual 160	java/lang/StringBuilder:append	(Ljava/lang/String;)Ljava/lang/StringBuilder;
    //   259: aload_1
    //   260: invokevirtual 173	java/lang/Exception:getMessage	()Ljava/lang/String;
    //   263: invokevirtual 160	java/lang/StringBuilder:append	(Ljava/lang/String;)Ljava/lang/StringBuilder;
    //   266: invokevirtual 167	java/lang/StringBuilder:toString	()Ljava/lang/String;
    //   269: invokestatic 170	com/tencent/qphone/base/util/QLog:e	(Ljava/lang/String;ILjava/lang/String;)V
    //   272: aconst_null
    //   273: astore_1
    //   274: goto -176 -> 98
    //   277: aload 6
    //   279: invokestatic 178	java/lang/Integer:parseInt	(Ljava/lang/String;)I
    //   282: istore 9
    //   284: getstatic 181	com/etrump/mixlayout/FontManager:jdField_a_of_type_JavaUtilConcurrentConcurrentHashMap	Ljava/util/concurrent/ConcurrentHashMap;
    //   287: iload 9
    //   289: invokestatic 185	java/lang/Integer:valueOf	(I)Ljava/lang/Integer;
    //   292: invokevirtual 190	java/util/concurrent/ConcurrentHashMap:containsKey	(Ljava/lang/Object;)Z
    //   295: ifeq +635 -> 930
    //   298: aload_2
    //   299: ldc -64
    //   301: iconst_0
    //   302: invokevirtual 196	org/json/JSONObject:optInt	(Ljava/lang/String;I)I
    //   305: istore 10
    //   307: aload_2
    //   308: ldc -58
    //   310: ldc -119
    //   312: invokevirtual 143	org/json/JSONObject:optString	(Ljava/lang/String;Ljava/lang/String;)Ljava/lang/String;
    //   315: astore 7
    //   317: aload 7
    //   319: invokestatic 108	android/text/TextUtils:isEmpty	(Ljava/lang/CharSequence;)Z
    //   322: ifne -142 -> 180
    //   325: aload 4
    //   327: aload 6
    //   329: ldc -119
    //   331: invokeinterface 201 3 0
    //   336: astore_3
    //   337: aload_3
    //   338: astore_2
    //   339: aload_3
    //   340: invokestatic 108	android/text/TextUtils:isEmpty	(Ljava/lang/CharSequence;)Z
    //   343: ifeq +126 -> 469
    //   346: new 70	java/io/File
    //   349: dup
    //   350: getstatic 181	com/etrump/mixlayout/FontManager:jdField_a_of_type_JavaUtilConcurrentConcurrentHashMap	Ljava/util/concurrent/ConcurrentHashMap;
    //   353: iload 9
    //   355: invokestatic 185	java/lang/Integer:valueOf	(I)Ljava/lang/Integer;
    //   358: invokevirtual 204	java/util/concurrent/ConcurrentHashMap:get	(Ljava/lang/Object;)Ljava/lang/Object;
    //   361: checkcast 206	com/etrump/mixlayout/FontInfo
    //   364: getfield 208	com/etrump/mixlayout/FontInfo:a	Ljava/lang/String;
    //   367: invokespecial 209	java/io/File:<init>	(Ljava/lang/String;)V
    //   370: astore_3
    //   371: new 211	java/io/BufferedInputStream
    //   374: dup
    //   375: new 213	java/io/FileInputStream
    //   378: dup
    //   379: aload_3
    //   380: invokespecial 216	java/io/FileInputStream:<init>	(Ljava/io/File;)V
    //   383: invokespecial 219	java/io/BufferedInputStream:<init>	(Ljava/io/InputStream;)V
    //   386: astore_2
    //   387: aload_2
    //   388: aload_3
    //   389: invokevirtual 222	java/io/File:length	()J
    //   392: invokestatic 228	com/tencent/qphone/base/util/MD5:toMD5Byte	(Ljava/io/InputStream;J)[B
    //   395: astore_3
    //   396: aload_2
    //   397: invokevirtual 231	java/io/BufferedInputStream:close	()V
    //   400: aload_3
    //   401: invokestatic 236	com/tencent/mobileqq/transfile/StructLongMessageDownloadProcessor:a	([B)Ljava/lang/String;
    //   404: astore_3
    //   405: aload 5
    //   407: aload 6
    //   409: aload_3
    //   410: invokeinterface 242 3 0
    //   415: pop
    //   416: aload 5
    //   418: invokeinterface 245 1 0
    //   423: pop
    //   424: aload_3
    //   425: astore_2
    //   426: invokestatic 44	com/tencent/qphone/base/util/QLog:isColorLevel	()Z
    //   429: ifeq +40 -> 469
    //   432: ldc 46
    //   434: iconst_2
    //   435: new 153	java/lang/StringBuilder
    //   438: dup
    //   439: invokespecial 154	java/lang/StringBuilder:<init>	()V
    //   442: ldc -9
    //   444: invokevirtual 160	java/lang/StringBuilder:append	(Ljava/lang/String;)Ljava/lang/StringBuilder;
    //   447: aload 6
    //   449: invokevirtual 160	java/lang/StringBuilder:append	(Ljava/lang/String;)Ljava/lang/StringBuilder;
    //   452: ldc -7
    //   454: invokevirtual 160	java/lang/StringBuilder:append	(Ljava/lang/String;)Ljava/lang/StringBuilder;
    //   457: aload_3
    //   458: invokevirtual 160	java/lang/StringBuilder:append	(Ljava/lang/String;)Ljava/lang/StringBuilder;
    //   461: invokevirtual 167	java/lang/StringBuilder:toString	()Ljava/lang/String;
    //   464: invokestatic 52	com/tencent/qphone/base/util/QLog:d	(Ljava/lang/String;ILjava/lang/String;)V
    //   467: aload_3
    //   468: astore_2
    //   469: aload_2
    //   470: aload 7
    //   472: invokevirtual 151	java/lang/String:equals	(Ljava/lang/Object;)Z
    //   475: ifne +409 -> 884
    //   478: invokestatic 44	com/tencent/qphone/base/util/QLog:isColorLevel	()Z
    //   481: ifeq +48 -> 529
    //   484: ldc 46
    //   486: iconst_2
    //   487: new 153	java/lang/StringBuilder
    //   490: dup
    //   491: invokespecial 154	java/lang/StringBuilder:<init>	()V
    //   494: ldc -5
    //   496: invokevirtual 160	java/lang/StringBuilder:append	(Ljava/lang/String;)Ljava/lang/StringBuilder;
    //   499: aload 6
    //   501: invokevirtual 160	java/lang/StringBuilder:append	(Ljava/lang/String;)Ljava/lang/StringBuilder;
    //   504: ldc -3
    //   506: invokevirtual 160	java/lang/StringBuilder:append	(Ljava/lang/String;)Ljava/lang/StringBuilder;
    //   509: aload_2
    //   510: invokevirtual 160	java/lang/StringBuilder:append	(Ljava/lang/String;)Ljava/lang/StringBuilder;
    //   513: ldc -1
    //   515: invokevirtual 160	java/lang/StringBuilder:append	(Ljava/lang/String;)Ljava/lang/StringBuilder;
    //   518: aload 7
    //   520: invokevirtual 160	java/lang/StringBuilder:append	(Ljava/lang/String;)Ljava/lang/StringBuilder;
    //   523: invokevirtual 167	java/lang/StringBuilder:toString	()Ljava/lang/String;
    //   526: invokestatic 52	com/tencent/qphone/base/util/QLog:d	(Ljava/lang/String;ILjava/lang/String;)V
    //   529: iload 10
    //   531: iconst_1
    //   532: if_icmpne +245 -> 777
    //   535: aload_0
    //   536: getfield 12	tl:a	Lcom/etrump/mixlayout/FontManager;
    //   539: getfield 257	com/etrump/mixlayout/FontManager:jdField_a_of_type_JavaUtilConcurrentAtomicAtomicBoolean	Ljava/util/concurrent/atomic/AtomicBoolean;
    //   542: invokevirtual 39	java/util/concurrent/atomic/AtomicBoolean:get	()Z
    //   545: ifeq +18 -> 563
    //   548: aload_0
    //   549: getfield 12	tl:a	Lcom/etrump/mixlayout/FontManager;
    //   552: getfield 260	com/etrump/mixlayout/FontManager:jdField_a_of_type_ComEtrumpMixlayoutETEngine	Lcom/etrump/mixlayout/ETEngine;
    //   555: iload 9
    //   557: invokevirtual 266	com/etrump/mixlayout/ETEngine:native_isFontLoaded	(I)Z
    //   560: ifne +141 -> 701
    //   563: invokestatic 44	com/tencent/qphone/base/util/QLog:isColorLevel	()Z
    //   566: ifeq +30 -> 596
    //   569: ldc 46
    //   571: iconst_2
    //   572: new 153	java/lang/StringBuilder
    //   575: dup
    //   576: invokespecial 154	java/lang/StringBuilder:<init>	()V
    //   579: ldc_w 268
    //   582: invokevirtual 160	java/lang/StringBuilder:append	(Ljava/lang/String;)Ljava/lang/StringBuilder;
    //   585: aload 6
    //   587: invokevirtual 160	java/lang/StringBuilder:append	(Ljava/lang/String;)Ljava/lang/StringBuilder;
    //   590: invokevirtual 167	java/lang/StringBuilder:toString	()Ljava/lang/String;
    //   593: invokestatic 52	com/tencent/qphone/base/util/QLog:d	(Ljava/lang/String;ILjava/lang/String;)V
    //   596: aload_0
    //   597: getfield 12	tl:a	Lcom/etrump/mixlayout/FontManager;
    //   600: getfield 73	com/etrump/mixlayout/FontManager:jdField_a_of_type_ComTencentMobileqqAppQQAppInterface	Lcom/tencent/mobileqq/app/QQAppInterface;
    //   603: ldc_w 270
    //   606: ldc -119
    //   608: ldc -119
    //   610: ldc_w 272
    //   613: ldc_w 274
    //   616: iconst_0
    //   617: iconst_0
    //   618: iload 9
    //   620: invokestatic 277	java/lang/Integer:toString	(I)Ljava/lang/String;
    //   623: ldc -119
    //   625: ldc -119
    //   627: ldc -119
    //   629: invokestatic 282	com/tencent/mobileqq/statistics/ReportController:b	(Lcom/tencent/mobileqq/app/QQAppInterface;Ljava/lang/String;Ljava/lang/String;Ljava/lang/String;Ljava/lang/String;Ljava/lang/String;IILjava/lang/String;Ljava/lang/String;Ljava/lang/String;Ljava/lang/String;)V
    //   632: aload_0
    //   633: getfield 12	tl:a	Lcom/etrump/mixlayout/FontManager;
    //   636: iload 9
    //   638: invokevirtual 285	com/etrump/mixlayout/FontManager:a	(I)V
    //   641: aload 5
    //   643: aload 6
    //   645: aload 7
    //   647: invokeinterface 242 3 0
    //   652: pop
    //   653: aload 5
    //   655: invokeinterface 245 1 0
    //   660: pop
    //   661: goto -481 -> 180
    //   664: astore_1
    //   665: invokestatic 44	com/tencent/qphone/base/util/QLog:isColorLevel	()Z
    //   668: ifeq +32 -> 700
    //   671: ldc 46
    //   673: iconst_2
    //   674: new 153	java/lang/StringBuilder
    //   677: dup
    //   678: invokespecial 154	java/lang/StringBuilder:<init>	()V
    //   681: ldc_w 287
    //   684: invokevirtual 160	java/lang/StringBuilder:append	(Ljava/lang/String;)Ljava/lang/StringBuilder;
    //   687: aload_1
    //   688: invokevirtual 173	java/lang/Exception:getMessage	()Ljava/lang/String;
    //   691: invokevirtual 160	java/lang/StringBuilder:append	(Ljava/lang/String;)Ljava/lang/StringBuilder;
    //   694: invokevirtual 167	java/lang/StringBuilder:toString	()Ljava/lang/String;
    //   697: invokestatic 170	com/tencent/qphone/base/util/QLog:e	(Ljava/lang/String;ILjava/lang/String;)V
    //   700: return
    //   701: invokestatic 44	com/tencent/qphone/base/util/QLog:isColorLevel	()Z
    //   704: ifeq -524 -> 180
    //   707: ldc 46
    //   709: iconst_2
    //   710: new 153	java/lang/StringBuilder
    //   713: dup
    //   714: invokespecial 154	java/lang/StringBuilder:<init>	()V
    //   717: ldc_w 289
    //   720: invokevirtual 160	java/lang/StringBuilder:append	(Ljava/lang/String;)Ljava/lang/StringBuilder;
    //   723: aload 6
    //   725: invokevirtual 160	java/lang/StringBuilder:append	(Ljava/lang/String;)Ljava/lang/StringBuilder;
    //   728: ldc_w 291
    //   731: invokevirtual 160	java/lang/StringBuilder:append	(Ljava/lang/String;)Ljava/lang/StringBuilder;
    //   734: aload_0
    //   735: getfield 12	tl:a	Lcom/etrump/mixlayout/FontManager;
    //   738: getfield 257	com/etrump/mixlayout/FontManager:jdField_a_of_type_JavaUtilConcurrentAtomicAtomicBoolean	Ljava/util/concurrent/atomic/AtomicBoolean;
    //   741: invokevirtual 39	java/util/concurrent/atomic/AtomicBoolean:get	()Z
    //   744: invokevirtual 294	java/lang/StringBuilder:append	(Z)Ljava/lang/StringBuilder;
    //   747: ldc_w 296
    //   750: invokevirtual 160	java/lang/StringBuilder:append	(Ljava/lang/String;)Ljava/lang/StringBuilder;
    //   753: aload_0
    //   754: getfield 12	tl:a	Lcom/etrump/mixlayout/FontManager;
    //   757: getfield 260	com/etrump/mixlayout/FontManager:jdField_a_of_type_ComEtrumpMixlayoutETEngine	Lcom/etrump/mixlayout/ETEngine;
    //   760: iload 9
    //   762: invokevirtual 266	com/etrump/mixlayout/ETEngine:native_isFontLoaded	(I)Z
    //   765: invokevirtual 294	java/lang/StringBuilder:append	(Z)Ljava/lang/StringBuilder;
    //   768: invokevirtual 167	java/lang/StringBuilder:toString	()Ljava/lang/String;
    //   771: invokestatic 52	com/tencent/qphone/base/util/QLog:d	(Ljava/lang/String;ILjava/lang/String;)V
    //   774: goto -594 -> 180
    //   777: iload 10
    //   779: iconst_2
    //   780: if_icmpne -600 -> 180
    //   783: invokestatic 44	com/tencent/qphone/base/util/QLog:isColorLevel	()Z
    //   786: ifeq +30 -> 816
    //   789: ldc 46
    //   791: iconst_2
    //   792: new 153	java/lang/StringBuilder
    //   795: dup
    //   796: invokespecial 154	java/lang/StringBuilder:<init>	()V
    //   799: ldc_w 298
    //   802: invokevirtual 160	java/lang/StringBuilder:append	(Ljava/lang/String;)Ljava/lang/StringBuilder;
    //   805: aload 6
    //   807: invokevirtual 160	java/lang/StringBuilder:append	(Ljava/lang/String;)Ljava/lang/StringBuilder;
    //   810: invokevirtual 167	java/lang/StringBuilder:toString	()Ljava/lang/String;
    //   813: invokestatic 52	com/tencent/qphone/base/util/QLog:d	(Ljava/lang/String;ILjava/lang/String;)V
    //   816: aload_0
    //   817: getfield 12	tl:a	Lcom/etrump/mixlayout/FontManager;
    //   820: getfield 73	com/etrump/mixlayout/FontManager:jdField_a_of_type_ComTencentMobileqqAppQQAppInterface	Lcom/tencent/mobileqq/app/QQAppInterface;
    //   823: ldc_w 270
    //   826: ldc -119
    //   828: ldc -119
    //   830: ldc_w 272
    //   833: ldc_w 274
    //   836: iconst_0
    //   837: iconst_0
    //   838: iload 9
    //   840: invokestatic 277	java/lang/Integer:toString	(I)Ljava/lang/String;
    //   843: ldc -119
    //   845: ldc -119
    //   847: ldc -119
    //   849: invokestatic 282	com/tencent/mobileqq/statistics/ReportController:b	(Lcom/tencent/mobileqq/app/QQAppInterface;Ljava/lang/String;Ljava/lang/String;Ljava/lang/String;Ljava/lang/String;Ljava/lang/String;IILjava/lang/String;Ljava/lang/String;Ljava/lang/String;Ljava/lang/String;)V
    //   852: aload_0
    //   853: getfield 12	tl:a	Lcom/etrump/mixlayout/FontManager;
    //   856: iload 9
    //   858: invokevirtual 285	com/etrump/mixlayout/FontManager:a	(I)V
    //   861: aload 5
    //   863: aload 6
    //   865: aload 7
    //   867: invokeinterface 242 3 0
    //   872: pop
    //   873: aload 5
    //   875: invokeinterface 245 1 0
    //   880: pop
    //   881: goto -701 -> 180
    //   884: invokestatic 44	com/tencent/qphone/base/util/QLog:isColorLevel	()Z
    //   887: ifeq -707 -> 180
    //   890: ldc 46
    //   892: iconst_2
    //   893: new 153	java/lang/StringBuilder
    //   896: dup
    //   897: invokespecial 154	java/lang/StringBuilder:<init>	()V
    //   900: ldc_w 300
    //   903: invokevirtual 160	java/lang/StringBuilder:append	(Ljava/lang/String;)Ljava/lang/StringBuilder;
    //   906: aload 6
    //   908: invokevirtual 160	java/lang/StringBuilder:append	(Ljava/lang/String;)Ljava/lang/StringBuilder;
    //   911: ldc_w 302
    //   914: invokevirtual 160	java/lang/StringBuilder:append	(Ljava/lang/String;)Ljava/lang/StringBuilder;
    //   917: aload_2
    //   918: invokevirtual 160	java/lang/StringBuilder:append	(Ljava/lang/String;)Ljava/lang/StringBuilder;
    //   921: invokevirtual 167	java/lang/StringBuilder:toString	()Ljava/lang/String;
    //   924: invokestatic 52	com/tencent/qphone/base/util/QLog:d	(Ljava/lang/String;ILjava/lang/String;)V
    //   927: goto -747 -> 180
    //   930: invokestatic 44	com/tencent/qphone/base/util/QLog:isColorLevel	()Z
    //   933: ifeq -753 -> 180
    //   936: ldc 46
    //   938: iconst_2
    //   939: new 153	java/lang/StringBuilder
    //   942: dup
    //   943: invokespecial 154	java/lang/StringBuilder:<init>	()V
    //   946: ldc_w 304
    //   949: invokevirtual 160	java/lang/StringBuilder:append	(Ljava/lang/String;)Ljava/lang/StringBuilder;
    //   952: aload 6
    //   954: invokevirtual 160	java/lang/StringBuilder:append	(Ljava/lang/String;)Ljava/lang/StringBuilder;
    //   957: invokevirtual 167	java/lang/StringBuilder:toString	()Ljava/lang/String;
    //   960: invokestatic 52	com/tencent/qphone/base/util/QLog:d	(Ljava/lang/String;ILjava/lang/String;)V
    //   963: goto -783 -> 180
    //   966: invokestatic 44	com/tencent/qphone/base/util/QLog:isColorLevel	()Z
    //   969: ifeq +12 -> 981
    //   972: ldc 46
    //   974: iconst_2
    //   975: ldc_w 306
    //   978: invokestatic 52	com/tencent/qphone/base/util/QLog:d	(Ljava/lang/String;ILjava/lang/String;)V
    //   981: aload_0
    //   982: getfield 12	tl:a	Lcom/etrump/mixlayout/FontManager;
    //   985: getfield 73	com/etrump/mixlayout/FontManager:jdField_a_of_type_ComTencentMobileqqAppQQAppInterface	Lcom/tencent/mobileqq/app/QQAppInterface;
    //   988: getstatic 65	com/tencent/mobileqq/vas/ClubContentJsonTask:n	Lcom/tencent/mobileqq/vas/ClubContentJsonTask$TaskInfo;
    //   991: invokestatic 309	com/tencent/mobileqq/vas/ClubContentJsonTask:b	(Lcom/tencent/mobileqq/app/QQAppInterface;Lcom/tencent/mobileqq/vas/ClubContentJsonTask$TaskInfo;)V
    //   994: return
    // Local variable table:
    //   start	length	slot	name	signature
    //   0	995	0	this	tl
    //   69	73	1	localObject1	Object
    //   189	27	1	localOutOfMemoryError	OutOfMemoryError
    //   229	1	1	localObject2	Object
    //   233	27	1	localException1	Exception
    //   273	1	1	localObject3	Object
    //   664	24	1	localException2	Exception
    //   44	874	2	localObject4	Object
    //   336	132	3	localObject5	Object
    //   118	208	4	localSharedPreferences	android.content.SharedPreferences
    //   127	747	5	localEditor	android.content.SharedPreferences.Editor
    //   156	797	6	str1	String
    //   315	551	7	str2	String
    //   130	55	8	i	int
    //   282	575	9	j	int
    //   305	476	10	k	int
    //   173	3	11	bool	boolean
    // Exception table:
    //   from	to	target	type
    //   77	82	189	java/lang/OutOfMemoryError
    //   89	98	233	java/lang/Exception
    //   102	129	664	java/lang/Exception
    //   132	175	664	java/lang/Exception
    //   277	337	664	java/lang/Exception
    //   339	424	664	java/lang/Exception
    //   426	467	664	java/lang/Exception
    //   469	529	664	java/lang/Exception
    //   535	563	664	java/lang/Exception
    //   563	596	664	java/lang/Exception
    //   596	661	664	java/lang/Exception
    //   701	774	664	java/lang/Exception
    //   783	816	664	java/lang/Exception
    //   816	881	664	java/lang/Exception
    //   884	927	664	java/lang/Exception
    //   930	963	664	java/lang/Exception
  }
}


/* Location:              E:\apk\QQ_91\classes2-dex2jar.jar!\tl.class
 * Java compiler version: 6 (50.0)
 * JD-Core Version:       0.7.1
 */