import com.tencent.mobileqq.hotpatch.NotVerifyClass;
import cooperation.troop_homework.jsp.TroopHWJsPlugin;

public class ytv
  implements Runnable
{
  public ytv(TroopHWJsPlugin paramTroopHWJsPlugin, String paramString)
  {
    boolean bool = NotVerifyClass.DO_VERIFY_CLASS;
  }
  
  /* Error */
  public void run()
  {
    // Byte code:
    //   0: new 32	java/io/FileInputStream
    //   3: dup
    //   4: aload_0
    //   5: getfield 15	ytv:jdField_a_of_type_JavaLangString	Ljava/lang/String;
    //   8: invokespecial 35	java/io/FileInputStream:<init>	(Ljava/lang/String;)V
    //   11: astore_2
    //   12: aload_2
    //   13: astore_1
    //   14: new 37	java/lang/StringBuilder
    //   17: dup
    //   18: invokespecial 38	java/lang/StringBuilder:<init>	()V
    //   21: astore_3
    //   22: aload_2
    //   23: astore_1
    //   24: sipush 30720
    //   27: newarray <illegal type>
    //   29: astore 4
    //   31: aload_2
    //   32: astore_1
    //   33: aload_2
    //   34: aload 4
    //   36: invokevirtual 42	java/io/FileInputStream:read	([B)I
    //   39: istore 6
    //   41: iload 6
    //   43: iconst_m1
    //   44: if_icmpeq +184 -> 228
    //   47: iload 6
    //   49: sipush 30720
    //   52: if_icmpge +97 -> 149
    //   55: aload_2
    //   56: astore_1
    //   57: iload 6
    //   59: newarray <illegal type>
    //   61: astore 5
    //   63: aload_2
    //   64: astore_1
    //   65: aload 4
    //   67: iconst_0
    //   68: aload 5
    //   70: iconst_0
    //   71: iload 6
    //   73: invokestatic 48	java/lang/System:arraycopy	(Ljava/lang/Object;ILjava/lang/Object;II)V
    //   76: aload_2
    //   77: astore_1
    //   78: aload_3
    //   79: aload 5
    //   81: iconst_2
    //   82: invokestatic 54	com/tencent/mobileqq/utils/Base64Util:encodeToString	([BI)Ljava/lang/String;
    //   85: invokevirtual 58	java/lang/StringBuilder:append	(Ljava/lang/String;)Ljava/lang/StringBuilder;
    //   88: pop
    //   89: goto -58 -> 31
    //   92: astore_3
    //   93: aload_2
    //   94: astore_1
    //   95: aload_3
    //   96: invokevirtual 61	java/io/FileNotFoundException:printStackTrace	()V
    //   99: new 63	org/json/JSONObject
    //   102: dup
    //   103: invokespecial 64	org/json/JSONObject:<init>	()V
    //   106: astore_1
    //   107: aload_1
    //   108: ldc 66
    //   110: aconst_null
    //   111: invokevirtual 70	org/json/JSONObject:put	(Ljava/lang/String;Ljava/lang/Object;)Lorg/json/JSONObject;
    //   114: pop
    //   115: aload_0
    //   116: getfield 13	ytv:jdField_a_of_type_CooperationTroop_homeworkJspTroopHWJsPlugin	Lcooperation/troop_homework/jsp/TroopHWJsPlugin;
    //   119: aload_0
    //   120: getfield 13	ytv:jdField_a_of_type_CooperationTroop_homeworkJspTroopHWJsPlugin	Lcooperation/troop_homework/jsp/TroopHWJsPlugin;
    //   123: getfield 75	cooperation/troop_homework/jsp/TroopHWJsPlugin:f	Ljava/lang/String;
    //   126: iconst_1
    //   127: anewarray 77	java/lang/String
    //   130: dup
    //   131: iconst_0
    //   132: aload_1
    //   133: invokevirtual 81	org/json/JSONObject:toString	()Ljava/lang/String;
    //   136: aastore
    //   137: invokevirtual 85	cooperation/troop_homework/jsp/TroopHWJsPlugin:callJs	(Ljava/lang/String;[Ljava/lang/String;)V
    //   140: aload_2
    //   141: ifnull +7 -> 148
    //   144: aload_2
    //   145: invokevirtual 88	java/io/FileInputStream:close	()V
    //   148: return
    //   149: aload_2
    //   150: astore_1
    //   151: aload_3
    //   152: aload 4
    //   154: iconst_2
    //   155: invokestatic 54	com/tencent/mobileqq/utils/Base64Util:encodeToString	([BI)Ljava/lang/String;
    //   158: invokevirtual 58	java/lang/StringBuilder:append	(Ljava/lang/String;)Ljava/lang/StringBuilder;
    //   161: pop
    //   162: goto -131 -> 31
    //   165: astore_3
    //   166: aload_2
    //   167: astore_1
    //   168: aload_3
    //   169: invokevirtual 89	java/lang/Exception:printStackTrace	()V
    //   172: new 63	org/json/JSONObject
    //   175: dup
    //   176: invokespecial 64	org/json/JSONObject:<init>	()V
    //   179: astore_1
    //   180: aload_1
    //   181: ldc 66
    //   183: aconst_null
    //   184: invokevirtual 70	org/json/JSONObject:put	(Ljava/lang/String;Ljava/lang/Object;)Lorg/json/JSONObject;
    //   187: pop
    //   188: aload_0
    //   189: getfield 13	ytv:jdField_a_of_type_CooperationTroop_homeworkJspTroopHWJsPlugin	Lcooperation/troop_homework/jsp/TroopHWJsPlugin;
    //   192: aload_0
    //   193: getfield 13	ytv:jdField_a_of_type_CooperationTroop_homeworkJspTroopHWJsPlugin	Lcooperation/troop_homework/jsp/TroopHWJsPlugin;
    //   196: getfield 75	cooperation/troop_homework/jsp/TroopHWJsPlugin:f	Ljava/lang/String;
    //   199: iconst_1
    //   200: anewarray 77	java/lang/String
    //   203: dup
    //   204: iconst_0
    //   205: aload_1
    //   206: invokevirtual 81	org/json/JSONObject:toString	()Ljava/lang/String;
    //   209: aastore
    //   210: invokevirtual 85	cooperation/troop_homework/jsp/TroopHWJsPlugin:callJs	(Ljava/lang/String;[Ljava/lang/String;)V
    //   213: aload_2
    //   214: ifnull -66 -> 148
    //   217: aload_2
    //   218: invokevirtual 88	java/io/FileInputStream:close	()V
    //   221: return
    //   222: astore_1
    //   223: aload_1
    //   224: invokevirtual 89	java/lang/Exception:printStackTrace	()V
    //   227: return
    //   228: aload_2
    //   229: astore_1
    //   230: aload_3
    //   231: invokevirtual 90	java/lang/StringBuilder:toString	()Ljava/lang/String;
    //   234: astore_3
    //   235: new 63	org/json/JSONObject
    //   238: dup
    //   239: invokespecial 64	org/json/JSONObject:<init>	()V
    //   242: astore_1
    //   243: aload_1
    //   244: ldc 66
    //   246: aload_3
    //   247: invokevirtual 70	org/json/JSONObject:put	(Ljava/lang/String;Ljava/lang/Object;)Lorg/json/JSONObject;
    //   250: pop
    //   251: aload_0
    //   252: getfield 13	ytv:jdField_a_of_type_CooperationTroop_homeworkJspTroopHWJsPlugin	Lcooperation/troop_homework/jsp/TroopHWJsPlugin;
    //   255: aload_0
    //   256: getfield 13	ytv:jdField_a_of_type_CooperationTroop_homeworkJspTroopHWJsPlugin	Lcooperation/troop_homework/jsp/TroopHWJsPlugin;
    //   259: getfield 75	cooperation/troop_homework/jsp/TroopHWJsPlugin:f	Ljava/lang/String;
    //   262: iconst_1
    //   263: anewarray 77	java/lang/String
    //   266: dup
    //   267: iconst_0
    //   268: aload_1
    //   269: invokevirtual 81	org/json/JSONObject:toString	()Ljava/lang/String;
    //   272: aastore
    //   273: invokevirtual 85	cooperation/troop_homework/jsp/TroopHWJsPlugin:callJs	(Ljava/lang/String;[Ljava/lang/String;)V
    //   276: aload_2
    //   277: ifnull -129 -> 148
    //   280: aload_2
    //   281: invokevirtual 88	java/io/FileInputStream:close	()V
    //   284: return
    //   285: astore_1
    //   286: aload_1
    //   287: invokevirtual 89	java/lang/Exception:printStackTrace	()V
    //   290: return
    //   291: astore_3
    //   292: aload_3
    //   293: invokevirtual 89	java/lang/Exception:printStackTrace	()V
    //   296: goto -45 -> 251
    //   299: astore_3
    //   300: aload_3
    //   301: invokevirtual 89	java/lang/Exception:printStackTrace	()V
    //   304: goto -189 -> 115
    //   307: astore_1
    //   308: aload_1
    //   309: invokevirtual 89	java/lang/Exception:printStackTrace	()V
    //   312: return
    //   313: astore_3
    //   314: aload_3
    //   315: invokevirtual 89	java/lang/Exception:printStackTrace	()V
    //   318: goto -130 -> 188
    //   321: astore_2
    //   322: aconst_null
    //   323: astore_1
    //   324: new 63	org/json/JSONObject
    //   327: dup
    //   328: invokespecial 64	org/json/JSONObject:<init>	()V
    //   331: astore_3
    //   332: aload_3
    //   333: ldc 66
    //   335: aconst_null
    //   336: invokevirtual 70	org/json/JSONObject:put	(Ljava/lang/String;Ljava/lang/Object;)Lorg/json/JSONObject;
    //   339: pop
    //   340: aload_0
    //   341: getfield 13	ytv:jdField_a_of_type_CooperationTroop_homeworkJspTroopHWJsPlugin	Lcooperation/troop_homework/jsp/TroopHWJsPlugin;
    //   344: aload_0
    //   345: getfield 13	ytv:jdField_a_of_type_CooperationTroop_homeworkJspTroopHWJsPlugin	Lcooperation/troop_homework/jsp/TroopHWJsPlugin;
    //   348: getfield 75	cooperation/troop_homework/jsp/TroopHWJsPlugin:f	Ljava/lang/String;
    //   351: iconst_1
    //   352: anewarray 77	java/lang/String
    //   355: dup
    //   356: iconst_0
    //   357: aload_3
    //   358: invokevirtual 81	org/json/JSONObject:toString	()Ljava/lang/String;
    //   361: aastore
    //   362: invokevirtual 85	cooperation/troop_homework/jsp/TroopHWJsPlugin:callJs	(Ljava/lang/String;[Ljava/lang/String;)V
    //   365: aload_1
    //   366: ifnull +7 -> 373
    //   369: aload_1
    //   370: invokevirtual 88	java/io/FileInputStream:close	()V
    //   373: aload_2
    //   374: athrow
    //   375: astore 4
    //   377: aload 4
    //   379: invokevirtual 89	java/lang/Exception:printStackTrace	()V
    //   382: goto -42 -> 340
    //   385: astore_1
    //   386: aload_1
    //   387: invokevirtual 89	java/lang/Exception:printStackTrace	()V
    //   390: goto -17 -> 373
    //   393: astore_2
    //   394: goto -70 -> 324
    //   397: astore_3
    //   398: aconst_null
    //   399: astore_2
    //   400: goto -234 -> 166
    //   403: astore_3
    //   404: aconst_null
    //   405: astore_2
    //   406: goto -313 -> 93
    // Local variable table:
    //   start	length	slot	name	signature
    //   0	409	0	this	ytv
    //   13	193	1	localObject1	Object
    //   222	2	1	localException1	Exception
    //   229	40	1	localObject2	Object
    //   285	2	1	localException2	Exception
    //   307	2	1	localException3	Exception
    //   323	47	1	localObject3	Object
    //   385	2	1	localException4	Exception
    //   11	270	2	localFileInputStream	java.io.FileInputStream
    //   321	53	2	localObject4	Object
    //   393	1	2	localObject5	Object
    //   399	7	2	localObject6	Object
    //   21	58	3	localStringBuilder	StringBuilder
    //   92	60	3	localFileNotFoundException1	java.io.FileNotFoundException
    //   165	66	3	localException5	Exception
    //   234	13	3	str	String
    //   291	2	3	localException6	Exception
    //   299	2	3	localException7	Exception
    //   313	2	3	localException8	Exception
    //   331	27	3	localJSONObject	org.json.JSONObject
    //   397	1	3	localException9	Exception
    //   403	1	3	localFileNotFoundException2	java.io.FileNotFoundException
    //   29	124	4	arrayOfByte1	byte[]
    //   375	3	4	localException10	Exception
    //   61	19	5	arrayOfByte2	byte[]
    //   39	33	6	i	int
    // Exception table:
    //   from	to	target	type
    //   14	22	92	java/io/FileNotFoundException
    //   24	31	92	java/io/FileNotFoundException
    //   33	41	92	java/io/FileNotFoundException
    //   57	63	92	java/io/FileNotFoundException
    //   65	76	92	java/io/FileNotFoundException
    //   78	89	92	java/io/FileNotFoundException
    //   151	162	92	java/io/FileNotFoundException
    //   230	235	92	java/io/FileNotFoundException
    //   14	22	165	java/lang/Exception
    //   24	31	165	java/lang/Exception
    //   33	41	165	java/lang/Exception
    //   57	63	165	java/lang/Exception
    //   65	76	165	java/lang/Exception
    //   78	89	165	java/lang/Exception
    //   151	162	165	java/lang/Exception
    //   230	235	165	java/lang/Exception
    //   217	221	222	java/lang/Exception
    //   280	284	285	java/lang/Exception
    //   243	251	291	java/lang/Exception
    //   107	115	299	java/lang/Exception
    //   144	148	307	java/lang/Exception
    //   180	188	313	java/lang/Exception
    //   0	12	321	finally
    //   332	340	375	java/lang/Exception
    //   369	373	385	java/lang/Exception
    //   14	22	393	finally
    //   24	31	393	finally
    //   33	41	393	finally
    //   57	63	393	finally
    //   65	76	393	finally
    //   78	89	393	finally
    //   95	99	393	finally
    //   151	162	393	finally
    //   168	172	393	finally
    //   230	235	393	finally
    //   0	12	397	java/lang/Exception
    //   0	12	403	java/io/FileNotFoundException
  }
}


/* Location:              E:\apk\QQ_91\classes2-dex2jar.jar!\ytv.class
 * Java compiler version: 6 (50.0)
 * JD-Core Version:       0.7.1
 */