package com.tencent.mobileqq.unifiedebug;

import com.tencent.mobileqq.hotpatch.NotVerifyClass;

public class UnifiedCommandUtil
{
  public static final String a;
  public static final String b = "sh";
  public static final String c = "\n";
  public static final String d = "exit\n";
  
  static
  {
    boolean bool = NotVerifyClass.DO_VERIFY_CLASS;
    jdField_a_of_type_JavaLangString = UnifiedCommandUtil.class.getSimpleName();
  }
  
  public static UnifiedCommandUtil.ExecResult a(String paramString)
  {
    return a(new String[] { paramString });
  }
  
  /* Error */
  public static UnifiedCommandUtil.ExecResult a(String[] paramArrayOfString)
  {
    // Byte code:
    //   0: new 47	com/tencent/mobileqq/unifiedebug/UnifiedCommandUtil$ExecResult
    //   3: dup
    //   4: invokespecial 48	com/tencent/mobileqq/unifiedebug/UnifiedCommandUtil$ExecResult:<init>	()V
    //   7: astore 13
    //   9: aload_0
    //   10: ifnull +8 -> 18
    //   13: aload_0
    //   14: arraylength
    //   15: ifne +12 -> 27
    //   18: aload 13
    //   20: iconst_0
    //   21: putfield 50	com/tencent/mobileqq/unifiedebug/UnifiedCommandUtil$ExecResult:jdField_a_of_type_Boolean	Z
    //   24: aload 13
    //   26: areturn
    //   27: invokestatic 56	com/tencent/qphone/base/util/QLog:isColorLevel	()Z
    //   30: ifeq +29 -> 59
    //   33: getstatic 31	com/tencent/mobileqq/unifiedebug/UnifiedCommandUtil:jdField_a_of_type_JavaLangString	Ljava/lang/String;
    //   36: iconst_2
    //   37: new 58	java/lang/StringBuilder
    //   40: dup
    //   41: invokespecial 59	java/lang/StringBuilder:<init>	()V
    //   44: ldc 61
    //   46: invokevirtual 65	java/lang/StringBuilder:append	(Ljava/lang/String;)Ljava/lang/StringBuilder;
    //   49: aload_0
    //   50: invokevirtual 68	java/lang/StringBuilder:append	(Ljava/lang/Object;)Ljava/lang/StringBuilder;
    //   53: invokevirtual 71	java/lang/StringBuilder:toString	()Ljava/lang/String;
    //   56: invokestatic 74	com/tencent/qphone/base/util/QLog:d	(Ljava/lang/String;ILjava/lang/String;)V
    //   59: aconst_null
    //   60: astore 6
    //   62: aconst_null
    //   63: astore 11
    //   65: aconst_null
    //   66: astore_3
    //   67: aconst_null
    //   68: astore 10
    //   70: aconst_null
    //   71: astore 12
    //   73: aconst_null
    //   74: astore 9
    //   76: new 76	java/util/ArrayList
    //   79: dup
    //   80: invokespecial 77	java/util/ArrayList:<init>	()V
    //   83: astore 14
    //   85: invokestatic 83	java/lang/Runtime:getRuntime	()Ljava/lang/Runtime;
    //   88: ldc 9
    //   90: invokevirtual 87	java/lang/Runtime:exec	(Ljava/lang/String;)Ljava/lang/Process;
    //   93: astore_1
    //   94: new 89	java/io/DataOutputStream
    //   97: dup
    //   98: aload_1
    //   99: invokevirtual 95	java/lang/Process:getOutputStream	()Ljava/io/OutputStream;
    //   102: invokespecial 98	java/io/DataOutputStream:<init>	(Ljava/io/OutputStream;)V
    //   105: astore 5
    //   107: aload 5
    //   109: astore 8
    //   111: aload 12
    //   113: astore 4
    //   115: aload 11
    //   117: astore 7
    //   119: aload_1
    //   120: astore 6
    //   122: aload_0
    //   123: arraylength
    //   124: istore 16
    //   126: iconst_0
    //   127: istore 15
    //   129: goto +877 -> 1006
    //   132: aload 5
    //   134: astore 8
    //   136: aload 12
    //   138: astore 4
    //   140: aload 11
    //   142: astore 7
    //   144: aload_1
    //   145: astore 6
    //   147: aload 5
    //   149: aload_2
    //   150: invokevirtual 102	java/lang/String:getBytes	()[B
    //   153: invokevirtual 106	java/io/DataOutputStream:write	([B)V
    //   156: aload 5
    //   158: astore 8
    //   160: aload 12
    //   162: astore 4
    //   164: aload 11
    //   166: astore 7
    //   168: aload_1
    //   169: astore 6
    //   171: aload 5
    //   173: ldc 12
    //   175: invokevirtual 110	java/io/DataOutputStream:writeBytes	(Ljava/lang/String;)V
    //   178: aload 5
    //   180: astore 8
    //   182: aload 12
    //   184: astore 4
    //   186: aload 11
    //   188: astore 7
    //   190: aload_1
    //   191: astore 6
    //   193: aload 5
    //   195: invokevirtual 113	java/io/DataOutputStream:flush	()V
    //   198: goto +824 -> 1022
    //   201: astore_3
    //   202: iconst_m1
    //   203: istore 15
    //   205: aconst_null
    //   206: astore 4
    //   208: aconst_null
    //   209: astore_0
    //   210: aconst_null
    //   211: astore 6
    //   213: aload_1
    //   214: astore_2
    //   215: aload 6
    //   217: astore_1
    //   218: aload_3
    //   219: invokevirtual 116	java/io/IOException:printStackTrace	()V
    //   222: aload 5
    //   224: ifnull +8 -> 232
    //   227: aload 5
    //   229: invokevirtual 119	java/io/DataOutputStream:close	()V
    //   232: aload_1
    //   233: ifnull +7 -> 240
    //   236: aload_1
    //   237: invokevirtual 122	java/io/BufferedReader:close	()V
    //   240: aload_0
    //   241: ifnull +7 -> 248
    //   244: aload_0
    //   245: invokevirtual 122	java/io/BufferedReader:close	()V
    //   248: iload 15
    //   250: istore 16
    //   252: aload 4
    //   254: astore_0
    //   255: aload_2
    //   256: ifnull +14 -> 270
    //   259: aload_2
    //   260: invokevirtual 125	java/lang/Process:destroy	()V
    //   263: aload 4
    //   265: astore_0
    //   266: iload 15
    //   268: istore 16
    //   270: invokestatic 56	com/tencent/qphone/base/util/QLog:isColorLevel	()Z
    //   273: ifeq +34 -> 307
    //   276: getstatic 31	com/tencent/mobileqq/unifiedebug/UnifiedCommandUtil:jdField_a_of_type_JavaLangString	Ljava/lang/String;
    //   279: iconst_2
    //   280: getstatic 131	java/util/Locale:CHINA	Ljava/util/Locale;
    //   283: ldc -123
    //   285: iconst_2
    //   286: anewarray 4	java/lang/Object
    //   289: dup
    //   290: iconst_0
    //   291: aload_0
    //   292: aastore
    //   293: dup
    //   294: iconst_1
    //   295: iload 16
    //   297: invokestatic 139	java/lang/Integer:valueOf	(I)Ljava/lang/Integer;
    //   300: aastore
    //   301: invokestatic 143	java/lang/String:format	(Ljava/util/Locale;Ljava/lang/String;[Ljava/lang/Object;)Ljava/lang/String;
    //   304: invokestatic 74	com/tencent/qphone/base/util/QLog:d	(Ljava/lang/String;ILjava/lang/String;)V
    //   307: iload 16
    //   309: ifne +459 -> 768
    //   312: iconst_1
    //   313: istore 17
    //   315: aload 13
    //   317: iload 17
    //   319: putfield 50	com/tencent/mobileqq/unifiedebug/UnifiedCommandUtil$ExecResult:jdField_a_of_type_Boolean	Z
    //   322: aload 13
    //   324: aload 14
    //   326: putfield 146	com/tencent/mobileqq/unifiedebug/UnifiedCommandUtil$ExecResult:jdField_a_of_type_JavaUtilList	Ljava/util/List;
    //   329: aload_0
    //   330: ifnull +12 -> 342
    //   333: aload 13
    //   335: aload_0
    //   336: invokevirtual 71	java/lang/StringBuilder:toString	()Ljava/lang/String;
    //   339: putfield 147	com/tencent/mobileqq/unifiedebug/UnifiedCommandUtil$ExecResult:jdField_a_of_type_JavaLangString	Ljava/lang/String;
    //   342: aload 13
    //   344: areturn
    //   345: aload 5
    //   347: astore 8
    //   349: aload 12
    //   351: astore 4
    //   353: aload 11
    //   355: astore 7
    //   357: aload_1
    //   358: astore 6
    //   360: aload 5
    //   362: ldc 15
    //   364: invokevirtual 110	java/io/DataOutputStream:writeBytes	(Ljava/lang/String;)V
    //   367: aload 5
    //   369: astore 8
    //   371: aload 12
    //   373: astore 4
    //   375: aload 11
    //   377: astore 7
    //   379: aload_1
    //   380: astore 6
    //   382: aload 5
    //   384: invokevirtual 113	java/io/DataOutputStream:flush	()V
    //   387: aload 5
    //   389: astore 8
    //   391: aload 12
    //   393: astore 4
    //   395: aload 11
    //   397: astore 7
    //   399: aload_1
    //   400: astore 6
    //   402: aload_1
    //   403: invokevirtual 151	java/lang/Process:waitFor	()I
    //   406: istore 15
    //   408: aload 5
    //   410: astore 8
    //   412: aload 12
    //   414: astore 4
    //   416: aload 11
    //   418: astore 7
    //   420: aload_1
    //   421: astore 6
    //   423: new 58	java/lang/StringBuilder
    //   426: dup
    //   427: invokespecial 59	java/lang/StringBuilder:<init>	()V
    //   430: astore_2
    //   431: aload 5
    //   433: astore 8
    //   435: aload 12
    //   437: astore 4
    //   439: aload 11
    //   441: astore 7
    //   443: aload_1
    //   444: astore 6
    //   446: new 121	java/io/BufferedReader
    //   449: dup
    //   450: new 153	java/io/InputStreamReader
    //   453: dup
    //   454: aload_1
    //   455: invokevirtual 157	java/lang/Process:getInputStream	()Ljava/io/InputStream;
    //   458: invokespecial 160	java/io/InputStreamReader:<init>	(Ljava/io/InputStream;)V
    //   461: invokespecial 163	java/io/BufferedReader:<init>	(Ljava/io/Reader;)V
    //   464: astore_0
    //   465: new 121	java/io/BufferedReader
    //   468: dup
    //   469: new 153	java/io/InputStreamReader
    //   472: dup
    //   473: aload_1
    //   474: invokevirtual 166	java/lang/Process:getErrorStream	()Ljava/io/InputStream;
    //   477: invokespecial 160	java/io/InputStreamReader:<init>	(Ljava/io/InputStream;)V
    //   480: invokespecial 163	java/io/BufferedReader:<init>	(Ljava/io/Reader;)V
    //   483: astore 6
    //   485: aload_0
    //   486: invokevirtual 169	java/io/BufferedReader:readLine	()Ljava/lang/String;
    //   489: astore_3
    //   490: aload_3
    //   491: ifnull +47 -> 538
    //   494: aload 14
    //   496: aload_3
    //   497: invokeinterface 175 2 0
    //   502: pop
    //   503: invokestatic 56	com/tencent/qphone/base/util/QLog:isColorLevel	()Z
    //   506: ifeq -21 -> 485
    //   509: getstatic 31	com/tencent/mobileqq/unifiedebug/UnifiedCommandUtil:jdField_a_of_type_JavaLangString	Ljava/lang/String;
    //   512: iconst_2
    //   513: new 58	java/lang/StringBuilder
    //   516: dup
    //   517: invokespecial 59	java/lang/StringBuilder:<init>	()V
    //   520: ldc -79
    //   522: invokevirtual 65	java/lang/StringBuilder:append	(Ljava/lang/String;)Ljava/lang/StringBuilder;
    //   525: aload_3
    //   526: invokevirtual 65	java/lang/StringBuilder:append	(Ljava/lang/String;)Ljava/lang/StringBuilder;
    //   529: invokevirtual 71	java/lang/StringBuilder:toString	()Ljava/lang/String;
    //   532: invokestatic 74	com/tencent/qphone/base/util/QLog:d	(Ljava/lang/String;ILjava/lang/String;)V
    //   535: goto -50 -> 485
    //   538: aload 6
    //   540: invokevirtual 169	java/io/BufferedReader:readLine	()Ljava/lang/String;
    //   543: astore_3
    //   544: aload_3
    //   545: ifnull +92 -> 637
    //   548: aload_2
    //   549: aload_3
    //   550: invokevirtual 65	java/lang/StringBuilder:append	(Ljava/lang/String;)Ljava/lang/StringBuilder;
    //   553: pop
    //   554: goto -16 -> 538
    //   557: astore 4
    //   559: aload_0
    //   560: astore_3
    //   561: aload 6
    //   563: astore 9
    //   565: aload 4
    //   567: astore_0
    //   568: aload 5
    //   570: astore 8
    //   572: aload 9
    //   574: astore 4
    //   576: aload_3
    //   577: astore 7
    //   579: aload_1
    //   580: astore 6
    //   582: aload_0
    //   583: invokevirtual 178	java/lang/Exception:printStackTrace	()V
    //   586: aload 5
    //   588: ifnull +8 -> 596
    //   591: aload 5
    //   593: invokevirtual 119	java/io/DataOutputStream:close	()V
    //   596: aload_3
    //   597: ifnull +7 -> 604
    //   600: aload_3
    //   601: invokevirtual 122	java/io/BufferedReader:close	()V
    //   604: aload 9
    //   606: ifnull +8 -> 614
    //   609: aload 9
    //   611: invokevirtual 122	java/io/BufferedReader:close	()V
    //   614: iload 15
    //   616: istore 16
    //   618: aload_2
    //   619: astore_0
    //   620: aload_1
    //   621: ifnull -351 -> 270
    //   624: aload_1
    //   625: invokevirtual 125	java/lang/Process:destroy	()V
    //   628: iload 15
    //   630: istore 16
    //   632: aload_2
    //   633: astore_0
    //   634: goto -364 -> 270
    //   637: aload 5
    //   639: ifnull +8 -> 647
    //   642: aload 5
    //   644: invokevirtual 119	java/io/DataOutputStream:close	()V
    //   647: aload_0
    //   648: ifnull +7 -> 655
    //   651: aload_0
    //   652: invokevirtual 122	java/io/BufferedReader:close	()V
    //   655: aload 6
    //   657: ifnull +8 -> 665
    //   660: aload 6
    //   662: invokevirtual 122	java/io/BufferedReader:close	()V
    //   665: iload 15
    //   667: istore 16
    //   669: aload_2
    //   670: astore_0
    //   671: aload_1
    //   672: ifnull -402 -> 270
    //   675: aload_1
    //   676: invokevirtual 125	java/lang/Process:destroy	()V
    //   679: iload 15
    //   681: istore 16
    //   683: aload_2
    //   684: astore_0
    //   685: goto -415 -> 270
    //   688: astore_0
    //   689: aload_0
    //   690: invokevirtual 116	java/io/IOException:printStackTrace	()V
    //   693: goto -28 -> 665
    //   696: astore_0
    //   697: aload_0
    //   698: invokevirtual 116	java/io/IOException:printStackTrace	()V
    //   701: goto -453 -> 248
    //   704: astore_0
    //   705: aload_0
    //   706: invokevirtual 116	java/io/IOException:printStackTrace	()V
    //   709: goto -95 -> 614
    //   712: astore_0
    //   713: aconst_null
    //   714: astore_1
    //   715: aconst_null
    //   716: astore_2
    //   717: aload 6
    //   719: astore_3
    //   720: aload 10
    //   722: astore 4
    //   724: aload_2
    //   725: ifnull +7 -> 732
    //   728: aload_2
    //   729: invokevirtual 119	java/io/DataOutputStream:close	()V
    //   732: aload_3
    //   733: ifnull +7 -> 740
    //   736: aload_3
    //   737: invokevirtual 122	java/io/BufferedReader:close	()V
    //   740: aload 4
    //   742: ifnull +8 -> 750
    //   745: aload 4
    //   747: invokevirtual 122	java/io/BufferedReader:close	()V
    //   750: aload_1
    //   751: ifnull +7 -> 758
    //   754: aload_1
    //   755: invokevirtual 125	java/lang/Process:destroy	()V
    //   758: aload_0
    //   759: athrow
    //   760: astore_2
    //   761: aload_2
    //   762: invokevirtual 116	java/io/IOException:printStackTrace	()V
    //   765: goto -15 -> 750
    //   768: iconst_0
    //   769: istore 17
    //   771: goto -456 -> 315
    //   774: astore_0
    //   775: aconst_null
    //   776: astore_2
    //   777: aload 10
    //   779: astore 4
    //   781: aload 6
    //   783: astore_3
    //   784: goto -60 -> 724
    //   787: astore_0
    //   788: aload 8
    //   790: astore_2
    //   791: aload 7
    //   793: astore_3
    //   794: aload 6
    //   796: astore_1
    //   797: goto -73 -> 724
    //   800: astore_2
    //   801: aload_0
    //   802: astore_3
    //   803: aload_2
    //   804: astore_0
    //   805: aload 5
    //   807: astore_2
    //   808: aload 10
    //   810: astore 4
    //   812: goto -88 -> 724
    //   815: astore_2
    //   816: aload 6
    //   818: astore 4
    //   820: aload_0
    //   821: astore_3
    //   822: aload_2
    //   823: astore_0
    //   824: aload 5
    //   826: astore_2
    //   827: goto -103 -> 724
    //   830: astore_3
    //   831: aload_2
    //   832: astore 6
    //   834: aload_0
    //   835: astore 4
    //   837: aload_3
    //   838: astore_0
    //   839: aload 5
    //   841: astore_2
    //   842: aload_1
    //   843: astore_3
    //   844: aload 6
    //   846: astore_1
    //   847: goto -123 -> 724
    //   850: astore_0
    //   851: aconst_null
    //   852: astore_1
    //   853: aconst_null
    //   854: astore 5
    //   856: iconst_m1
    //   857: istore 15
    //   859: aconst_null
    //   860: astore_2
    //   861: goto -293 -> 568
    //   864: astore_0
    //   865: aconst_null
    //   866: astore 5
    //   868: iconst_m1
    //   869: istore 15
    //   871: aconst_null
    //   872: astore_2
    //   873: goto -305 -> 568
    //   876: astore_0
    //   877: iconst_m1
    //   878: istore 15
    //   880: aconst_null
    //   881: astore_2
    //   882: goto -314 -> 568
    //   885: astore_0
    //   886: aconst_null
    //   887: astore_2
    //   888: goto -320 -> 568
    //   891: astore_0
    //   892: goto -324 -> 568
    //   895: astore 4
    //   897: aload_0
    //   898: astore_3
    //   899: aload 4
    //   901: astore_0
    //   902: goto -334 -> 568
    //   905: astore_3
    //   906: iconst_m1
    //   907: istore 15
    //   909: aconst_null
    //   910: astore 4
    //   912: aconst_null
    //   913: astore_0
    //   914: aconst_null
    //   915: astore_1
    //   916: aconst_null
    //   917: astore_2
    //   918: aconst_null
    //   919: astore 5
    //   921: goto -703 -> 218
    //   924: astore_3
    //   925: aconst_null
    //   926: astore 5
    //   928: iconst_m1
    //   929: istore 15
    //   931: aconst_null
    //   932: astore 4
    //   934: aconst_null
    //   935: astore_0
    //   936: aconst_null
    //   937: astore 6
    //   939: aload_1
    //   940: astore_2
    //   941: aload 6
    //   943: astore_1
    //   944: goto -726 -> 218
    //   947: astore_3
    //   948: aconst_null
    //   949: astore 4
    //   951: aconst_null
    //   952: astore_0
    //   953: aconst_null
    //   954: astore 6
    //   956: aload_1
    //   957: astore_2
    //   958: aload 6
    //   960: astore_1
    //   961: goto -743 -> 218
    //   964: astore_3
    //   965: aconst_null
    //   966: astore_0
    //   967: aconst_null
    //   968: astore 7
    //   970: aload_1
    //   971: astore 6
    //   973: aload_2
    //   974: astore 4
    //   976: aload 7
    //   978: astore_1
    //   979: aload 6
    //   981: astore_2
    //   982: goto -764 -> 218
    //   985: astore_3
    //   986: aconst_null
    //   987: astore 7
    //   989: aload_1
    //   990: astore 6
    //   992: aload_0
    //   993: astore_1
    //   994: aload_2
    //   995: astore 4
    //   997: aload 7
    //   999: astore_0
    //   1000: aload 6
    //   1002: astore_2
    //   1003: goto -785 -> 218
    //   1006: iload 15
    //   1008: iload 16
    //   1010: if_icmpge -665 -> 345
    //   1013: aload_0
    //   1014: iload 15
    //   1016: aaload
    //   1017: astore_2
    //   1018: aload_2
    //   1019: ifnonnull -887 -> 132
    //   1022: iload 15
    //   1024: iconst_1
    //   1025: iadd
    //   1026: istore 15
    //   1028: goto -22 -> 1006
    //   1031: astore_3
    //   1032: aload_0
    //   1033: astore 7
    //   1035: aload_1
    //   1036: astore 8
    //   1038: aload_2
    //   1039: astore 4
    //   1041: aload 6
    //   1043: astore_0
    //   1044: aload 7
    //   1046: astore_1
    //   1047: aload 8
    //   1049: astore_2
    //   1050: goto -832 -> 218
    // Local variable table:
    //   start	length	slot	name	signature
    //   0	1053	0	paramArrayOfString	String[]
    //   93	954	1	localObject1	Object
    //   149	580	2	localObject2	Object
    //   760	2	2	localIOException1	java.io.IOException
    //   776	15	2	localObject3	Object
    //   800	4	2	localObject4	Object
    //   807	1	2	localDataOutputStream1	java.io.DataOutputStream
    //   815	8	2	localObject5	Object
    //   826	224	2	localObject6	Object
    //   66	1	3	localObject7	Object
    //   201	18	3	localIOException2	java.io.IOException
    //   489	333	3	localObject8	Object
    //   830	8	3	localObject9	Object
    //   843	56	3	localObject10	Object
    //   905	1	3	localIOException3	java.io.IOException
    //   924	1	3	localIOException4	java.io.IOException
    //   947	1	3	localIOException5	java.io.IOException
    //   964	1	3	localIOException6	java.io.IOException
    //   985	1	3	localIOException7	java.io.IOException
    //   1031	1	3	localIOException8	java.io.IOException
    //   113	325	4	localObject11	Object
    //   557	9	4	localException1	Exception
    //   574	262	4	localObject12	Object
    //   895	5	4	localException2	Exception
    //   910	130	4	localObject13	Object
    //   105	822	5	localDataOutputStream2	java.io.DataOutputStream
    //   60	982	6	localObject14	Object
    //   117	928	7	localObject15	Object
    //   109	939	8	localObject16	Object
    //   74	536	9	localObject17	Object
    //   68	741	10	localObject18	Object
    //   63	377	11	localObject19	Object
    //   71	365	12	localObject20	Object
    //   7	336	13	localExecResult	UnifiedCommandUtil.ExecResult
    //   83	412	14	localArrayList	java.util.ArrayList
    //   127	900	15	i	int
    //   124	887	16	j	int
    //   313	457	17	bool	boolean
    // Exception table:
    //   from	to	target	type
    //   122	126	201	java/io/IOException
    //   147	156	201	java/io/IOException
    //   171	178	201	java/io/IOException
    //   193	198	201	java/io/IOException
    //   360	367	201	java/io/IOException
    //   382	387	201	java/io/IOException
    //   402	408	201	java/io/IOException
    //   485	490	557	java/lang/Exception
    //   494	535	557	java/lang/Exception
    //   538	544	557	java/lang/Exception
    //   548	554	557	java/lang/Exception
    //   642	647	688	java/io/IOException
    //   651	655	688	java/io/IOException
    //   660	665	688	java/io/IOException
    //   227	232	696	java/io/IOException
    //   236	240	696	java/io/IOException
    //   244	248	696	java/io/IOException
    //   591	596	704	java/io/IOException
    //   600	604	704	java/io/IOException
    //   609	614	704	java/io/IOException
    //   85	94	712	finally
    //   728	732	760	java/io/IOException
    //   736	740	760	java/io/IOException
    //   745	750	760	java/io/IOException
    //   94	107	774	finally
    //   122	126	787	finally
    //   147	156	787	finally
    //   171	178	787	finally
    //   193	198	787	finally
    //   360	367	787	finally
    //   382	387	787	finally
    //   402	408	787	finally
    //   423	431	787	finally
    //   446	465	787	finally
    //   582	586	787	finally
    //   465	485	800	finally
    //   485	490	815	finally
    //   494	535	815	finally
    //   538	544	815	finally
    //   548	554	815	finally
    //   218	222	830	finally
    //   85	94	850	java/lang/Exception
    //   94	107	864	java/lang/Exception
    //   122	126	876	java/lang/Exception
    //   147	156	876	java/lang/Exception
    //   171	178	876	java/lang/Exception
    //   193	198	876	java/lang/Exception
    //   360	367	876	java/lang/Exception
    //   382	387	876	java/lang/Exception
    //   402	408	876	java/lang/Exception
    //   423	431	885	java/lang/Exception
    //   446	465	891	java/lang/Exception
    //   465	485	895	java/lang/Exception
    //   85	94	905	java/io/IOException
    //   94	107	924	java/io/IOException
    //   423	431	947	java/io/IOException
    //   446	465	964	java/io/IOException
    //   465	485	985	java/io/IOException
    //   485	490	1031	java/io/IOException
    //   494	535	1031	java/io/IOException
    //   538	544	1031	java/io/IOException
    //   548	554	1031	java/io/IOException
  }
}


/* Location:              E:\apk\QQ_91\classes2-dex2jar.jar!\com\tencent\mobileqq\unifiedebug\UnifiedCommandUtil.class
 * Java compiler version: 6 (50.0)
 * JD-Core Version:       0.7.1
 */