package st;

import android.os.Handler;

abstract class c
  extends d
{
  private boolean c;
  
  void a(Handler paramHandler, b.1 param1)
    throws Exception
  {
    try
    {
      this.c = false;
      super.a(paramHandler, param1);
      return;
    }
    finally
    {
      paramHandler = finally;
      throw paramHandler;
    }
  }
  
  /* Error */
  final void a(boolean paramBoolean)
  {
    // Byte code:
    //   0: aload_0
    //   1: monitorenter
    //   2: aload_0
    //   3: getfield 17	st/c:c	Z
    //   6: iload_1
    //   7: ixor
    //   8: ifeq +19 -> 27
    //   11: aload_0
    //   12: iload_1
    //   13: putfield 17	st/c:c	Z
    //   16: aload_0
    //   17: getfield 17	st/c:c	Z
    //   20: ifeq +10 -> 30
    //   23: aload_0
    //   24: invokevirtual 24	st/c:b	()V
    //   27: aload_0
    //   28: monitorexit
    //   29: return
    //   30: aload_0
    //   31: invokevirtual 26	st/c:c	()V
    //   34: goto -7 -> 27
    //   37: astore_2
    //   38: aload_0
    //   39: monitorexit
    //   40: aload_2
    //   41: athrow
    // Local variable table:
    //   start	length	slot	name	signature
    //   0	42	0	this	c
    //   0	42	1	paramBoolean	boolean
    //   37	4	2	localObject	Object
    // Exception table:
    //   from	to	target	type
    //   2	27	37	finally
    //   30	34	37	finally
  }
  
  abstract void b();
  
  abstract void c();
}


/* Location:              E:\apk\QQ_91\classes3-dex2jar.jar!\st\c.class
 * Java compiler version: 6 (50.0)
 * JD-Core Version:       0.7.1
 */