package com.tencent.mobileqq.msf.core;

final class s
  implements Runnable
{
  /* Error */
  public void run()
  {
    // Byte code:
    //   0: invokestatic 22	java/util/Calendar:getInstance	()Ljava/util/Calendar;
    //   3: astore_1
    //   4: aload_1
    //   5: bipush 11
    //   7: iconst_0
    //   8: invokevirtual 26	java/util/Calendar:set	(II)V
    //   11: aload_1
    //   12: bipush 12
    //   14: iconst_0
    //   15: invokevirtual 26	java/util/Calendar:set	(II)V
    //   18: aload_1
    //   19: bipush 13
    //   21: iconst_0
    //   22: invokevirtual 26	java/util/Calendar:set	(II)V
    //   25: aload_1
    //   26: bipush 14
    //   28: iconst_0
    //   29: invokevirtual 26	java/util/Calendar:set	(II)V
    //   32: aload_1
    //   33: invokevirtual 30	java/util/Calendar:getTimeInMillis	()J
    //   36: invokestatic 36	java/lang/String:valueOf	(J)Ljava/lang/String;
    //   39: astore_3
    //   40: new 38	java/io/File
    //   43: dup
    //   44: getstatic 44	com/tencent/mobileqq/msf/core/o:ab	Ljava/lang/String;
    //   47: invokespecial 47	java/io/File:<init>	(Ljava/lang/String;)V
    //   50: astore_1
    //   51: aload_1
    //   52: invokevirtual 51	java/io/File:exists	()Z
    //   55: ifne +351 -> 406
    //   58: aload_1
    //   59: invokevirtual 54	java/io/File:createNewFile	()Z
    //   62: pop
    //   63: invokestatic 60	com/tencent/qphone/base/util/BaseApplication:getContext	()Lcom/tencent/qphone/base/util/BaseApplication;
    //   66: ldc 62
    //   68: iconst_0
    //   69: invokevirtual 66	com/tencent/qphone/base/util/BaseApplication:getSharedPreferences	(Ljava/lang/String;I)Landroid/content/SharedPreferences;
    //   72: astore_1
    //   73: new 68	org/json/JSONObject
    //   76: dup
    //   77: invokespecial 69	org/json/JSONObject:<init>	()V
    //   80: putstatic 73	com/tencent/mobileqq/msf/core/o:ac	Lorg/json/JSONObject;
    //   83: aload_1
    //   84: new 75	java/lang/StringBuilder
    //   87: dup
    //   88: invokespecial 76	java/lang/StringBuilder:<init>	()V
    //   91: aload_3
    //   92: invokevirtual 80	java/lang/StringBuilder:append	(Ljava/lang/String;)Ljava/lang/StringBuilder;
    //   95: ldc 82
    //   97: invokevirtual 80	java/lang/StringBuilder:append	(Ljava/lang/String;)Ljava/lang/StringBuilder;
    //   100: invokevirtual 86	java/lang/StringBuilder:toString	()Ljava/lang/String;
    //   103: invokeinterface 92 2 0
    //   108: ifeq +62 -> 170
    //   111: aload_1
    //   112: new 75	java/lang/StringBuilder
    //   115: dup
    //   116: invokespecial 76	java/lang/StringBuilder:<init>	()V
    //   119: aload_3
    //   120: invokevirtual 80	java/lang/StringBuilder:append	(Ljava/lang/String;)Ljava/lang/StringBuilder;
    //   123: ldc 82
    //   125: invokevirtual 80	java/lang/StringBuilder:append	(Ljava/lang/String;)Ljava/lang/StringBuilder;
    //   128: invokevirtual 86	java/lang/StringBuilder:toString	()Ljava/lang/String;
    //   131: fconst_1
    //   132: invokeinterface 96 3 0
    //   137: f2i
    //   138: putstatic 100	com/tencent/mobileqq/msf/core/o:W	I
    //   141: getstatic 73	com/tencent/mobileqq/msf/core/o:ac	Lorg/json/JSONObject;
    //   144: new 75	java/lang/StringBuilder
    //   147: dup
    //   148: invokespecial 76	java/lang/StringBuilder:<init>	()V
    //   151: aload_3
    //   152: invokevirtual 80	java/lang/StringBuilder:append	(Ljava/lang/String;)Ljava/lang/StringBuilder;
    //   155: ldc 82
    //   157: invokevirtual 80	java/lang/StringBuilder:append	(Ljava/lang/String;)Ljava/lang/StringBuilder;
    //   160: invokevirtual 86	java/lang/StringBuilder:toString	()Ljava/lang/String;
    //   163: getstatic 100	com/tencent/mobileqq/msf/core/o:W	I
    //   166: invokevirtual 104	org/json/JSONObject:put	(Ljava/lang/String;I)Lorg/json/JSONObject;
    //   169: pop
    //   170: aload_1
    //   171: new 75	java/lang/StringBuilder
    //   174: dup
    //   175: invokespecial 76	java/lang/StringBuilder:<init>	()V
    //   178: aload_3
    //   179: invokevirtual 80	java/lang/StringBuilder:append	(Ljava/lang/String;)Ljava/lang/StringBuilder;
    //   182: ldc 106
    //   184: invokevirtual 80	java/lang/StringBuilder:append	(Ljava/lang/String;)Ljava/lang/StringBuilder;
    //   187: invokevirtual 86	java/lang/StringBuilder:toString	()Ljava/lang/String;
    //   190: invokeinterface 92 2 0
    //   195: ifeq +62 -> 257
    //   198: aload_1
    //   199: new 75	java/lang/StringBuilder
    //   202: dup
    //   203: invokespecial 76	java/lang/StringBuilder:<init>	()V
    //   206: aload_3
    //   207: invokevirtual 80	java/lang/StringBuilder:append	(Ljava/lang/String;)Ljava/lang/StringBuilder;
    //   210: ldc 106
    //   212: invokevirtual 80	java/lang/StringBuilder:append	(Ljava/lang/String;)Ljava/lang/StringBuilder;
    //   215: invokevirtual 86	java/lang/StringBuilder:toString	()Ljava/lang/String;
    //   218: fconst_1
    //   219: invokeinterface 96 3 0
    //   224: f2i
    //   225: putstatic 109	com/tencent/mobileqq/msf/core/o:X	I
    //   228: getstatic 73	com/tencent/mobileqq/msf/core/o:ac	Lorg/json/JSONObject;
    //   231: new 75	java/lang/StringBuilder
    //   234: dup
    //   235: invokespecial 76	java/lang/StringBuilder:<init>	()V
    //   238: aload_3
    //   239: invokevirtual 80	java/lang/StringBuilder:append	(Ljava/lang/String;)Ljava/lang/StringBuilder;
    //   242: ldc 106
    //   244: invokevirtual 80	java/lang/StringBuilder:append	(Ljava/lang/String;)Ljava/lang/StringBuilder;
    //   247: invokevirtual 86	java/lang/StringBuilder:toString	()Ljava/lang/String;
    //   250: getstatic 109	com/tencent/mobileqq/msf/core/o:X	I
    //   253: invokevirtual 104	org/json/JSONObject:put	(Ljava/lang/String;I)Lorg/json/JSONObject;
    //   256: pop
    //   257: aload_1
    //   258: new 75	java/lang/StringBuilder
    //   261: dup
    //   262: invokespecial 76	java/lang/StringBuilder:<init>	()V
    //   265: aload_3
    //   266: invokevirtual 80	java/lang/StringBuilder:append	(Ljava/lang/String;)Ljava/lang/StringBuilder;
    //   269: ldc 111
    //   271: invokevirtual 80	java/lang/StringBuilder:append	(Ljava/lang/String;)Ljava/lang/StringBuilder;
    //   274: invokevirtual 86	java/lang/StringBuilder:toString	()Ljava/lang/String;
    //   277: invokeinterface 92 2 0
    //   282: ifeq +62 -> 344
    //   285: aload_1
    //   286: new 75	java/lang/StringBuilder
    //   289: dup
    //   290: invokespecial 76	java/lang/StringBuilder:<init>	()V
    //   293: aload_3
    //   294: invokevirtual 80	java/lang/StringBuilder:append	(Ljava/lang/String;)Ljava/lang/StringBuilder;
    //   297: ldc 111
    //   299: invokevirtual 80	java/lang/StringBuilder:append	(Ljava/lang/String;)Ljava/lang/StringBuilder;
    //   302: invokevirtual 86	java/lang/StringBuilder:toString	()Ljava/lang/String;
    //   305: fconst_1
    //   306: invokeinterface 96 3 0
    //   311: f2i
    //   312: putstatic 114	com/tencent/mobileqq/msf/core/o:Y	I
    //   315: getstatic 73	com/tencent/mobileqq/msf/core/o:ac	Lorg/json/JSONObject;
    //   318: new 75	java/lang/StringBuilder
    //   321: dup
    //   322: invokespecial 76	java/lang/StringBuilder:<init>	()V
    //   325: aload_3
    //   326: invokevirtual 80	java/lang/StringBuilder:append	(Ljava/lang/String;)Ljava/lang/StringBuilder;
    //   329: ldc 82
    //   331: invokevirtual 80	java/lang/StringBuilder:append	(Ljava/lang/String;)Ljava/lang/StringBuilder;
    //   334: invokevirtual 86	java/lang/StringBuilder:toString	()Ljava/lang/String;
    //   337: getstatic 114	com/tencent/mobileqq/msf/core/o:Y	I
    //   340: invokevirtual 104	org/json/JSONObject:put	(Ljava/lang/String;I)Lorg/json/JSONObject;
    //   343: pop
    //   344: aload_1
    //   345: ldc 116
    //   347: invokeinterface 92 2 0
    //   352: ifeq +27 -> 379
    //   355: aload_1
    //   356: ldc 116
    //   358: iconst_1
    //   359: invokeinterface 120 3 0
    //   364: putstatic 124	com/tencent/mobileqq/msf/core/o:M	Z
    //   367: getstatic 73	com/tencent/mobileqq/msf/core/o:ac	Lorg/json/JSONObject;
    //   370: ldc 126
    //   372: getstatic 124	com/tencent/mobileqq/msf/core/o:M	Z
    //   375: invokevirtual 129	org/json/JSONObject:put	(Ljava/lang/String;Z)Lorg/json/JSONObject;
    //   378: pop
    //   379: getstatic 132	com/tencent/mobileqq/msf/core/o:Z	Ljava/util/concurrent/atomic/AtomicBoolean;
    //   382: astore_2
    //   383: aload_2
    //   384: monitorenter
    //   385: getstatic 132	com/tencent/mobileqq/msf/core/o:Z	Ljava/util/concurrent/atomic/AtomicBoolean;
    //   388: iconst_1
    //   389: invokevirtual 137	java/util/concurrent/atomic/AtomicBoolean:set	(Z)V
    //   392: getstatic 132	com/tencent/mobileqq/msf/core/o:Z	Ljava/util/concurrent/atomic/AtomicBoolean;
    //   395: invokevirtual 140	java/lang/Object:notify	()V
    //   398: aload_2
    //   399: monitorexit
    //   400: return
    //   401: astore_1
    //   402: aload_2
    //   403: monitorexit
    //   404: aload_1
    //   405: athrow
    //   406: new 142	com/tencent/qphone/base/util/Cryptor
    //   409: dup
    //   410: invokespecial 143	com/tencent/qphone/base/util/Cryptor:<init>	()V
    //   413: astore 5
    //   415: new 145	java/io/RandomAccessFile
    //   418: dup
    //   419: getstatic 44	com/tencent/mobileqq/msf/core/o:ab	Ljava/lang/String;
    //   422: ldc -109
    //   424: invokespecial 150	java/io/RandomAccessFile:<init>	(Ljava/lang/String;Ljava/lang/String;)V
    //   427: astore_2
    //   428: aload_2
    //   429: astore_1
    //   430: aload_2
    //   431: invokevirtual 153	java/io/RandomAccessFile:length	()J
    //   434: l2i
    //   435: newarray <illegal type>
    //   437: astore 4
    //   439: aload_2
    //   440: astore_1
    //   441: aload_2
    //   442: aload 4
    //   444: invokevirtual 157	java/io/RandomAccessFile:read	([B)I
    //   447: pop
    //   448: aload_2
    //   449: astore_1
    //   450: new 68	org/json/JSONObject
    //   453: dup
    //   454: new 32	java/lang/String
    //   457: dup
    //   458: aload 5
    //   460: aload 4
    //   462: ldc -97
    //   464: invokevirtual 163	java/lang/String:getBytes	()[B
    //   467: invokevirtual 167	com/tencent/qphone/base/util/Cryptor:decrypt	([B[B)[B
    //   470: invokespecial 170	java/lang/String:<init>	([B)V
    //   473: invokespecial 171	org/json/JSONObject:<init>	(Ljava/lang/String;)V
    //   476: putstatic 73	com/tencent/mobileqq/msf/core/o:ac	Lorg/json/JSONObject;
    //   479: aload_2
    //   480: astore_1
    //   481: getstatic 73	com/tencent/mobileqq/msf/core/o:ac	Lorg/json/JSONObject;
    //   484: new 75	java/lang/StringBuilder
    //   487: dup
    //   488: invokespecial 76	java/lang/StringBuilder:<init>	()V
    //   491: aload_3
    //   492: invokevirtual 80	java/lang/StringBuilder:append	(Ljava/lang/String;)Ljava/lang/StringBuilder;
    //   495: ldc 82
    //   497: invokevirtual 80	java/lang/StringBuilder:append	(Ljava/lang/String;)Ljava/lang/StringBuilder;
    //   500: invokevirtual 86	java/lang/StringBuilder:toString	()Ljava/lang/String;
    //   503: invokevirtual 174	org/json/JSONObject:has	(Ljava/lang/String;)Z
    //   506: ifeq +33 -> 539
    //   509: aload_2
    //   510: astore_1
    //   511: getstatic 73	com/tencent/mobileqq/msf/core/o:ac	Lorg/json/JSONObject;
    //   514: new 75	java/lang/StringBuilder
    //   517: dup
    //   518: invokespecial 76	java/lang/StringBuilder:<init>	()V
    //   521: aload_3
    //   522: invokevirtual 80	java/lang/StringBuilder:append	(Ljava/lang/String;)Ljava/lang/StringBuilder;
    //   525: ldc 82
    //   527: invokevirtual 80	java/lang/StringBuilder:append	(Ljava/lang/String;)Ljava/lang/StringBuilder;
    //   530: invokevirtual 86	java/lang/StringBuilder:toString	()Ljava/lang/String;
    //   533: invokevirtual 178	org/json/JSONObject:getInt	(Ljava/lang/String;)I
    //   536: putstatic 100	com/tencent/mobileqq/msf/core/o:W	I
    //   539: aload_2
    //   540: astore_1
    //   541: getstatic 73	com/tencent/mobileqq/msf/core/o:ac	Lorg/json/JSONObject;
    //   544: new 75	java/lang/StringBuilder
    //   547: dup
    //   548: invokespecial 76	java/lang/StringBuilder:<init>	()V
    //   551: aload_3
    //   552: invokevirtual 80	java/lang/StringBuilder:append	(Ljava/lang/String;)Ljava/lang/StringBuilder;
    //   555: ldc 106
    //   557: invokevirtual 80	java/lang/StringBuilder:append	(Ljava/lang/String;)Ljava/lang/StringBuilder;
    //   560: invokevirtual 86	java/lang/StringBuilder:toString	()Ljava/lang/String;
    //   563: invokevirtual 174	org/json/JSONObject:has	(Ljava/lang/String;)Z
    //   566: ifeq +33 -> 599
    //   569: aload_2
    //   570: astore_1
    //   571: getstatic 73	com/tencent/mobileqq/msf/core/o:ac	Lorg/json/JSONObject;
    //   574: new 75	java/lang/StringBuilder
    //   577: dup
    //   578: invokespecial 76	java/lang/StringBuilder:<init>	()V
    //   581: aload_3
    //   582: invokevirtual 80	java/lang/StringBuilder:append	(Ljava/lang/String;)Ljava/lang/StringBuilder;
    //   585: ldc 106
    //   587: invokevirtual 80	java/lang/StringBuilder:append	(Ljava/lang/String;)Ljava/lang/StringBuilder;
    //   590: invokevirtual 86	java/lang/StringBuilder:toString	()Ljava/lang/String;
    //   593: invokevirtual 178	org/json/JSONObject:getInt	(Ljava/lang/String;)I
    //   596: putstatic 109	com/tencent/mobileqq/msf/core/o:X	I
    //   599: aload_2
    //   600: astore_1
    //   601: getstatic 73	com/tencent/mobileqq/msf/core/o:ac	Lorg/json/JSONObject;
    //   604: new 75	java/lang/StringBuilder
    //   607: dup
    //   608: invokespecial 76	java/lang/StringBuilder:<init>	()V
    //   611: aload_3
    //   612: invokevirtual 80	java/lang/StringBuilder:append	(Ljava/lang/String;)Ljava/lang/StringBuilder;
    //   615: ldc 111
    //   617: invokevirtual 80	java/lang/StringBuilder:append	(Ljava/lang/String;)Ljava/lang/StringBuilder;
    //   620: invokevirtual 86	java/lang/StringBuilder:toString	()Ljava/lang/String;
    //   623: invokevirtual 174	org/json/JSONObject:has	(Ljava/lang/String;)Z
    //   626: ifeq +33 -> 659
    //   629: aload_2
    //   630: astore_1
    //   631: getstatic 73	com/tencent/mobileqq/msf/core/o:ac	Lorg/json/JSONObject;
    //   634: new 75	java/lang/StringBuilder
    //   637: dup
    //   638: invokespecial 76	java/lang/StringBuilder:<init>	()V
    //   641: aload_3
    //   642: invokevirtual 80	java/lang/StringBuilder:append	(Ljava/lang/String;)Ljava/lang/StringBuilder;
    //   645: ldc 111
    //   647: invokevirtual 80	java/lang/StringBuilder:append	(Ljava/lang/String;)Ljava/lang/StringBuilder;
    //   650: invokevirtual 86	java/lang/StringBuilder:toString	()Ljava/lang/String;
    //   653: invokevirtual 178	org/json/JSONObject:getInt	(Ljava/lang/String;)I
    //   656: putstatic 114	com/tencent/mobileqq/msf/core/o:Y	I
    //   659: aload_2
    //   660: astore_1
    //   661: getstatic 73	com/tencent/mobileqq/msf/core/o:ac	Lorg/json/JSONObject;
    //   664: ldc 126
    //   666: invokevirtual 174	org/json/JSONObject:has	(Ljava/lang/String;)Z
    //   669: ifeq +16 -> 685
    //   672: aload_2
    //   673: astore_1
    //   674: getstatic 73	com/tencent/mobileqq/msf/core/o:ac	Lorg/json/JSONObject;
    //   677: ldc 126
    //   679: invokevirtual 180	org/json/JSONObject:getBoolean	(Ljava/lang/String;)Z
    //   682: putstatic 124	com/tencent/mobileqq/msf/core/o:M	Z
    //   685: aload_2
    //   686: astore_1
    //   687: getstatic 73	com/tencent/mobileqq/msf/core/o:ac	Lorg/json/JSONObject;
    //   690: ldc -74
    //   692: invokevirtual 174	org/json/JSONObject:has	(Ljava/lang/String;)Z
    //   695: ifeq +16 -> 711
    //   698: aload_2
    //   699: astore_1
    //   700: getstatic 73	com/tencent/mobileqq/msf/core/o:ac	Lorg/json/JSONObject;
    //   703: ldc -74
    //   705: invokevirtual 186	org/json/JSONObject:getLong	(Ljava/lang/String;)J
    //   708: putstatic 190	com/tencent/mobileqq/msf/core/o:aa	J
    //   711: aload_2
    //   712: astore_1
    //   713: aload_2
    //   714: invokevirtual 193	java/io/RandomAccessFile:close	()V
    //   717: ldc -61
    //   719: iconst_1
    //   720: new 75	java/lang/StringBuilder
    //   723: dup
    //   724: invokespecial 76	java/lang/StringBuilder:<init>	()V
    //   727: ldc -59
    //   729: invokevirtual 80	java/lang/StringBuilder:append	(Ljava/lang/String;)Ljava/lang/StringBuilder;
    //   732: aload_3
    //   733: invokevirtual 80	java/lang/StringBuilder:append	(Ljava/lang/String;)Ljava/lang/StringBuilder;
    //   736: ldc -57
    //   738: invokevirtual 80	java/lang/StringBuilder:append	(Ljava/lang/String;)Ljava/lang/StringBuilder;
    //   741: getstatic 73	com/tencent/mobileqq/msf/core/o:ac	Lorg/json/JSONObject;
    //   744: invokevirtual 200	org/json/JSONObject:toString	()Ljava/lang/String;
    //   747: invokevirtual 80	java/lang/StringBuilder:append	(Ljava/lang/String;)Ljava/lang/StringBuilder;
    //   750: invokevirtual 86	java/lang/StringBuilder:toString	()Ljava/lang/String;
    //   753: invokestatic 206	com/tencent/qphone/base/util/QLog:i	(Ljava/lang/String;ILjava/lang/String;)V
    //   756: iconst_0
    //   757: ifeq +11 -> 768
    //   760: new 208	java/lang/NullPointerException
    //   763: dup
    //   764: invokespecial 209	java/lang/NullPointerException:<init>	()V
    //   767: athrow
    //   768: getstatic 132	com/tencent/mobileqq/msf/core/o:Z	Ljava/util/concurrent/atomic/AtomicBoolean;
    //   771: astore_1
    //   772: aload_1
    //   773: monitorenter
    //   774: getstatic 132	com/tencent/mobileqq/msf/core/o:Z	Ljava/util/concurrent/atomic/AtomicBoolean;
    //   777: iconst_1
    //   778: invokevirtual 137	java/util/concurrent/atomic/AtomicBoolean:set	(Z)V
    //   781: getstatic 132	com/tencent/mobileqq/msf/core/o:Z	Ljava/util/concurrent/atomic/AtomicBoolean;
    //   784: invokevirtual 140	java/lang/Object:notify	()V
    //   787: aload_1
    //   788: monitorexit
    //   789: return
    //   790: astore_2
    //   791: aload_1
    //   792: monitorexit
    //   793: aload_2
    //   794: athrow
    //   795: astore_3
    //   796: aconst_null
    //   797: astore_2
    //   798: aload_2
    //   799: astore_1
    //   800: ldc -61
    //   802: iconst_1
    //   803: new 75	java/lang/StringBuilder
    //   806: dup
    //   807: invokespecial 76	java/lang/StringBuilder:<init>	()V
    //   810: ldc -45
    //   812: invokevirtual 80	java/lang/StringBuilder:append	(Ljava/lang/String;)Ljava/lang/StringBuilder;
    //   815: aload_3
    //   816: invokevirtual 214	java/lang/StringBuilder:append	(Ljava/lang/Object;)Ljava/lang/StringBuilder;
    //   819: invokevirtual 86	java/lang/StringBuilder:toString	()Ljava/lang/String;
    //   822: invokestatic 217	com/tencent/qphone/base/util/QLog:e	(Ljava/lang/String;ILjava/lang/String;)V
    //   825: aload_2
    //   826: ifnull -58 -> 768
    //   829: aload_2
    //   830: invokevirtual 193	java/io/RandomAccessFile:close	()V
    //   833: goto -65 -> 768
    //   836: astore_1
    //   837: goto -69 -> 768
    //   840: astore_2
    //   841: aconst_null
    //   842: astore_1
    //   843: aload_1
    //   844: ifnull +7 -> 851
    //   847: aload_1
    //   848: invokevirtual 193	java/io/RandomAccessFile:close	()V
    //   851: aload_2
    //   852: athrow
    //   853: astore_1
    //   854: goto -791 -> 63
    //   857: astore_1
    //   858: goto -7 -> 851
    //   861: astore_2
    //   862: goto -19 -> 843
    //   865: astore_3
    //   866: goto -68 -> 798
    //   869: astore_1
    //   870: goto -491 -> 379
    // Local variable table:
    //   start	length	slot	name	signature
    //   0	873	0	this	s
    //   3	353	1	localObject1	Object
    //   401	4	1	localObject2	Object
    //   836	1	1	localIOException1	java.io.IOException
    //   842	6	1	localObject4	Object
    //   853	1	1	localException1	Exception
    //   857	1	1	localIOException2	java.io.IOException
    //   869	1	1	localException2	Exception
    //   382	332	2	localObject5	Object
    //   790	4	2	localObject6	Object
    //   797	33	2	localObject7	Object
    //   840	12	2	localObject8	Object
    //   861	1	2	localObject9	Object
    //   39	694	3	str	String
    //   795	21	3	localException3	Exception
    //   865	1	3	localException4	Exception
    //   437	24	4	arrayOfByte	byte[]
    //   413	46	5	localCryptor	com.tencent.qphone.base.util.Cryptor
    // Exception table:
    //   from	to	target	type
    //   385	400	401	finally
    //   402	404	401	finally
    //   774	789	790	finally
    //   791	793	790	finally
    //   406	428	795	java/lang/Exception
    //   717	756	795	java/lang/Exception
    //   760	768	836	java/io/IOException
    //   829	833	836	java/io/IOException
    //   406	428	840	finally
    //   717	756	840	finally
    //   58	63	853	java/lang/Exception
    //   847	851	857	java/io/IOException
    //   430	439	861	finally
    //   441	448	861	finally
    //   450	479	861	finally
    //   481	509	861	finally
    //   511	539	861	finally
    //   541	569	861	finally
    //   571	599	861	finally
    //   601	629	861	finally
    //   631	659	861	finally
    //   661	672	861	finally
    //   674	685	861	finally
    //   687	698	861	finally
    //   700	711	861	finally
    //   713	717	861	finally
    //   800	825	861	finally
    //   430	439	865	java/lang/Exception
    //   441	448	865	java/lang/Exception
    //   450	479	865	java/lang/Exception
    //   481	509	865	java/lang/Exception
    //   511	539	865	java/lang/Exception
    //   541	569	865	java/lang/Exception
    //   571	599	865	java/lang/Exception
    //   601	629	865	java/lang/Exception
    //   631	659	865	java/lang/Exception
    //   661	672	865	java/lang/Exception
    //   674	685	865	java/lang/Exception
    //   687	698	865	java/lang/Exception
    //   700	711	865	java/lang/Exception
    //   713	717	865	java/lang/Exception
    //   83	170	869	java/lang/Exception
    //   170	257	869	java/lang/Exception
    //   257	344	869	java/lang/Exception
    //   344	379	869	java/lang/Exception
  }
}


/* Location:              E:\apk\QQ_91\classes-dex2jar.jar!\com\tencent\mobileqq\msf\core\s.class
 * Java compiler version: 6 (50.0)
 * JD-Core Version:       0.7.1
 */