import com.tencent.mobileqq.app.LebaHelper;
import com.tencent.mobileqq.hotpatch.NotVerifyClass;
import mqq.observer.ServerConfigObserver;

public class pzi
  extends ServerConfigObserver
{
  public pzi(LebaHelper paramLebaHelper)
  {
    boolean bool = NotVerifyClass.DO_VERIFY_CLASS;
  }
  
  /* Error */
  public void onGetPluginConfig(boolean paramBoolean, int paramInt, protocol.KQQConfig.GetResourceRespV2 arg3)
  {
    // Byte code:
    //   0: iload_2
    //   1: bipush 64
    //   3: iand
    //   4: ifne +4 -> 8
    //   7: return
    //   8: invokestatic 30	com/tencent/qphone/base/util/QLog:isColorLevel	()Z
    //   11: ifeq +11 -> 22
    //   14: ldc 32
    //   16: iconst_2
    //   17: ldc 34
    //   19: invokestatic 38	com/tencent/qphone/base/util/QLog:i	(Ljava/lang/String;ILjava/lang/String;)V
    //   22: iload_1
    //   23: ifeq +1012 -> 1035
    //   26: aload_3
    //   27: ifnull +1008 -> 1035
    //   30: aload_0
    //   31: getfield 10	pzi:a	Lcom/tencent/mobileqq/app/LebaHelper;
    //   34: iconst_0
    //   35: putfield 42	com/tencent/mobileqq/app/LebaHelper:jdField_a_of_type_Boolean	Z
    //   38: invokestatic 30	com/tencent/qphone/base/util/QLog:isColorLevel	()Z
    //   41: ifeq +28 -> 69
    //   44: ldc 32
    //   46: iconst_2
    //   47: new 44	java/lang/StringBuilder
    //   50: dup
    //   51: invokespecial 45	java/lang/StringBuilder:<init>	()V
    //   54: ldc 47
    //   56: invokevirtual 51	java/lang/StringBuilder:append	(Ljava/lang/String;)Ljava/lang/StringBuilder;
    //   59: aload_3
    //   60: invokevirtual 54	java/lang/StringBuilder:append	(Ljava/lang/Object;)Ljava/lang/StringBuilder;
    //   63: invokevirtual 58	java/lang/StringBuilder:toString	()Ljava/lang/String;
    //   66: invokestatic 61	com/tencent/qphone/base/util/QLog:d	(Ljava/lang/String;ILjava/lang/String;)V
    //   69: aload_0
    //   70: getfield 10	pzi:a	Lcom/tencent/mobileqq/app/LebaHelper;
    //   73: getfield 64	com/tencent/mobileqq/app/LebaHelper:jdField_a_of_type_ComTencentMobileqqAppQQAppInterface	Lcom/tencent/mobileqq/app/QQAppInterface;
    //   76: invokevirtual 69	com/tencent/mobileqq/app/QQAppInterface:a	()Lcom/tencent/mobileqq/persistence/EntityManagerFactory;
    //   79: invokevirtual 75	com/tencent/mobileqq/persistence/EntityManagerFactory:createEntityManager	()Lcom/tencent/mobileqq/persistence/EntityManager;
    //   82: astore 4
    //   84: aload 4
    //   86: invokevirtual 80	com/tencent/mobileqq/persistence/EntityManager:a	()Lcom/tencent/mobileqq/persistence/EntityTransaction;
    //   89: astore 5
    //   91: iconst_0
    //   92: istore 8
    //   94: iconst_0
    //   95: istore 9
    //   97: iconst_0
    //   98: istore 10
    //   100: iconst_0
    //   101: istore 7
    //   103: iconst_0
    //   104: istore 11
    //   106: iconst_0
    //   107: istore_2
    //   108: aload_0
    //   109: getfield 10	pzi:a	Lcom/tencent/mobileqq/app/LebaHelper;
    //   112: getfield 64	com/tencent/mobileqq/app/LebaHelper:jdField_a_of_type_ComTencentMobileqqAppQQAppInterface	Lcom/tencent/mobileqq/app/QQAppInterface;
    //   115: invokevirtual 83	com/tencent/mobileqq/app/QQAppInterface:a	()Lcom/tencent/qphone/base/util/BaseApplication;
    //   118: invokevirtual 89	com/tencent/qphone/base/util/BaseApplication:getResources	()Landroid/content/res/Resources;
    //   121: invokevirtual 95	android/content/res/Resources:getDisplayMetrics	()Landroid/util/DisplayMetrics;
    //   124: getfield 101	android/util/DisplayMetrics:widthPixels	I
    //   127: sipush 480
    //   130: if_icmplt +1032 -> 1162
    //   133: iconst_1
    //   134: istore_1
    //   135: aload 5
    //   137: invokevirtual 105	com/tencent/mobileqq/persistence/EntityTransaction:a	()V
    //   140: iconst_0
    //   141: istore 12
    //   143: iload_2
    //   144: istore 11
    //   146: iload 7
    //   148: istore 10
    //   150: iload 9
    //   152: istore 8
    //   154: iload 12
    //   156: aload_3
    //   157: getfield 111	protocol/KQQConfig/GetResourceRespV2:vecAddedResInfo	Ljava/util/ArrayList;
    //   160: invokevirtual 117	java/util/ArrayList:size	()I
    //   163: if_icmpge +215 -> 378
    //   166: iload_2
    //   167: istore 11
    //   169: iload 7
    //   171: istore 10
    //   173: iload 9
    //   175: istore 8
    //   177: aload_3
    //   178: getfield 111	protocol/KQQConfig/GetResourceRespV2:vecAddedResInfo	Ljava/util/ArrayList;
    //   181: iload 12
    //   183: invokevirtual 121	java/util/ArrayList:get	(I)Ljava/lang/Object;
    //   186: checkcast 123	protocol/KQQConfig/GetResourceRespInfoV2
    //   189: astore 6
    //   191: iload_2
    //   192: istore 11
    //   194: iload 7
    //   196: istore 10
    //   198: iload 9
    //   200: istore 8
    //   202: aload 6
    //   204: getfield 126	protocol/KQQConfig/GetResourceRespInfoV2:iPluginType	I
    //   207: bipush 64
    //   209: if_icmpeq +10 -> 219
    //   212: iload 9
    //   214: istore 8
    //   216: goto +933 -> 1149
    //   219: iload_2
    //   220: istore 11
    //   222: iload 7
    //   224: istore 10
    //   226: iload 9
    //   228: istore 8
    //   230: aload 6
    //   232: getfield 130	protocol/KQQConfig/GetResourceRespInfoV2:sResSubType	S
    //   235: ifeq +23 -> 258
    //   238: iload_2
    //   239: istore 11
    //   241: iload 7
    //   243: istore 10
    //   245: iload 9
    //   247: istore 8
    //   249: aload 6
    //   251: getfield 130	protocol/KQQConfig/GetResourceRespInfoV2:sResSubType	S
    //   254: iconst_2
    //   255: if_icmpne +890 -> 1145
    //   258: iload_2
    //   259: istore 11
    //   261: iload 7
    //   263: istore 10
    //   265: iload 9
    //   267: istore 8
    //   269: aload 4
    //   271: iload_1
    //   272: aload 6
    //   274: invokestatic 135	com/tencent/mobileqq/config/ConfigManager:a	(Lcom/tencent/mobileqq/persistence/EntityManager;ZLprotocol/KQQConfig/GetResourceRespInfoV2;)Lcom/tencent/mobileqq/data/ResourcePluginInfo;
    //   277: astore 6
    //   279: iconst_1
    //   280: istore 13
    //   282: iconst_1
    //   283: istore 9
    //   285: iconst_1
    //   286: istore 14
    //   288: iconst_1
    //   289: istore 7
    //   291: iload_2
    //   292: istore 11
    //   294: iload 14
    //   296: istore 10
    //   298: iload 13
    //   300: istore 8
    //   302: aload 6
    //   304: getfield 141	com/tencent/mobileqq/data/ResourcePluginInfo:cDefaultState	B
    //   307: ifne +835 -> 1142
    //   310: iload_2
    //   311: istore 11
    //   313: iload 14
    //   315: istore 10
    //   317: iload 13
    //   319: istore 8
    //   321: aload 6
    //   323: getfield 145	com/tencent/mobileqq/data/ResourcePluginInfo:uiResId	J
    //   326: lstore 15
    //   328: lload 15
    //   330: lconst_0
    //   331: lcmp
    //   332: ifgt +810 -> 1142
    //   335: iconst_1
    //   336: istore_2
    //   337: invokestatic 30	com/tencent/qphone/base/util/QLog:isColorLevel	()Z
    //   340: ifeq +29 -> 369
    //   343: ldc 32
    //   345: iconst_2
    //   346: new 44	java/lang/StringBuilder
    //   349: dup
    //   350: invokespecial 45	java/lang/StringBuilder:<init>	()V
    //   353: ldc -109
    //   355: invokevirtual 51	java/lang/StringBuilder:append	(Ljava/lang/String;)Ljava/lang/StringBuilder;
    //   358: aload 6
    //   360: invokevirtual 54	java/lang/StringBuilder:append	(Ljava/lang/Object;)Ljava/lang/StringBuilder;
    //   363: invokevirtual 58	java/lang/StringBuilder:toString	()Ljava/lang/String;
    //   366: invokestatic 61	com/tencent/qphone/base/util/QLog:d	(Ljava/lang/String;ILjava/lang/String;)V
    //   369: iconst_1
    //   370: istore 7
    //   372: iconst_1
    //   373: istore 8
    //   375: goto +774 -> 1149
    //   378: iconst_0
    //   379: istore 12
    //   381: iload_2
    //   382: istore 11
    //   384: iload 7
    //   386: istore 10
    //   388: iload 9
    //   390: istore 8
    //   392: iload 12
    //   394: aload_3
    //   395: getfield 150	protocol/KQQConfig/GetResourceRespV2:vecDeletedResInfo	Ljava/util/ArrayList;
    //   398: invokevirtual 117	java/util/ArrayList:size	()I
    //   401: if_icmpge +333 -> 734
    //   404: iload_2
    //   405: istore 11
    //   407: iload 7
    //   409: istore 10
    //   411: iload 9
    //   413: istore 8
    //   415: aload_3
    //   416: getfield 150	protocol/KQQConfig/GetResourceRespV2:vecDeletedResInfo	Ljava/util/ArrayList;
    //   419: iload 12
    //   421: invokevirtual 121	java/util/ArrayList:get	(I)Ljava/lang/Object;
    //   424: checkcast 123	protocol/KQQConfig/GetResourceRespInfoV2
    //   427: astore 6
    //   429: iload_2
    //   430: istore 11
    //   432: iload 7
    //   434: istore 10
    //   436: iload 9
    //   438: istore 8
    //   440: aload 6
    //   442: getfield 126	protocol/KQQConfig/GetResourceRespInfoV2:iPluginType	I
    //   445: bipush 64
    //   447: if_icmpeq +10 -> 457
    //   450: iload 9
    //   452: istore 8
    //   454: goto +713 -> 1167
    //   457: iload_2
    //   458: istore 11
    //   460: iload 7
    //   462: istore 10
    //   464: iload 9
    //   466: istore 8
    //   468: aload 6
    //   470: getfield 130	protocol/KQQConfig/GetResourceRespInfoV2:sResSubType	S
    //   473: ifeq +23 -> 496
    //   476: iload_2
    //   477: istore 11
    //   479: iload 7
    //   481: istore 10
    //   483: iload 9
    //   485: istore 8
    //   487: aload 6
    //   489: getfield 130	protocol/KQQConfig/GetResourceRespInfoV2:sResSubType	S
    //   492: iconst_2
    //   493: if_icmpne +642 -> 1135
    //   496: iload_2
    //   497: istore 11
    //   499: iload 7
    //   501: istore 10
    //   503: iload 9
    //   505: istore 8
    //   507: aload 6
    //   509: getfield 154	protocol/KQQConfig/GetResourceRespInfoV2:strPkgName	Ljava/lang/String;
    //   512: astore 6
    //   514: iload_2
    //   515: istore 11
    //   517: iload 7
    //   519: istore 10
    //   521: iload 9
    //   523: istore 8
    //   525: aload 4
    //   527: aload 6
    //   529: invokestatic 158	com/tencent/mobileqq/data/ResourcePluginInfo:remove	(Lcom/tencent/mobileqq/persistence/EntityManager;Ljava/lang/String;)V
    //   532: iconst_1
    //   533: istore 9
    //   535: iload 9
    //   537: istore 8
    //   539: invokestatic 30	com/tencent/qphone/base/util/QLog:isColorLevel	()Z
    //   542: ifeq +625 -> 1167
    //   545: ldc 32
    //   547: iconst_2
    //   548: new 44	java/lang/StringBuilder
    //   551: dup
    //   552: invokespecial 45	java/lang/StringBuilder:<init>	()V
    //   555: ldc -96
    //   557: invokevirtual 51	java/lang/StringBuilder:append	(Ljava/lang/String;)Ljava/lang/StringBuilder;
    //   560: aload 6
    //   562: invokevirtual 51	java/lang/StringBuilder:append	(Ljava/lang/String;)Ljava/lang/StringBuilder;
    //   565: invokevirtual 58	java/lang/StringBuilder:toString	()Ljava/lang/String;
    //   568: invokestatic 61	com/tencent/qphone/base/util/QLog:d	(Ljava/lang/String;ILjava/lang/String;)V
    //   571: iload 9
    //   573: istore 8
    //   575: goto +592 -> 1167
    //   578: astore_3
    //   579: iconst_1
    //   580: istore 8
    //   582: invokestatic 30	com/tencent/qphone/base/util/QLog:isColorLevel	()Z
    //   585: ifeq +31 -> 616
    //   588: ldc 32
    //   590: iconst_2
    //   591: new 44	java/lang/StringBuilder
    //   594: dup
    //   595: invokespecial 45	java/lang/StringBuilder:<init>	()V
    //   598: ldc -94
    //   600: invokevirtual 51	java/lang/StringBuilder:append	(Ljava/lang/String;)Ljava/lang/StringBuilder;
    //   603: aload_3
    //   604: invokevirtual 163	java/lang/Exception:toString	()Ljava/lang/String;
    //   607: invokevirtual 51	java/lang/StringBuilder:append	(Ljava/lang/String;)Ljava/lang/StringBuilder;
    //   610: invokevirtual 58	java/lang/StringBuilder:toString	()Ljava/lang/String;
    //   613: invokestatic 61	com/tencent/qphone/base/util/QLog:d	(Ljava/lang/String;ILjava/lang/String;)V
    //   616: aload_3
    //   617: invokevirtual 166	java/lang/Exception:printStackTrace	()V
    //   620: aload 5
    //   622: invokevirtual 169	com/tencent/mobileqq/persistence/EntityTransaction:c	()V
    //   625: aload 5
    //   627: invokevirtual 172	com/tencent/mobileqq/persistence/EntityTransaction:b	()V
    //   630: aload 4
    //   632: invokevirtual 173	com/tencent/mobileqq/persistence/EntityManager:a	()V
    //   635: aload_0
    //   636: getfield 10	pzi:a	Lcom/tencent/mobileqq/app/LebaHelper;
    //   639: invokestatic 175	com/tencent/mobileqq/app/LebaHelper:a	(Lcom/tencent/mobileqq/app/LebaHelper;)V
    //   642: aload_0
    //   643: getfield 10	pzi:a	Lcom/tencent/mobileqq/app/LebaHelper;
    //   646: invokestatic 177	com/tencent/mobileqq/app/LebaHelper:b	(Lcom/tencent/mobileqq/app/LebaHelper;)V
    //   649: iload 8
    //   651: ifeq +318 -> 969
    //   654: new 113	java/util/ArrayList
    //   657: dup
    //   658: aload_0
    //   659: getfield 10	pzi:a	Lcom/tencent/mobileqq/app/LebaHelper;
    //   662: getfield 180	com/tencent/mobileqq/app/LebaHelper:c	Ljava/util/List;
    //   665: invokespecial 183	java/util/ArrayList:<init>	(Ljava/util/Collection;)V
    //   668: invokeinterface 189 1 0
    //   673: astore_3
    //   674: aload_3
    //   675: invokeinterface 194 1 0
    //   680: ifeq -673 -> 7
    //   683: aload_3
    //   684: invokeinterface 198 1 0
    //   689: checkcast 200	com/tencent/mobileqq/config/ResourcePluginListener
    //   692: astore 4
    //   694: iload 7
    //   696: ifeq +263 -> 959
    //   699: aload 4
    //   701: iconst_3
    //   702: iconst_1
    //   703: invokestatic 203	com/tencent/mobileqq/config/ResourcePluginListener:a	(Lcom/tencent/mobileqq/config/ResourcePluginListener;BI)V
    //   706: iload_2
    //   707: ifeq -33 -> 674
    //   710: invokestatic 30	com/tencent/qphone/base/util/QLog:isColorLevel	()Z
    //   713: ifeq +11 -> 724
    //   716: ldc 32
    //   718: iconst_2
    //   719: ldc -51
    //   721: invokestatic 61	com/tencent/qphone/base/util/QLog:d	(Ljava/lang/String;ILjava/lang/String;)V
    //   724: aload 4
    //   726: iconst_4
    //   727: iconst_1
    //   728: invokestatic 203	com/tencent/mobileqq/config/ResourcePluginListener:a	(Lcom/tencent/mobileqq/config/ResourcePluginListener;BI)V
    //   731: goto -57 -> 674
    //   734: iconst_0
    //   735: istore 12
    //   737: iload_2
    //   738: istore 11
    //   740: iload 7
    //   742: istore 10
    //   744: iload 9
    //   746: istore 8
    //   748: iload 12
    //   750: aload_3
    //   751: getfield 208	protocol/KQQConfig/GetResourceRespV2:vecUpdatedResInfo	Ljava/util/ArrayList;
    //   754: invokevirtual 117	java/util/ArrayList:size	()I
    //   757: if_icmpge +180 -> 937
    //   760: iload_2
    //   761: istore 11
    //   763: iload 7
    //   765: istore 10
    //   767: iload 9
    //   769: istore 8
    //   771: aload_3
    //   772: getfield 208	protocol/KQQConfig/GetResourceRespV2:vecUpdatedResInfo	Ljava/util/ArrayList;
    //   775: iload 12
    //   777: invokevirtual 121	java/util/ArrayList:get	(I)Ljava/lang/Object;
    //   780: checkcast 123	protocol/KQQConfig/GetResourceRespInfoV2
    //   783: astore 6
    //   785: iload_2
    //   786: istore 11
    //   788: iload 7
    //   790: istore 10
    //   792: iload 9
    //   794: istore 8
    //   796: aload 6
    //   798: getfield 126	protocol/KQQConfig/GetResourceRespInfoV2:iPluginType	I
    //   801: bipush 64
    //   803: if_icmpeq +10 -> 813
    //   806: iload 9
    //   808: istore 8
    //   810: goto +370 -> 1180
    //   813: iload_2
    //   814: istore 11
    //   816: iload 7
    //   818: istore 10
    //   820: iload 9
    //   822: istore 8
    //   824: aload 6
    //   826: getfield 130	protocol/KQQConfig/GetResourceRespInfoV2:sResSubType	S
    //   829: ifeq +23 -> 852
    //   832: iload_2
    //   833: istore 11
    //   835: iload 7
    //   837: istore 10
    //   839: iload 9
    //   841: istore 8
    //   843: aload 6
    //   845: getfield 130	protocol/KQQConfig/GetResourceRespInfoV2:sResSubType	S
    //   848: iconst_2
    //   849: if_icmpne +279 -> 1128
    //   852: iload_2
    //   853: istore 11
    //   855: iload 7
    //   857: istore 10
    //   859: iload 9
    //   861: istore 8
    //   863: aload 4
    //   865: iload_1
    //   866: aload 6
    //   868: invokestatic 135	com/tencent/mobileqq/config/ConfigManager:a	(Lcom/tencent/mobileqq/persistence/EntityManager;ZLprotocol/KQQConfig/GetResourceRespInfoV2;)Lcom/tencent/mobileqq/data/ResourcePluginInfo;
    //   871: astore 6
    //   873: iconst_1
    //   874: istore 9
    //   876: iload 9
    //   878: istore 8
    //   880: invokestatic 30	com/tencent/qphone/base/util/QLog:isColorLevel	()Z
    //   883: ifeq +297 -> 1180
    //   886: ldc 32
    //   888: iconst_2
    //   889: new 44	java/lang/StringBuilder
    //   892: dup
    //   893: invokespecial 45	java/lang/StringBuilder:<init>	()V
    //   896: ldc -46
    //   898: invokevirtual 51	java/lang/StringBuilder:append	(Ljava/lang/String;)Ljava/lang/StringBuilder;
    //   901: aload 6
    //   903: invokevirtual 54	java/lang/StringBuilder:append	(Ljava/lang/Object;)Ljava/lang/StringBuilder;
    //   906: invokevirtual 58	java/lang/StringBuilder:toString	()Ljava/lang/String;
    //   909: invokestatic 61	com/tencent/qphone/base/util/QLog:d	(Ljava/lang/String;ILjava/lang/String;)V
    //   912: iload 9
    //   914: istore 8
    //   916: goto +264 -> 1180
    //   919: astore_3
    //   920: aload 5
    //   922: invokevirtual 169	com/tencent/mobileqq/persistence/EntityTransaction:c	()V
    //   925: aload 5
    //   927: invokevirtual 172	com/tencent/mobileqq/persistence/EntityTransaction:b	()V
    //   930: aload 4
    //   932: invokevirtual 173	com/tencent/mobileqq/persistence/EntityManager:a	()V
    //   935: aload_3
    //   936: athrow
    //   937: aload 5
    //   939: invokevirtual 169	com/tencent/mobileqq/persistence/EntityTransaction:c	()V
    //   942: aload 5
    //   944: invokevirtual 172	com/tencent/mobileqq/persistence/EntityTransaction:b	()V
    //   947: aload 4
    //   949: invokevirtual 173	com/tencent/mobileqq/persistence/EntityManager:a	()V
    //   952: iload 9
    //   954: istore 8
    //   956: goto -321 -> 635
    //   959: aload 4
    //   961: iconst_2
    //   962: iconst_1
    //   963: invokestatic 203	com/tencent/mobileqq/config/ResourcePluginListener:a	(Lcom/tencent/mobileqq/config/ResourcePluginListener;BI)V
    //   966: goto -292 -> 674
    //   969: aload_0
    //   970: getfield 10	pzi:a	Lcom/tencent/mobileqq/app/LebaHelper;
    //   973: getfield 180	com/tencent/mobileqq/app/LebaHelper:c	Ljava/util/List;
    //   976: astore_3
    //   977: aload_3
    //   978: monitorenter
    //   979: iconst_0
    //   980: istore_2
    //   981: iload_2
    //   982: aload_0
    //   983: getfield 10	pzi:a	Lcom/tencent/mobileqq/app/LebaHelper;
    //   986: getfield 180	com/tencent/mobileqq/app/LebaHelper:c	Ljava/util/List;
    //   989: invokeinterface 211 1 0
    //   994: if_icmpge +31 -> 1025
    //   997: aload_0
    //   998: getfield 10	pzi:a	Lcom/tencent/mobileqq/app/LebaHelper;
    //   1001: getfield 180	com/tencent/mobileqq/app/LebaHelper:c	Ljava/util/List;
    //   1004: iload_2
    //   1005: invokeinterface 212 2 0
    //   1010: checkcast 200	com/tencent/mobileqq/config/ResourcePluginListener
    //   1013: iconst_1
    //   1014: iconst_1
    //   1015: invokestatic 203	com/tencent/mobileqq/config/ResourcePluginListener:a	(Lcom/tencent/mobileqq/config/ResourcePluginListener;BI)V
    //   1018: iload_2
    //   1019: iconst_1
    //   1020: iadd
    //   1021: istore_2
    //   1022: goto -41 -> 981
    //   1025: aload_3
    //   1026: monitorexit
    //   1027: return
    //   1028: astore 4
    //   1030: aload_3
    //   1031: monitorexit
    //   1032: aload 4
    //   1034: athrow
    //   1035: aload_0
    //   1036: getfield 10	pzi:a	Lcom/tencent/mobileqq/app/LebaHelper;
    //   1039: getfield 180	com/tencent/mobileqq/app/LebaHelper:c	Ljava/util/List;
    //   1042: astore_3
    //   1043: aload_3
    //   1044: monitorenter
    //   1045: aload_0
    //   1046: getfield 10	pzi:a	Lcom/tencent/mobileqq/app/LebaHelper;
    //   1049: iconst_1
    //   1050: putfield 42	com/tencent/mobileqq/app/LebaHelper:jdField_a_of_type_Boolean	Z
    //   1053: iconst_0
    //   1054: istore_2
    //   1055: iload_2
    //   1056: aload_0
    //   1057: getfield 10	pzi:a	Lcom/tencent/mobileqq/app/LebaHelper;
    //   1060: getfield 180	com/tencent/mobileqq/app/LebaHelper:c	Ljava/util/List;
    //   1063: invokeinterface 211 1 0
    //   1068: if_icmpge +31 -> 1099
    //   1071: aload_0
    //   1072: getfield 10	pzi:a	Lcom/tencent/mobileqq/app/LebaHelper;
    //   1075: getfield 180	com/tencent/mobileqq/app/LebaHelper:c	Ljava/util/List;
    //   1078: iload_2
    //   1079: invokeinterface 212 2 0
    //   1084: checkcast 200	com/tencent/mobileqq/config/ResourcePluginListener
    //   1087: iconst_m1
    //   1088: iconst_1
    //   1089: invokestatic 203	com/tencent/mobileqq/config/ResourcePluginListener:a	(Lcom/tencent/mobileqq/config/ResourcePluginListener;BI)V
    //   1092: iload_2
    //   1093: iconst_1
    //   1094: iadd
    //   1095: istore_2
    //   1096: goto -41 -> 1055
    //   1099: aload_3
    //   1100: monitorexit
    //   1101: return
    //   1102: astore 4
    //   1104: aload_3
    //   1105: monitorexit
    //   1106: aload 4
    //   1108: athrow
    //   1109: astore_3
    //   1110: iload 11
    //   1112: istore_2
    //   1113: iload 10
    //   1115: istore 7
    //   1117: goto -535 -> 582
    //   1120: astore_3
    //   1121: iload 9
    //   1123: istore 8
    //   1125: goto -543 -> 582
    //   1128: iload 9
    //   1130: istore 8
    //   1132: goto +48 -> 1180
    //   1135: iload 9
    //   1137: istore 8
    //   1139: goto +28 -> 1167
    //   1142: goto -805 -> 337
    //   1145: iload 9
    //   1147: istore 8
    //   1149: iload 12
    //   1151: iconst_1
    //   1152: iadd
    //   1153: istore 12
    //   1155: iload 8
    //   1157: istore 9
    //   1159: goto -1016 -> 143
    //   1162: iconst_0
    //   1163: istore_1
    //   1164: goto -1029 -> 135
    //   1167: iload 12
    //   1169: iconst_1
    //   1170: iadd
    //   1171: istore 12
    //   1173: iload 8
    //   1175: istore 9
    //   1177: goto -796 -> 381
    //   1180: iload 12
    //   1182: iconst_1
    //   1183: iadd
    //   1184: istore 12
    //   1186: iload 8
    //   1188: istore 9
    //   1190: goto -453 -> 737
    // Local variable table:
    //   start	length	slot	name	signature
    //   0	1193	0	this	pzi
    //   0	1193	1	paramBoolean	boolean
    //   0	1193	2	paramInt	int
    //   82	878	4	localObject1	Object
    //   1028	5	4	localObject2	Object
    //   1102	5	4	localObject3	Object
    //   89	854	5	localEntityTransaction	com.tencent.mobileqq.persistence.EntityTransaction
    //   189	713	6	localObject4	Object
    //   101	1015	7	i	int
    //   92	1095	8	j	int
    //   95	1094	9	k	int
    //   98	1016	10	m	int
    //   104	1007	11	n	int
    //   141	1044	12	i1	int
    //   280	38	13	i2	int
    //   286	28	14	i3	int
    //   326	3	15	l	long
    // Exception table:
    //   from	to	target	type
    //   539	571	578	java/lang/Exception
    //   880	912	578	java/lang/Exception
    //   135	140	919	finally
    //   154	166	919	finally
    //   177	191	919	finally
    //   202	212	919	finally
    //   230	238	919	finally
    //   249	258	919	finally
    //   269	279	919	finally
    //   302	310	919	finally
    //   321	328	919	finally
    //   337	369	919	finally
    //   392	404	919	finally
    //   415	429	919	finally
    //   440	450	919	finally
    //   468	476	919	finally
    //   487	496	919	finally
    //   507	514	919	finally
    //   525	532	919	finally
    //   539	571	919	finally
    //   582	616	919	finally
    //   616	620	919	finally
    //   748	760	919	finally
    //   771	785	919	finally
    //   796	806	919	finally
    //   824	832	919	finally
    //   843	852	919	finally
    //   863	873	919	finally
    //   880	912	919	finally
    //   981	1018	1028	finally
    //   1025	1027	1028	finally
    //   1030	1032	1028	finally
    //   1045	1053	1102	finally
    //   1055	1092	1102	finally
    //   1099	1101	1102	finally
    //   1104	1106	1102	finally
    //   135	140	1109	java/lang/Exception
    //   154	166	1109	java/lang/Exception
    //   177	191	1109	java/lang/Exception
    //   202	212	1109	java/lang/Exception
    //   230	238	1109	java/lang/Exception
    //   249	258	1109	java/lang/Exception
    //   269	279	1109	java/lang/Exception
    //   302	310	1109	java/lang/Exception
    //   321	328	1109	java/lang/Exception
    //   392	404	1109	java/lang/Exception
    //   415	429	1109	java/lang/Exception
    //   440	450	1109	java/lang/Exception
    //   468	476	1109	java/lang/Exception
    //   487	496	1109	java/lang/Exception
    //   507	514	1109	java/lang/Exception
    //   525	532	1109	java/lang/Exception
    //   748	760	1109	java/lang/Exception
    //   771	785	1109	java/lang/Exception
    //   796	806	1109	java/lang/Exception
    //   824	832	1109	java/lang/Exception
    //   843	852	1109	java/lang/Exception
    //   863	873	1109	java/lang/Exception
    //   337	369	1120	java/lang/Exception
  }
}


/* Location:              E:\apk\QQ_91\classes-dex2jar.jar!\pzi.class
 * Java compiler version: 6 (50.0)
 * JD-Core Version:       0.7.1
 */