package ct;

public final class ar
{
  private static ar k = null;
  String a = "";
  String b = "";
  String c = "";
  String d = "";
  String e = "";
  private String f = "";
  private String g = "";
  private String h = "";
  private String i = "";
  private String j = "";
  
  /* Error */
  public static void a(android.content.Context paramContext)
  {
    // Byte code:
    //   0: ldc 2
    //   2: monitorenter
    //   3: aload_0
    //   4: ifnull +231 -> 235
    //   7: getstatic 21	ct/ar:k	Lct/ar;
    //   10: ifnonnull +13 -> 23
    //   13: new 2	ct/ar
    //   16: dup
    //   17: invokespecial 49	ct/ar:<init>	()V
    //   20: putstatic 21	ct/ar:k	Lct/ar;
    //   23: getstatic 21	ct/ar:k	Lct/ar;
    //   26: astore_1
    //   27: aload_1
    //   28: monitorenter
    //   29: getstatic 21	ct/ar:k	Lct/ar;
    //   32: astore_2
    //   33: aload_0
    //   34: invokestatic 54	ct/as:a	(Landroid/content/Context;)Lct/as;
    //   37: pop
    //   38: new 56	java/lang/StringBuffer
    //   41: dup
    //   42: invokespecial 57	java/lang/StringBuffer:<init>	()V
    //   45: astore_3
    //   46: aload_3
    //   47: invokestatic 60	ct/as:a	()Ljava/lang/String;
    //   50: invokevirtual 64	java/lang/StringBuffer:append	(Ljava/lang/String;)Ljava/lang/StringBuffer;
    //   53: pop
    //   54: aload_3
    //   55: ldc 66
    //   57: invokevirtual 64	java/lang/StringBuffer:append	(Ljava/lang/String;)Ljava/lang/StringBuffer;
    //   60: pop
    //   61: aload_3
    //   62: invokestatic 68	ct/as:b	()Ljava/lang/String;
    //   65: invokevirtual 64	java/lang/StringBuffer:append	(Ljava/lang/String;)Ljava/lang/StringBuffer;
    //   68: pop
    //   69: aload_3
    //   70: ldc 70
    //   72: invokevirtual 64	java/lang/StringBuffer:append	(Ljava/lang/String;)Ljava/lang/StringBuffer;
    //   75: pop
    //   76: aload_3
    //   77: invokestatic 72	ct/as:c	()Ljava/lang/String;
    //   80: invokevirtual 64	java/lang/StringBuffer:append	(Ljava/lang/String;)Ljava/lang/StringBuffer;
    //   83: pop
    //   84: aload_2
    //   85: aload_3
    //   86: invokevirtual 75	java/lang/StringBuffer:toString	()Ljava/lang/String;
    //   89: invokespecial 78	ct/ar:a	(Ljava/lang/String;)V
    //   92: getstatic 21	ct/ar:k	Lct/ar;
    //   95: invokespecial 80	ct/ar:g	()V
    //   98: getstatic 21	ct/ar:k	Lct/ar;
    //   101: invokespecial 82	ct/ar:h	()V
    //   104: getstatic 21	ct/ar:k	Lct/ar;
    //   107: aload_0
    //   108: invokestatic 87	ct/aq:c	(Landroid/content/Context;)Ljava/lang/String;
    //   111: invokespecial 89	ct/ar:c	(Ljava/lang/String;)V
    //   114: getstatic 21	ct/ar:k	Lct/ar;
    //   117: astore_2
    //   118: aload_0
    //   119: invokestatic 54	ct/as:a	(Landroid/content/Context;)Lct/as;
    //   122: pop
    //   123: aload_2
    //   124: aload_0
    //   125: invokestatic 91	ct/as:b	(Landroid/content/Context;)Ljava/lang/String;
    //   128: invokespecial 93	ct/ar:d	(Ljava/lang/String;)V
    //   131: getstatic 21	ct/ar:k	Lct/ar;
    //   134: astore_2
    //   135: aload_0
    //   136: invokestatic 54	ct/as:a	(Landroid/content/Context;)Lct/as;
    //   139: pop
    //   140: aload_2
    //   141: aload_0
    //   142: invokestatic 94	ct/as:c	(Landroid/content/Context;)Ljava/lang/String;
    //   145: putfield 37	ct/ar:a	Ljava/lang/String;
    //   148: getstatic 21	ct/ar:k	Lct/ar;
    //   151: astore_2
    //   152: aload_0
    //   153: invokestatic 54	ct/as:a	(Landroid/content/Context;)Lct/as;
    //   156: pop
    //   157: aload_2
    //   158: aload_0
    //   159: invokestatic 96	ct/as:e	(Landroid/content/Context;)Ljava/lang/String;
    //   162: putfield 39	ct/ar:b	Ljava/lang/String;
    //   165: getstatic 21	ct/ar:k	Lct/ar;
    //   168: astore_2
    //   169: aload_0
    //   170: invokestatic 54	ct/as:a	(Landroid/content/Context;)Lct/as;
    //   173: pop
    //   174: aload_2
    //   175: aload_0
    //   176: invokestatic 98	ct/as:d	(Landroid/content/Context;)Ljava/lang/String;
    //   179: putfield 41	ct/ar:c	Ljava/lang/String;
    //   182: getstatic 21	ct/ar:k	Lct/ar;
    //   185: invokestatic 102	ct/p:g	()Ljava/lang/String;
    //   188: invokespecial 104	ct/ar:e	(Ljava/lang/String;)V
    //   191: getstatic 21	ct/ar:k	Lct/ar;
    //   194: aload_0
    //   195: invokestatic 106	ct/aq:a	(Landroid/content/Context;)Ljava/lang/String;
    //   198: invokespecial 108	ct/ar:b	(Ljava/lang/String;)V
    //   201: getstatic 21	ct/ar:k	Lct/ar;
    //   204: astore_2
    //   205: aload_0
    //   206: invokestatic 54	ct/as:a	(Landroid/content/Context;)Lct/as;
    //   209: pop
    //   210: aload_2
    //   211: invokestatic 110	ct/as:d	()Ljava/lang/String;
    //   214: putfield 45	ct/ar:d	Ljava/lang/String;
    //   217: getstatic 21	ct/ar:k	Lct/ar;
    //   220: astore_2
    //   221: aload_0
    //   222: invokestatic 54	ct/as:a	(Landroid/content/Context;)Lct/as;
    //   225: pop
    //   226: aload_2
    //   227: invokestatic 60	ct/as:a	()Ljava/lang/String;
    //   230: putfield 47	ct/ar:e	Ljava/lang/String;
    //   233: aload_1
    //   234: monitorexit
    //   235: ldc 2
    //   237: monitorexit
    //   238: return
    //   239: astore_0
    //   240: aload_1
    //   241: monitorexit
    //   242: aload_0
    //   243: athrow
    //   244: astore_0
    //   245: ldc 2
    //   247: monitorexit
    //   248: aload_0
    //   249: athrow
    // Local variable table:
    //   start	length	slot	name	signature
    //   0	250	0	paramContext	android.content.Context
    //   32	195	2	localar2	ar
    //   45	41	3	localStringBuffer	StringBuffer
    // Exception table:
    //   from	to	target	type
    //   29	235	239	finally
    //   7	23	244	finally
    //   23	29	244	finally
    //   240	244	244	finally
  }
  
  private void a(String paramString)
  {
    try
    {
      this.f = paramString;
      return;
    }
    finally
    {
      paramString = finally;
      throw paramString;
    }
  }
  
  private void b(String paramString)
  {
    try
    {
      this.g = paramString;
      return;
    }
    finally
    {
      paramString = finally;
      throw paramString;
    }
  }
  
  private void c(String paramString)
  {
    try
    {
      this.h = paramString;
      return;
    }
    finally
    {
      paramString = finally;
      throw paramString;
    }
  }
  
  private void d(String paramString)
  {
    try
    {
      this.i = paramString;
      return;
    }
    finally
    {
      paramString = finally;
      throw paramString;
    }
  }
  
  private void e(String paramString)
  {
    try
    {
      this.j = paramString;
      return;
    }
    finally
    {
      paramString = finally;
      throw paramString;
    }
  }
  
  public static ar f()
  {
    try
    {
      ar localar = k;
      return localar;
    }
    finally
    {
      localObject = finally;
      throw ((Throwable)localObject);
    }
  }
  
  private void g() {}
  
  private void h() {}
  
  public final String a()
  {
    try
    {
      String str = this.f;
      return str;
    }
    finally
    {
      localObject = finally;
      throw ((Throwable)localObject);
    }
  }
  
  public final String b()
  {
    try
    {
      String str = this.g;
      return str;
    }
    finally
    {
      localObject = finally;
      throw ((Throwable)localObject);
    }
  }
  
  public final String c()
  {
    try
    {
      String str = this.h;
      return str;
    }
    finally
    {
      localObject = finally;
      throw ((Throwable)localObject);
    }
  }
  
  public final String d()
  {
    try
    {
      String str = this.i;
      return str;
    }
    finally
    {
      localObject = finally;
      throw ((Throwable)localObject);
    }
  }
  
  public final String e()
  {
    try
    {
      String str = this.j;
      return str;
    }
    finally
    {
      localObject = finally;
      throw ((Throwable)localObject);
    }
  }
}


/* Location:              E:\apk\QQ_91\classes3-dex2jar.jar!\ct\ar.class
 * Java compiler version: 6 (50.0)
 * JD-Core Version:       0.7.1
 */