package ct;

import android.text.TextUtils;
import java.net.MalformedURLException;
import java.net.URL;
import org.apache.http.impl.client.DefaultHttpClient;

public final class x
{
  private DefaultHttpClient a = null;
  
  public static z a(String paramString, byte[] paramArrayOfByte)
    throws ah
  {
    try
    {
      URL localURL = new URL(be.c(paramString));
      int i = localURL.getPort();
      ad localad = new ad(localURL.getHost(), new int[] { i });
      if ((!TextUtils.isEmpty(paramString)) && (paramString.toLowerCase().startsWith("https://"))) {
        localad.a = true;
      }
      localad.f = localURL.getFile();
      localad.j = paramArrayOfByte;
      return localad;
    }
    catch (MalformedURLException paramArrayOfByte)
    {
      paramArrayOfByte.printStackTrace();
      throw new ah("url format error:" + paramString);
    }
  }
  
  /* Error */
  private DefaultHttpClient a(ad paramad)
  {
    // Byte code:
    //   0: iconst_5
    //   1: istore 4
    //   3: bipush 15
    //   5: istore 5
    //   7: aload_0
    //   8: getfield 12	ct/x:a	Lorg/apache/http/impl/client/DefaultHttpClient;
    //   11: ifnonnull +134 -> 145
    //   14: new 97	org/apache/http/params/BasicHttpParams
    //   17: dup
    //   18: invokespecial 98	org/apache/http/params/BasicHttpParams:<init>	()V
    //   21: astore_2
    //   22: aload_2
    //   23: iconst_0
    //   24: invokestatic 104	org/apache/http/client/params/HttpClientParams:setRedirecting	(Lorg/apache/http/params/HttpParams;Z)V
    //   27: aload_0
    //   28: new 106	org/apache/http/impl/client/DefaultHttpClient
    //   31: dup
    //   32: aload_2
    //   33: invokespecial 109	org/apache/http/impl/client/DefaultHttpClient:<init>	(Lorg/apache/http/params/HttpParams;)V
    //   36: putfield 12	ct/x:a	Lorg/apache/http/impl/client/DefaultHttpClient;
    //   39: aload_1
    //   40: getfield 62	ct/ad:a	Z
    //   43: ifeq +217 -> 260
    //   46: invokestatic 114	java/security/KeyStore:getDefaultType	()Ljava/lang/String;
    //   49: invokestatic 118	java/security/KeyStore:getInstance	(Ljava/lang/String;)Ljava/security/KeyStore;
    //   52: astore_3
    //   53: aload_3
    //   54: aconst_null
    //   55: aconst_null
    //   56: invokevirtual 122	java/security/KeyStore:load	(Ljava/io/InputStream;[C)V
    //   59: new 124	ct/bd
    //   62: dup
    //   63: aload_3
    //   64: aload_1
    //   65: getfield 127	ct/ad:e	Ljava/lang/String;
    //   68: invokespecial 130	ct/bd:<init>	(Ljava/security/KeyStore;Ljava/lang/String;)V
    //   71: astore_1
    //   72: aload_1
    //   73: getstatic 136	org/apache/http/conn/ssl/SSLSocketFactory:STRICT_HOSTNAME_VERIFIER	Lorg/apache/http/conn/ssl/X509HostnameVerifier;
    //   76: invokevirtual 140	org/apache/http/conn/ssl/SSLSocketFactory:setHostnameVerifier	(Lorg/apache/http/conn/ssl/X509HostnameVerifier;)V
    //   79: new 142	org/apache/http/conn/scheme/SchemeRegistry
    //   82: dup
    //   83: invokespecial 143	org/apache/http/conn/scheme/SchemeRegistry:<init>	()V
    //   86: astore_3
    //   87: aload_3
    //   88: new 145	org/apache/http/conn/scheme/Scheme
    //   91: dup
    //   92: ldc -109
    //   94: aload_1
    //   95: sipush 443
    //   98: invokespecial 150	org/apache/http/conn/scheme/Scheme:<init>	(Ljava/lang/String;Lorg/apache/http/conn/scheme/SocketFactory;I)V
    //   101: invokevirtual 154	org/apache/http/conn/scheme/SchemeRegistry:register	(Lorg/apache/http/conn/scheme/Scheme;)Lorg/apache/http/conn/scheme/Scheme;
    //   104: pop
    //   105: aload_3
    //   106: new 145	org/apache/http/conn/scheme/Scheme
    //   109: dup
    //   110: ldc -100
    //   112: invokestatic 162	org/apache/http/conn/scheme/PlainSocketFactory:getSocketFactory	()Lorg/apache/http/conn/scheme/PlainSocketFactory;
    //   115: bipush 80
    //   117: invokespecial 150	org/apache/http/conn/scheme/Scheme:<init>	(Ljava/lang/String;Lorg/apache/http/conn/scheme/SocketFactory;I)V
    //   120: invokevirtual 154	org/apache/http/conn/scheme/SchemeRegistry:register	(Lorg/apache/http/conn/scheme/Scheme;)Lorg/apache/http/conn/scheme/Scheme;
    //   123: pop
    //   124: aload_0
    //   125: new 106	org/apache/http/impl/client/DefaultHttpClient
    //   128: dup
    //   129: new 164	org/apache/http/impl/conn/tsccm/ThreadSafeClientConnManager
    //   132: dup
    //   133: aload_2
    //   134: aload_3
    //   135: invokespecial 167	org/apache/http/impl/conn/tsccm/ThreadSafeClientConnManager:<init>	(Lorg/apache/http/params/HttpParams;Lorg/apache/http/conn/scheme/SchemeRegistry;)V
    //   138: aload_2
    //   139: invokespecial 170	org/apache/http/impl/client/DefaultHttpClient:<init>	(Lorg/apache/http/conn/ClientConnectionManager;Lorg/apache/http/params/HttpParams;)V
    //   142: putfield 12	ct/x:a	Lorg/apache/http/impl/client/DefaultHttpClient;
    //   145: aload_0
    //   146: getfield 12	ct/x:a	Lorg/apache/http/impl/client/DefaultHttpClient;
    //   149: invokestatic 175	ct/bb:a	(Lorg/apache/http/client/HttpClient;)V
    //   152: aload_0
    //   153: getfield 12	ct/x:a	Lorg/apache/http/impl/client/DefaultHttpClient;
    //   156: astore_1
    //   157: invokestatic 178	ct/bb:f	()Z
    //   160: ifeq +115 -> 275
    //   163: iconst_5
    //   164: istore 5
    //   166: aload_1
    //   167: invokeinterface 184 1 0
    //   172: ldc -70
    //   174: iload 5
    //   176: sipush 1000
    //   179: imul
    //   180: invokestatic 192	java/lang/Integer:valueOf	(I)Ljava/lang/Integer;
    //   183: invokeinterface 198 3 0
    //   188: pop
    //   189: aload_1
    //   190: invokeinterface 184 1 0
    //   195: ldc -56
    //   197: iload 4
    //   199: sipush 1000
    //   202: imul
    //   203: invokestatic 192	java/lang/Integer:valueOf	(I)Ljava/lang/Integer;
    //   206: invokeinterface 198 3 0
    //   211: pop
    //   212: aload_0
    //   213: getfield 12	ct/x:a	Lorg/apache/http/impl/client/DefaultHttpClient;
    //   216: new 202	org/apache/http/impl/client/DefaultHttpRequestRetryHandler
    //   219: dup
    //   220: iconst_0
    //   221: iconst_0
    //   222: invokespecial 205	org/apache/http/impl/client/DefaultHttpRequestRetryHandler:<init>	(IZ)V
    //   225: invokevirtual 209	org/apache/http/impl/client/DefaultHttpClient:setHttpRequestRetryHandler	(Lorg/apache/http/client/HttpRequestRetryHandler;)V
    //   228: aload_0
    //   229: getfield 12	ct/x:a	Lorg/apache/http/impl/client/DefaultHttpClient;
    //   232: new 211	ct/ac
    //   235: dup
    //   236: invokespecial 212	ct/ac:<init>	()V
    //   239: invokevirtual 216	org/apache/http/impl/client/DefaultHttpClient:setKeepAliveStrategy	(Lorg/apache/http/conn/ConnectionKeepAliveStrategy;)V
    //   242: aload_0
    //   243: getfield 12	ct/x:a	Lorg/apache/http/impl/client/DefaultHttpClient;
    //   246: areturn
    //   247: astore_1
    //   248: aload_1
    //   249: invokevirtual 217	java/lang/Exception:printStackTrace	()V
    //   252: aload_0
    //   253: aconst_null
    //   254: putfield 12	ct/x:a	Lorg/apache/http/impl/client/DefaultHttpClient;
    //   257: goto -112 -> 145
    //   260: aload_0
    //   261: new 106	org/apache/http/impl/client/DefaultHttpClient
    //   264: dup
    //   265: aload_2
    //   266: invokespecial 109	org/apache/http/impl/client/DefaultHttpClient:<init>	(Lorg/apache/http/params/HttpParams;)V
    //   269: putfield 12	ct/x:a	Lorg/apache/http/impl/client/DefaultHttpClient;
    //   272: goto -127 -> 145
    //   275: invokestatic 220	ct/bb:h	()Z
    //   278: ifeq +10 -> 288
    //   281: bipush 15
    //   283: istore 4
    //   285: goto -119 -> 166
    //   288: invokestatic 223	ct/bb:g	()Z
    //   291: ifeq +14 -> 305
    //   294: bipush 10
    //   296: istore 4
    //   298: goto -132 -> 166
    //   301: astore_1
    //   302: goto -60 -> 242
    //   305: bipush 20
    //   307: istore 4
    //   309: bipush 10
    //   311: istore 5
    //   313: goto -147 -> 166
    // Local variable table:
    //   start	length	slot	name	signature
    //   0	316	0	this	x
    //   0	316	1	paramad	ad
    //   21	245	2	localBasicHttpParams	org.apache.http.params.BasicHttpParams
    //   52	83	3	localObject	Object
    //   1	307	4	i	int
    //   5	307	5	j	int
    // Exception table:
    //   from	to	target	type
    //   46	145	247	java/lang/Exception
    //   228	242	301	java/lang/Throwable
  }
  
  private static boolean a(long paramLong)
  {
    if (bb.f()) {
      if (System.currentTimeMillis() - paramLong <= 6000L) {}
    }
    do
    {
      do
      {
        return true;
        return false;
        if (!bb.h()) {
          break;
        }
      } while (System.currentTimeMillis() - paramLong > 10000L);
      return false;
    } while (System.currentTimeMillis() - paramLong > 10000L);
    return false;
  }
  
  /* Error */
  private ae b(ad paramad)
  {
    // Byte code:
    //   0: new 240	ct/ae
    //   3: dup
    //   4: invokespecial 241	ct/ae:<init>	()V
    //   7: astore 6
    //   9: new 243	ct/ab
    //   12: dup
    //   13: aload_1
    //   14: invokespecial 246	ct/ab:<init>	(Lct/ad;)V
    //   17: astore 17
    //   19: aload 17
    //   21: getfield 249	ct/ab:c	Ljava/util/List;
    //   24: astore 18
    //   26: aload 17
    //   28: getfield 251	ct/ab:b	Ljava/lang/String;
    //   31: astore 19
    //   33: aload 18
    //   35: invokeinterface 256 1 0
    //   40: istore 28
    //   42: aload 18
    //   44: invokeinterface 256 1 0
    //   49: istore 29
    //   51: iconst_0
    //   52: istore 24
    //   54: ldc_w 258
    //   57: astore 5
    //   59: iconst_0
    //   60: istore 38
    //   62: invokestatic 230	java/lang/System:currentTimeMillis	()J
    //   65: aload_1
    //   66: getfield 262	ct/ad:k	J
    //   69: lsub
    //   70: l2i
    //   71: istore 30
    //   73: ldc_w 258
    //   76: astore_3
    //   77: iconst_0
    //   78: istore 25
    //   80: iconst_0
    //   81: istore 22
    //   83: iload 24
    //   85: aload_1
    //   86: getfield 266	ct/ad:n	I
    //   89: if_icmpgt +5534 -> 5623
    //   92: iload 22
    //   94: ifne +5529 -> 5623
    //   97: invokestatic 230	java/lang/System:currentTimeMillis	()J
    //   100: lstore 33
    //   102: aload_1
    //   103: getfield 269	ct/ad:p	Z
    //   106: istore 37
    //   108: new 240	ct/ae
    //   111: dup
    //   112: invokespecial 241	ct/ae:<init>	()V
    //   115: astore 7
    //   117: new 271	ct/af
    //   120: dup
    //   121: invokespecial 272	ct/af:<init>	()V
    //   124: astore 16
    //   126: aload 16
    //   128: aload 19
    //   130: putfield 275	ct/af:y	Ljava/lang/String;
    //   133: aload 16
    //   135: iload 30
    //   137: putfield 278	ct/af:i	I
    //   140: aload 16
    //   142: aload 17
    //   144: getfield 281	ct/ab:a	Lct/s;
    //   147: putfield 283	ct/af:b	Lct/s;
    //   150: aconst_null
    //   151: astore 6
    //   153: aconst_null
    //   154: astore 8
    //   156: aconst_null
    //   157: astore 15
    //   159: aconst_null
    //   160: astore 14
    //   162: iconst_0
    //   163: istore 37
    //   165: iload 24
    //   167: aload_1
    //   168: getfield 266	ct/ad:n	I
    //   171: if_icmpne +6 -> 177
    //   174: iconst_1
    //   175: istore 37
    //   177: iload 24
    //   179: iload 29
    //   181: irem
    //   182: istore 23
    //   184: iload 23
    //   186: iload 28
    //   188: iconst_1
    //   189: isub
    //   190: if_icmpge +31 -> 221
    //   193: aload 16
    //   195: iconst_1
    //   196: putfield 286	ct/af:x	Z
    //   199: aload_1
    //   200: ldc_w 288
    //   203: aload_1
    //   204: getfield 127	ct/ad:e	Ljava/lang/String;
    //   207: invokevirtual 291	ct/ad:a	(Ljava/lang/String;Ljava/lang/String;)V
    //   210: aload_1
    //   211: ldc_w 293
    //   214: aload_1
    //   215: getfield 127	ct/ad:e	Ljava/lang/String;
    //   218: invokevirtual 291	ct/ad:a	(Ljava/lang/String;Ljava/lang/String;)V
    //   221: aload 18
    //   223: iload 23
    //   225: invokeinterface 297 2 0
    //   230: checkcast 299	ct/s
    //   233: astore 13
    //   235: aload 16
    //   237: aload 13
    //   239: putfield 300	ct/af:a	Lct/s;
    //   242: aload 16
    //   244: aload_1
    //   245: getfield 302	ct/ad:c	Ljava/lang/String;
    //   248: putfield 303	ct/af:c	Ljava/lang/String;
    //   251: aload 16
    //   253: aload_1
    //   254: getfield 62	ct/ad:a	Z
    //   257: putfield 306	ct/af:D	Z
    //   260: aload 16
    //   262: aload_1
    //   263: getfield 266	ct/ad:n	I
    //   266: putfield 309	ct/af:u	I
    //   269: invokestatic 230	java/lang/System:currentTimeMillis	()J
    //   272: aload_1
    //   273: getfield 262	ct/ad:k	J
    //   276: lsub
    //   277: aload_1
    //   278: getfield 312	ct/ad:m	I
    //   281: i2l
    //   282: lcmp
    //   283: ifle +5702 -> 5985
    //   286: aload 18
    //   288: aload 18
    //   290: invokeinterface 256 1 0
    //   295: iconst_1
    //   296: isub
    //   297: invokeinterface 297 2 0
    //   302: checkcast 299	ct/s
    //   305: astore 13
    //   307: iconst_1
    //   308: istore 23
    //   310: iconst_1
    //   311: istore 26
    //   313: iconst_1
    //   314: istore 22
    //   316: aload 16
    //   318: iconst_1
    //   319: putfield 315	ct/af:A	Z
    //   322: iload 22
    //   324: istore 23
    //   326: iload 22
    //   328: istore 26
    //   330: aload 5
    //   332: invokestatic 48	android/text/TextUtils:isEmpty	(Ljava/lang/CharSequence;)Z
    //   335: ifeq +1083 -> 1418
    //   338: iload 22
    //   340: istore 23
    //   342: iload 22
    //   344: istore 26
    //   346: aload_1
    //   347: getfield 62	ct/ad:a	Z
    //   350: ifne +943 -> 1293
    //   353: iload 22
    //   355: istore 23
    //   357: iload 22
    //   359: istore 26
    //   361: aload 13
    //   363: getfield 317	ct/s:b	I
    //   366: iconst_m1
    //   367: if_icmpeq +893 -> 1260
    //   370: iload 22
    //   372: istore 23
    //   374: iload 22
    //   376: istore 26
    //   378: new 78	java/lang/StringBuilder
    //   381: dup
    //   382: ldc_w 319
    //   385: invokespecial 81	java/lang/StringBuilder:<init>	(Ljava/lang/String;)V
    //   388: aload 13
    //   390: getfield 321	ct/s:a	Ljava/lang/String;
    //   393: invokevirtual 85	java/lang/StringBuilder:append	(Ljava/lang/String;)Ljava/lang/StringBuilder;
    //   396: ldc_w 323
    //   399: invokevirtual 85	java/lang/StringBuilder:append	(Ljava/lang/String;)Ljava/lang/StringBuilder;
    //   402: aload 13
    //   404: getfield 317	ct/s:b	I
    //   407: invokevirtual 326	java/lang/StringBuilder:append	(I)Ljava/lang/StringBuilder;
    //   410: invokevirtual 88	java/lang/StringBuilder:toString	()Ljava/lang/String;
    //   413: astore_2
    //   414: iload 22
    //   416: istore 23
    //   418: iload 22
    //   420: istore 26
    //   422: aload_1
    //   423: getfield 69	ct/ad:f	Ljava/lang/String;
    //   426: astore 9
    //   428: aload_2
    //   429: astore 4
    //   431: iload 22
    //   433: istore 23
    //   435: iload 22
    //   437: istore 26
    //   439: aload 9
    //   441: invokestatic 48	android/text/TextUtils:isEmpty	(Ljava/lang/CharSequence;)Z
    //   444: ifne +51 -> 495
    //   447: iload 22
    //   449: istore 23
    //   451: iload 22
    //   453: istore 26
    //   455: aload 9
    //   457: ldc_w 328
    //   460: invokevirtual 59	java/lang/String:startsWith	(Ljava/lang/String;)Z
    //   463: ifeq +917 -> 1380
    //   466: iload 22
    //   468: istore 23
    //   470: iload 22
    //   472: istore 26
    //   474: new 78	java/lang/StringBuilder
    //   477: dup
    //   478: invokespecial 329	java/lang/StringBuilder:<init>	()V
    //   481: aload_2
    //   482: invokevirtual 85	java/lang/StringBuilder:append	(Ljava/lang/String;)Ljava/lang/StringBuilder;
    //   485: aload 9
    //   487: invokevirtual 85	java/lang/StringBuilder:append	(Ljava/lang/String;)Ljava/lang/StringBuilder;
    //   490: invokevirtual 88	java/lang/StringBuilder:toString	()Ljava/lang/String;
    //   493: astore 4
    //   495: iload 22
    //   497: istore 23
    //   499: iload 22
    //   501: istore 26
    //   503: aload 16
    //   505: aload 4
    //   507: putfield 332	ct/af:d	Ljava/lang/String;
    //   510: aload 5
    //   512: astore_2
    //   513: aload_2
    //   514: astore 10
    //   516: aload_3
    //   517: astore 12
    //   519: aload 14
    //   521: astore 6
    //   523: aload_2
    //   524: astore 11
    //   526: aload_3
    //   527: astore 9
    //   529: aload 15
    //   531: astore 8
    //   533: new 78	java/lang/StringBuilder
    //   536: dup
    //   537: ldc_w 334
    //   540: invokespecial 81	java/lang/StringBuilder:<init>	(Ljava/lang/String;)V
    //   543: iload 24
    //   545: invokevirtual 326	java/lang/StringBuilder:append	(I)Ljava/lang/StringBuilder;
    //   548: ldc_w 336
    //   551: invokevirtual 85	java/lang/StringBuilder:append	(Ljava/lang/String;)Ljava/lang/StringBuilder;
    //   554: aload 4
    //   556: invokevirtual 85	java/lang/StringBuilder:append	(Ljava/lang/String;)Ljava/lang/StringBuilder;
    //   559: ldc_w 338
    //   562: invokevirtual 85	java/lang/StringBuilder:append	(Ljava/lang/String;)Ljava/lang/StringBuilder;
    //   565: iload 38
    //   567: invokevirtual 341	java/lang/StringBuilder:append	(Z)Ljava/lang/StringBuilder;
    //   570: ldc_w 343
    //   573: invokevirtual 85	java/lang/StringBuilder:append	(Ljava/lang/String;)Ljava/lang/StringBuilder;
    //   576: aload 13
    //   578: invokevirtual 346	java/lang/StringBuilder:append	(Ljava/lang/Object;)Ljava/lang/StringBuilder;
    //   581: pop
    //   582: aload_2
    //   583: astore 10
    //   585: aload_3
    //   586: astore 12
    //   588: aload 14
    //   590: astore 6
    //   592: aload_2
    //   593: astore 11
    //   595: aload_3
    //   596: astore 9
    //   598: aload 15
    //   600: astore 8
    //   602: invokestatic 350	ct/bc:a	()V
    //   605: aload_2
    //   606: astore 10
    //   608: aload_3
    //   609: astore 12
    //   611: aload 14
    //   613: astore 6
    //   615: aload_2
    //   616: astore 11
    //   618: aload_3
    //   619: astore 9
    //   621: aload 15
    //   623: astore 8
    //   625: new 352	org/apache/http/client/methods/HttpPost
    //   628: dup
    //   629: aload 4
    //   631: invokespecial 353	org/apache/http/client/methods/HttpPost:<init>	(Ljava/lang/String;)V
    //   634: astore 20
    //   636: aload_2
    //   637: astore 10
    //   639: aload_3
    //   640: astore 12
    //   642: aload 14
    //   644: astore 6
    //   646: aload_2
    //   647: astore 11
    //   649: aload_3
    //   650: astore 9
    //   652: aload 15
    //   654: astore 8
    //   656: new 355	java/util/HashMap
    //   659: dup
    //   660: invokespecial 356	java/util/HashMap:<init>	()V
    //   663: astore 5
    //   665: aload_2
    //   666: astore 10
    //   668: aload_3
    //   669: astore 12
    //   671: aload 14
    //   673: astore 6
    //   675: aload_2
    //   676: astore 11
    //   678: aload_3
    //   679: astore 9
    //   681: aload 15
    //   683: astore 8
    //   685: aload 5
    //   687: aload_1
    //   688: getfield 359	ct/ad:i	Ljava/util/Map;
    //   691: invokeinterface 365 2 0
    //   696: aload_2
    //   697: astore 10
    //   699: aload_3
    //   700: astore 12
    //   702: aload 14
    //   704: astore 6
    //   706: aload_2
    //   707: astore 11
    //   709: aload_3
    //   710: astore 9
    //   712: aload 15
    //   714: astore 8
    //   716: aload 5
    //   718: invokeinterface 366 1 0
    //   723: ifle +779 -> 1502
    //   726: iload 38
    //   728: ifne +774 -> 1502
    //   731: aload_2
    //   732: astore 10
    //   734: aload_3
    //   735: astore 12
    //   737: aload 14
    //   739: astore 6
    //   741: aload_2
    //   742: astore 11
    //   744: aload_3
    //   745: astore 9
    //   747: aload 15
    //   749: astore 8
    //   751: aload 5
    //   753: invokeinterface 370 1 0
    //   758: invokeinterface 376 1 0
    //   763: astore 13
    //   765: aload_2
    //   766: astore 10
    //   768: aload_3
    //   769: astore 12
    //   771: aload 14
    //   773: astore 6
    //   775: aload_2
    //   776: astore 11
    //   778: aload_3
    //   779: astore 9
    //   781: aload 15
    //   783: astore 8
    //   785: aload 13
    //   787: invokeinterface 381 1 0
    //   792: ifeq +650 -> 1442
    //   795: aload_2
    //   796: astore 10
    //   798: aload_3
    //   799: astore 12
    //   801: aload 14
    //   803: astore 6
    //   805: aload_2
    //   806: astore 11
    //   808: aload_3
    //   809: astore 9
    //   811: aload 15
    //   813: astore 8
    //   815: aload 13
    //   817: invokeinterface 385 1 0
    //   822: checkcast 50	java/lang/String
    //   825: astore 21
    //   827: aload_2
    //   828: astore 10
    //   830: aload_3
    //   831: astore 12
    //   833: aload 14
    //   835: astore 6
    //   837: aload_2
    //   838: astore 11
    //   840: aload_3
    //   841: astore 9
    //   843: aload 15
    //   845: astore 8
    //   847: aload 20
    //   849: aload 21
    //   851: aload 5
    //   853: aload 21
    //   855: invokeinterface 388 2 0
    //   860: checkcast 50	java/lang/String
    //   863: invokeinterface 393 3 0
    //   868: goto -103 -> 765
    //   871: astore 5
    //   873: aload_3
    //   874: astore 6
    //   876: iconst_3
    //   877: istore 26
    //   879: iload 22
    //   881: istore 23
    //   883: aconst_null
    //   884: astore_3
    //   885: iload 26
    //   887: istore 22
    //   889: aload_2
    //   890: astore 4
    //   892: aload 6
    //   894: astore_2
    //   895: invokestatic 395	ct/bc:d	()V
    //   898: aload 16
    //   900: aload 5
    //   902: invokevirtual 399	java/lang/Object:getClass	()Ljava/lang/Class;
    //   905: invokevirtual 404	java/lang/Class:getSimpleName	()Ljava/lang/String;
    //   908: putfield 407	ct/af:q	Ljava/lang/String;
    //   911: aload 16
    //   913: new 78	java/lang/StringBuilder
    //   916: dup
    //   917: invokespecial 329	java/lang/StringBuilder:<init>	()V
    //   920: iload 22
    //   922: invokevirtual 326	java/lang/StringBuilder:append	(I)Ljava/lang/StringBuilder;
    //   925: ldc_w 409
    //   928: invokevirtual 85	java/lang/StringBuilder:append	(Ljava/lang/String;)Ljava/lang/StringBuilder;
    //   931: aload 5
    //   933: invokestatic 412	ct/be:a	(Ljava/lang/Exception;)Ljava/lang/String;
    //   936: invokevirtual 85	java/lang/StringBuilder:append	(Ljava/lang/String;)Ljava/lang/StringBuilder;
    //   939: invokevirtual 88	java/lang/StringBuilder:toString	()Ljava/lang/String;
    //   942: putfield 415	ct/af:r	Ljava/lang/String;
    //   945: invokestatic 417	ct/bb:e	()Z
    //   948: ifeq +4504 -> 5452
    //   951: aload 5
    //   953: instanceof 419
    //   956: ifeq +4365 -> 5321
    //   959: bipush -10
    //   961: istore 22
    //   963: aload 7
    //   965: iload 22
    //   967: putfield 421	ct/ae:a	I
    //   970: aload 16
    //   972: getfield 415	ct/af:r	Ljava/lang/String;
    //   975: ldc_w 423
    //   978: invokevirtual 426	java/lang/String:contains	(Ljava/lang/CharSequence;)Z
    //   981: ifeq +10 -> 991
    //   984: aload 7
    //   986: bipush -18
    //   988: putfield 421	ct/ae:a	I
    //   991: aload 16
    //   993: new 78	java/lang/StringBuilder
    //   996: dup
    //   997: invokespecial 329	java/lang/StringBuilder:<init>	()V
    //   1000: aload_1
    //   1001: getfield 427	ct/ad:q	Ljava/lang/String;
    //   1004: invokevirtual 85	java/lang/StringBuilder:append	(Ljava/lang/String;)Ljava/lang/StringBuilder;
    //   1007: ldc_w 429
    //   1010: invokevirtual 85	java/lang/StringBuilder:append	(Ljava/lang/String;)Ljava/lang/StringBuilder;
    //   1013: iload 24
    //   1015: invokevirtual 326	java/lang/StringBuilder:append	(I)Ljava/lang/StringBuilder;
    //   1018: invokevirtual 88	java/lang/StringBuilder:toString	()Ljava/lang/String;
    //   1021: putfield 431	ct/af:p	Ljava/lang/String;
    //   1024: aload 16
    //   1026: iload 24
    //   1028: putfield 434	ct/af:s	I
    //   1031: aload 4
    //   1033: invokestatic 48	android/text/TextUtils:isEmpty	(Ljava/lang/CharSequence;)Z
    //   1036: ifeq +4423 -> 5459
    //   1039: iload 24
    //   1041: iconst_1
    //   1042: iadd
    //   1043: istore 25
    //   1045: iconst_0
    //   1046: istore 22
    //   1048: invokestatic 438	ct/p:b	()Ljava/lang/String;
    //   1051: invokestatic 48	android/text/TextUtils:isEmpty	(Ljava/lang/CharSequence;)Z
    //   1054: ifne +161 -> 1215
    //   1057: aload 7
    //   1059: getfield 421	ct/ae:a	I
    //   1062: bipush -21
    //   1064: if_icmpeq +151 -> 1215
    //   1067: aload 7
    //   1069: invokestatic 230	java/lang/System:currentTimeMillis	()J
    //   1072: aload_1
    //   1073: getfield 262	ct/ad:k	J
    //   1076: lsub
    //   1077: l2i
    //   1078: putfield 440	ct/ae:f	I
    //   1081: aload 16
    //   1083: aload 7
    //   1085: getfield 421	ct/ae:a	I
    //   1088: putfield 442	ct/af:k	I
    //   1091: aload 16
    //   1093: aload_2
    //   1094: putfield 445	ct/af:C	Ljava/lang/String;
    //   1097: aload 16
    //   1099: aload 7
    //   1101: getfield 440	ct/ae:f	I
    //   1104: putfield 448	ct/af:l	I
    //   1107: aload 16
    //   1109: invokestatic 230	java/lang/System:currentTimeMillis	()J
    //   1112: lload 33
    //   1114: lsub
    //   1115: l2i
    //   1116: putfield 449	ct/af:m	I
    //   1119: aload 16
    //   1121: aload 4
    //   1123: putfield 450	ct/af:f	Ljava/lang/String;
    //   1126: aload_1
    //   1127: getfield 73	ct/ad:j	[B
    //   1130: ifnull +4369 -> 5499
    //   1133: aload 16
    //   1135: aload_1
    //   1136: getfield 73	ct/ad:j	[B
    //   1139: arraylength
    //   1140: i2l
    //   1141: putfield 452	ct/af:n	J
    //   1144: aload 16
    //   1146: iload 37
    //   1148: putfield 455	ct/af:z	Z
    //   1151: iload 37
    //   1153: ifeq +17 -> 1170
    //   1156: aload 16
    //   1158: getfield 442	ct/af:k	I
    //   1161: ifeq +9 -> 1170
    //   1164: aload 16
    //   1166: iconst_1
    //   1167: putfield 458	ct/af:w	I
    //   1170: aload 16
    //   1172: aload_1
    //   1173: getfield 460	ct/ad:h	Z
    //   1176: putfield 463	ct/af:B	Z
    //   1179: invokestatic 468	ct/o:a	()Lct/o;
    //   1182: new 470	ct/ag
    //   1185: dup
    //   1186: aload 16
    //   1188: invokespecial 473	ct/ag:<init>	(Lct/af;)V
    //   1191: invokevirtual 476	ct/o:a	(Ljava/lang/Runnable;)V
    //   1194: aload_1
    //   1195: aload 16
    //   1197: invokevirtual 478	ct/ad:a	(Lct/af;)V
    //   1200: aload 16
    //   1202: invokevirtual 479	ct/af:toString	()Ljava/lang/String;
    //   1205: pop
    //   1206: aload 16
    //   1208: invokevirtual 479	ct/af:toString	()Ljava/lang/String;
    //   1211: pop
    //   1212: invokestatic 481	ct/bc:b	()V
    //   1215: aload_3
    //   1216: ifnull +9 -> 1225
    //   1219: aload_1
    //   1220: getfield 269	ct/ad:p	Z
    //   1223: istore 37
    //   1225: lload 33
    //   1227: invokestatic 483	ct/x:a	(J)Z
    //   1230: istore 37
    //   1232: aload 7
    //   1234: getfield 421	ct/ae:a	I
    //   1237: bipush -4
    //   1239: if_icmpeq +18 -> 1257
    //   1242: aload 7
    //   1244: getfield 421	ct/ae:a	I
    //   1247: bipush -17
    //   1249: if_icmpeq +8 -> 1257
    //   1252: iload 37
    //   1254: ifeq +4264 -> 5518
    //   1257: aload 7
    //   1259: areturn
    //   1260: iload 22
    //   1262: istore 23
    //   1264: iload 22
    //   1266: istore 26
    //   1268: new 78	java/lang/StringBuilder
    //   1271: dup
    //   1272: ldc_w 319
    //   1275: invokespecial 81	java/lang/StringBuilder:<init>	(Ljava/lang/String;)V
    //   1278: aload 13
    //   1280: getfield 321	ct/s:a	Ljava/lang/String;
    //   1283: invokevirtual 85	java/lang/StringBuilder:append	(Ljava/lang/String;)Ljava/lang/StringBuilder;
    //   1286: invokevirtual 88	java/lang/StringBuilder:toString	()Ljava/lang/String;
    //   1289: astore_2
    //   1290: goto -876 -> 414
    //   1293: iload 22
    //   1295: istore 23
    //   1297: iload 22
    //   1299: istore 26
    //   1301: aload 13
    //   1303: getfield 317	ct/s:b	I
    //   1306: iconst_m1
    //   1307: if_icmpeq +41 -> 1348
    //   1310: iload 22
    //   1312: istore 23
    //   1314: iload 22
    //   1316: istore 26
    //   1318: new 78	java/lang/StringBuilder
    //   1321: dup
    //   1322: ldc 55
    //   1324: invokespecial 81	java/lang/StringBuilder:<init>	(Ljava/lang/String;)V
    //   1327: aload 13
    //   1329: getfield 321	ct/s:a	Ljava/lang/String;
    //   1332: invokevirtual 85	java/lang/StringBuilder:append	(Ljava/lang/String;)Ljava/lang/StringBuilder;
    //   1335: ldc_w 485
    //   1338: invokevirtual 85	java/lang/StringBuilder:append	(Ljava/lang/String;)Ljava/lang/StringBuilder;
    //   1341: invokevirtual 88	java/lang/StringBuilder:toString	()Ljava/lang/String;
    //   1344: astore_2
    //   1345: goto -931 -> 414
    //   1348: iload 22
    //   1350: istore 23
    //   1352: iload 22
    //   1354: istore 26
    //   1356: new 78	java/lang/StringBuilder
    //   1359: dup
    //   1360: ldc 55
    //   1362: invokespecial 81	java/lang/StringBuilder:<init>	(Ljava/lang/String;)V
    //   1365: aload 13
    //   1367: getfield 321	ct/s:a	Ljava/lang/String;
    //   1370: invokevirtual 85	java/lang/StringBuilder:append	(Ljava/lang/String;)Ljava/lang/StringBuilder;
    //   1373: invokevirtual 88	java/lang/StringBuilder:toString	()Ljava/lang/String;
    //   1376: astore_2
    //   1377: goto -963 -> 414
    //   1380: iload 22
    //   1382: istore 23
    //   1384: iload 22
    //   1386: istore 26
    //   1388: new 78	java/lang/StringBuilder
    //   1391: dup
    //   1392: invokespecial 329	java/lang/StringBuilder:<init>	()V
    //   1395: aload_2
    //   1396: invokevirtual 85	java/lang/StringBuilder:append	(Ljava/lang/String;)Ljava/lang/StringBuilder;
    //   1399: ldc_w 328
    //   1402: invokevirtual 85	java/lang/StringBuilder:append	(Ljava/lang/String;)Ljava/lang/StringBuilder;
    //   1405: aload 9
    //   1407: invokevirtual 85	java/lang/StringBuilder:append	(Ljava/lang/String;)Ljava/lang/StringBuilder;
    //   1410: invokevirtual 88	java/lang/StringBuilder:toString	()Ljava/lang/String;
    //   1413: astore 4
    //   1415: goto -920 -> 495
    //   1418: iload 22
    //   1420: istore 23
    //   1422: iload 22
    //   1424: istore 26
    //   1426: aload 16
    //   1428: aload 5
    //   1430: putfield 450	ct/af:f	Ljava/lang/String;
    //   1433: aconst_null
    //   1434: astore_2
    //   1435: aload 5
    //   1437: astore 4
    //   1439: goto -926 -> 513
    //   1442: aload_2
    //   1443: astore 10
    //   1445: aload_3
    //   1446: astore 12
    //   1448: aload 14
    //   1450: astore 6
    //   1452: aload_2
    //   1453: astore 11
    //   1455: aload_3
    //   1456: astore 9
    //   1458: aload 15
    //   1460: astore 8
    //   1462: getstatic 487	ct/bb:d	Z
    //   1465: ifeq +37 -> 1502
    //   1468: aload_2
    //   1469: astore 10
    //   1471: aload_3
    //   1472: astore 12
    //   1474: aload 14
    //   1476: astore 6
    //   1478: aload_2
    //   1479: astore 11
    //   1481: aload_3
    //   1482: astore 9
    //   1484: aload 15
    //   1486: astore 8
    //   1488: aload 20
    //   1490: ldc_w 489
    //   1493: aload_1
    //   1494: getfield 127	ct/ad:e	Ljava/lang/String;
    //   1497: invokeinterface 393 3 0
    //   1502: aload_2
    //   1503: astore 10
    //   1505: aload_3
    //   1506: astore 12
    //   1508: aload 14
    //   1510: astore 6
    //   1512: aload_2
    //   1513: astore 11
    //   1515: aload_3
    //   1516: astore 9
    //   1518: aload 15
    //   1520: astore 8
    //   1522: aload 20
    //   1524: ldc_w 491
    //   1527: new 78	java/lang/StringBuilder
    //   1530: dup
    //   1531: ldc_w 493
    //   1534: invokespecial 81	java/lang/StringBuilder:<init>	(Ljava/lang/String;)V
    //   1537: invokestatic 495	ct/p:f	()Ljava/lang/String;
    //   1540: invokevirtual 85	java/lang/StringBuilder:append	(Ljava/lang/String;)Ljava/lang/StringBuilder;
    //   1543: ldc_w 497
    //   1546: invokevirtual 85	java/lang/StringBuilder:append	(Ljava/lang/String;)Ljava/lang/StringBuilder;
    //   1549: aload_1
    //   1550: getfield 427	ct/ad:q	Ljava/lang/String;
    //   1553: invokevirtual 85	java/lang/StringBuilder:append	(Ljava/lang/String;)Ljava/lang/StringBuilder;
    //   1556: ldc_w 429
    //   1559: invokevirtual 85	java/lang/StringBuilder:append	(Ljava/lang/String;)Ljava/lang/StringBuilder;
    //   1562: iload 24
    //   1564: invokevirtual 326	java/lang/StringBuilder:append	(I)Ljava/lang/StringBuilder;
    //   1567: invokevirtual 88	java/lang/StringBuilder:toString	()Ljava/lang/String;
    //   1570: invokeinterface 393 3 0
    //   1575: iload 38
    //   1577: ifeq +500 -> 2077
    //   1580: aload_2
    //   1581: astore 10
    //   1583: aload_3
    //   1584: astore 12
    //   1586: aload 14
    //   1588: astore 6
    //   1590: aload_2
    //   1591: astore 11
    //   1593: aload_3
    //   1594: astore 9
    //   1596: aload 15
    //   1598: astore 8
    //   1600: aload 5
    //   1602: invokeinterface 370 1 0
    //   1607: invokeinterface 376 1 0
    //   1612: astore 13
    //   1614: aload_2
    //   1615: astore 10
    //   1617: aload_3
    //   1618: astore 12
    //   1620: aload 14
    //   1622: astore 6
    //   1624: aload_2
    //   1625: astore 11
    //   1627: aload_3
    //   1628: astore 9
    //   1630: aload 15
    //   1632: astore 8
    //   1634: aload 13
    //   1636: invokeinterface 381 1 0
    //   1641: ifeq +375 -> 2016
    //   1644: aload_2
    //   1645: astore 10
    //   1647: aload_3
    //   1648: astore 12
    //   1650: aload 14
    //   1652: astore 6
    //   1654: aload_2
    //   1655: astore 11
    //   1657: aload_3
    //   1658: astore 9
    //   1660: aload 15
    //   1662: astore 8
    //   1664: aload 13
    //   1666: invokeinterface 385 1 0
    //   1671: checkcast 50	java/lang/String
    //   1674: astore 21
    //   1676: aload_2
    //   1677: astore 10
    //   1679: aload_3
    //   1680: astore 12
    //   1682: aload 14
    //   1684: astore 6
    //   1686: aload_2
    //   1687: astore 11
    //   1689: aload_3
    //   1690: astore 9
    //   1692: aload 15
    //   1694: astore 8
    //   1696: aload 20
    //   1698: aload 21
    //   1700: aload 5
    //   1702: aload 21
    //   1704: invokeinterface 388 2 0
    //   1709: checkcast 50	java/lang/String
    //   1712: invokeinterface 393 3 0
    //   1717: goto -103 -> 1614
    //   1720: astore_2
    //   1721: aload 12
    //   1723: astore_2
    //   1724: aload 10
    //   1726: astore_3
    //   1727: aload 6
    //   1729: astore 5
    //   1731: aload 16
    //   1733: new 78	java/lang/StringBuilder
    //   1736: dup
    //   1737: invokespecial 329	java/lang/StringBuilder:<init>	()V
    //   1740: aload_1
    //   1741: getfield 427	ct/ad:q	Ljava/lang/String;
    //   1744: invokevirtual 85	java/lang/StringBuilder:append	(Ljava/lang/String;)Ljava/lang/StringBuilder;
    //   1747: ldc_w 429
    //   1750: invokevirtual 85	java/lang/StringBuilder:append	(Ljava/lang/String;)Ljava/lang/StringBuilder;
    //   1753: iload 24
    //   1755: invokevirtual 326	java/lang/StringBuilder:append	(I)Ljava/lang/StringBuilder;
    //   1758: invokevirtual 88	java/lang/StringBuilder:toString	()Ljava/lang/String;
    //   1761: putfield 431	ct/af:p	Ljava/lang/String;
    //   1764: aload 16
    //   1766: iload 24
    //   1768: putfield 434	ct/af:s	I
    //   1771: aload_3
    //   1772: invokestatic 48	android/text/TextUtils:isEmpty	(Ljava/lang/CharSequence;)Z
    //   1775: ifeq +3772 -> 5547
    //   1778: iload 24
    //   1780: iconst_1
    //   1781: iadd
    //   1782: istore 25
    //   1784: iconst_0
    //   1785: istore 23
    //   1787: invokestatic 438	ct/p:b	()Ljava/lang/String;
    //   1790: invokestatic 48	android/text/TextUtils:isEmpty	(Ljava/lang/CharSequence;)Z
    //   1793: ifne +160 -> 1953
    //   1796: aload 7
    //   1798: getfield 421	ct/ae:a	I
    //   1801: bipush -21
    //   1803: if_icmpeq +150 -> 1953
    //   1806: aload 7
    //   1808: invokestatic 230	java/lang/System:currentTimeMillis	()J
    //   1811: aload_1
    //   1812: getfield 262	ct/ad:k	J
    //   1815: lsub
    //   1816: l2i
    //   1817: putfield 440	ct/ae:f	I
    //   1820: aload 16
    //   1822: aload 7
    //   1824: getfield 421	ct/ae:a	I
    //   1827: putfield 442	ct/af:k	I
    //   1830: aload 16
    //   1832: aload_2
    //   1833: putfield 445	ct/af:C	Ljava/lang/String;
    //   1836: aload 16
    //   1838: aload 7
    //   1840: getfield 440	ct/ae:f	I
    //   1843: putfield 448	ct/af:l	I
    //   1846: aload 16
    //   1848: invokestatic 230	java/lang/System:currentTimeMillis	()J
    //   1851: lload 33
    //   1853: lsub
    //   1854: l2i
    //   1855: putfield 449	ct/af:m	I
    //   1858: aload 16
    //   1860: aload_3
    //   1861: putfield 450	ct/af:f	Ljava/lang/String;
    //   1864: aload_1
    //   1865: getfield 73	ct/ad:j	[B
    //   1868: ifnull +3719 -> 5587
    //   1871: aload 16
    //   1873: aload_1
    //   1874: getfield 73	ct/ad:j	[B
    //   1877: arraylength
    //   1878: i2l
    //   1879: putfield 452	ct/af:n	J
    //   1882: aload 16
    //   1884: iload 37
    //   1886: putfield 455	ct/af:z	Z
    //   1889: iload 37
    //   1891: ifeq +17 -> 1908
    //   1894: aload 16
    //   1896: getfield 442	ct/af:k	I
    //   1899: ifeq +9 -> 1908
    //   1902: aload 16
    //   1904: iconst_1
    //   1905: putfield 458	ct/af:w	I
    //   1908: aload 16
    //   1910: aload_1
    //   1911: getfield 460	ct/ad:h	Z
    //   1914: putfield 463	ct/af:B	Z
    //   1917: invokestatic 468	ct/o:a	()Lct/o;
    //   1920: new 470	ct/ag
    //   1923: dup
    //   1924: aload 16
    //   1926: invokespecial 473	ct/ag:<init>	(Lct/af;)V
    //   1929: invokevirtual 476	ct/o:a	(Ljava/lang/Runnable;)V
    //   1932: aload_1
    //   1933: aload 16
    //   1935: invokevirtual 478	ct/ad:a	(Lct/af;)V
    //   1938: aload 16
    //   1940: invokevirtual 479	ct/af:toString	()Ljava/lang/String;
    //   1943: pop
    //   1944: aload 16
    //   1946: invokevirtual 479	ct/af:toString	()Ljava/lang/String;
    //   1949: pop
    //   1950: invokestatic 481	ct/bc:b	()V
    //   1953: aload 5
    //   1955: ifnull +9 -> 1964
    //   1958: aload_1
    //   1959: getfield 269	ct/ad:p	Z
    //   1962: istore 37
    //   1964: lload 33
    //   1966: invokestatic 483	ct/x:a	(J)Z
    //   1969: istore 37
    //   1971: aload 7
    //   1973: getfield 421	ct/ae:a	I
    //   1976: bipush -4
    //   1978: if_icmpeq -721 -> 1257
    //   1981: aload 7
    //   1983: getfield 421	ct/ae:a	I
    //   1986: bipush -17
    //   1988: if_icmpeq -731 -> 1257
    //   1991: iload 37
    //   1993: ifne -736 -> 1257
    //   1996: aload 7
    //   1998: astore 6
    //   2000: aload_3
    //   2001: astore 5
    //   2003: iload 25
    //   2005: istore 24
    //   2007: aload_2
    //   2008: astore_3
    //   2009: iload 23
    //   2011: istore 25
    //   2013: goto -1930 -> 83
    //   2016: aload_2
    //   2017: astore 10
    //   2019: aload_3
    //   2020: astore 12
    //   2022: aload 14
    //   2024: astore 6
    //   2026: aload_2
    //   2027: astore 11
    //   2029: aload_3
    //   2030: astore 9
    //   2032: aload 15
    //   2034: astore 8
    //   2036: getstatic 487	ct/bb:d	Z
    //   2039: ifeq +38 -> 2077
    //   2042: aload_2
    //   2043: astore 10
    //   2045: aload_3
    //   2046: astore 12
    //   2048: aload 14
    //   2050: astore 6
    //   2052: aload_2
    //   2053: astore 11
    //   2055: aload_3
    //   2056: astore 9
    //   2058: aload 15
    //   2060: astore 8
    //   2062: aload 20
    //   2064: ldc_w 489
    //   2067: aload 4
    //   2069: invokestatic 499	ct/be:d	(Ljava/lang/String;)Ljava/lang/String;
    //   2072: invokeinterface 393 3 0
    //   2077: aload_2
    //   2078: astore 10
    //   2080: aload_3
    //   2081: astore 12
    //   2083: aload 14
    //   2085: astore 6
    //   2087: aload_2
    //   2088: astore 11
    //   2090: aload_3
    //   2091: astore 9
    //   2093: aload 15
    //   2095: astore 8
    //   2097: aload_1
    //   2098: getfield 73	ct/ad:j	[B
    //   2101: astore 4
    //   2103: aload 4
    //   2105: ifnull +66 -> 2171
    //   2108: aload_2
    //   2109: astore 10
    //   2111: aload_3
    //   2112: astore 12
    //   2114: aload 14
    //   2116: astore 6
    //   2118: aload_2
    //   2119: astore 11
    //   2121: aload_3
    //   2122: astore 9
    //   2124: aload 15
    //   2126: astore 8
    //   2128: aload 4
    //   2130: arraylength
    //   2131: ifle +40 -> 2171
    //   2134: aload_2
    //   2135: astore 10
    //   2137: aload_3
    //   2138: astore 12
    //   2140: aload 14
    //   2142: astore 6
    //   2144: aload_2
    //   2145: astore 11
    //   2147: aload_3
    //   2148: astore 9
    //   2150: aload 15
    //   2152: astore 8
    //   2154: aload 20
    //   2156: checkcast 352	org/apache/http/client/methods/HttpPost
    //   2159: new 501	org/apache/http/entity/ByteArrayEntity
    //   2162: dup
    //   2163: aload 4
    //   2165: invokespecial 504	org/apache/http/entity/ByteArrayEntity:<init>	([B)V
    //   2168: invokevirtual 508	org/apache/http/client/methods/HttpPost:setEntity	(Lorg/apache/http/HttpEntity;)V
    //   2171: aload_2
    //   2172: astore 10
    //   2174: aload_3
    //   2175: astore 12
    //   2177: aload 14
    //   2179: astore 6
    //   2181: aload_2
    //   2182: astore 11
    //   2184: aload_3
    //   2185: astore 9
    //   2187: aload 15
    //   2189: astore 8
    //   2191: aload_0
    //   2192: aload_1
    //   2193: invokespecial 510	ct/x:a	(Lct/ad;)Lorg/apache/http/impl/client/DefaultHttpClient;
    //   2196: astore 5
    //   2198: iconst_5
    //   2199: istore 26
    //   2201: aload_2
    //   2202: astore 10
    //   2204: aload_3
    //   2205: astore 12
    //   2207: aload 5
    //   2209: astore 6
    //   2211: aload_2
    //   2212: astore 11
    //   2214: aload_3
    //   2215: astore 9
    //   2217: aload 5
    //   2219: astore 8
    //   2221: iload 26
    //   2223: istore 23
    //   2225: aload_3
    //   2226: astore 13
    //   2228: aload 16
    //   2230: invokestatic 230	java/lang/System:currentTimeMillis	()J
    //   2233: lload 33
    //   2235: lsub
    //   2236: l2i
    //   2237: putfield 512	ct/af:g	I
    //   2240: aload_2
    //   2241: astore 10
    //   2243: aload_3
    //   2244: astore 12
    //   2246: aload 5
    //   2248: astore 6
    //   2250: aload_2
    //   2251: astore 11
    //   2253: aload_3
    //   2254: astore 9
    //   2256: aload 5
    //   2258: astore 8
    //   2260: iload 26
    //   2262: istore 23
    //   2264: aload_3
    //   2265: astore 13
    //   2267: invokestatic 230	java/lang/System:currentTimeMillis	()J
    //   2270: lstore 35
    //   2272: aload_2
    //   2273: astore 10
    //   2275: aload_3
    //   2276: astore 12
    //   2278: aload 5
    //   2280: astore 6
    //   2282: aload_2
    //   2283: astore 11
    //   2285: aload_3
    //   2286: astore 9
    //   2288: aload 5
    //   2290: astore 8
    //   2292: iload 26
    //   2294: istore 23
    //   2296: aload_3
    //   2297: astore 13
    //   2299: aload 5
    //   2301: aload 20
    //   2303: invokevirtual 516	org/apache/http/impl/client/DefaultHttpClient:execute	(Lorg/apache/http/client/methods/HttpUriRequest;)Lorg/apache/http/HttpResponse;
    //   2306: astore 14
    //   2308: aload_2
    //   2309: astore 10
    //   2311: aload_3
    //   2312: astore 12
    //   2314: aload 5
    //   2316: astore 6
    //   2318: aload_2
    //   2319: astore 11
    //   2321: aload_3
    //   2322: astore 9
    //   2324: aload 5
    //   2326: astore 8
    //   2328: iload 26
    //   2330: istore 23
    //   2332: aload_3
    //   2333: astore 13
    //   2335: aload 7
    //   2337: invokestatic 230	java/lang/System:currentTimeMillis	()J
    //   2340: lload 35
    //   2342: lsub
    //   2343: l2i
    //   2344: putfield 518	ct/ae:c	I
    //   2347: bipush 6
    //   2349: istore 26
    //   2351: aload_2
    //   2352: astore 10
    //   2354: aload_3
    //   2355: astore 12
    //   2357: aload 5
    //   2359: astore 6
    //   2361: aload_2
    //   2362: astore 11
    //   2364: aload_3
    //   2365: astore 9
    //   2367: aload 5
    //   2369: astore 8
    //   2371: iload 26
    //   2373: istore 23
    //   2375: aload_3
    //   2376: astore 13
    //   2378: new 78	java/lang/StringBuilder
    //   2381: dup
    //   2382: ldc_w 520
    //   2385: invokespecial 81	java/lang/StringBuilder:<init>	(Ljava/lang/String;)V
    //   2388: aload 7
    //   2390: getfield 518	ct/ae:c	I
    //   2393: invokevirtual 326	java/lang/StringBuilder:append	(I)Ljava/lang/StringBuilder;
    //   2396: pop
    //   2397: aload_2
    //   2398: astore 10
    //   2400: aload_3
    //   2401: astore 12
    //   2403: aload 5
    //   2405: astore 6
    //   2407: aload_2
    //   2408: astore 11
    //   2410: aload_3
    //   2411: astore 9
    //   2413: aload 5
    //   2415: astore 8
    //   2417: iload 26
    //   2419: istore 23
    //   2421: aload_3
    //   2422: astore 13
    //   2424: invokestatic 350	ct/bc:a	()V
    //   2427: aload_2
    //   2428: astore 10
    //   2430: aload_3
    //   2431: astore 12
    //   2433: aload 5
    //   2435: astore 6
    //   2437: aload_2
    //   2438: astore 11
    //   2440: aload_3
    //   2441: astore 9
    //   2443: aload 5
    //   2445: astore 8
    //   2447: iload 26
    //   2449: istore 23
    //   2451: aload_3
    //   2452: astore 13
    //   2454: aload 14
    //   2456: invokeinterface 526 1 0
    //   2461: invokeinterface 531 1 0
    //   2466: istore 27
    //   2468: aload_2
    //   2469: astore 10
    //   2471: aload_3
    //   2472: astore 12
    //   2474: aload 5
    //   2476: astore 6
    //   2478: aload_2
    //   2479: astore 11
    //   2481: aload_3
    //   2482: astore 9
    //   2484: aload 5
    //   2486: astore 8
    //   2488: iload 26
    //   2490: istore 23
    //   2492: aload_3
    //   2493: astore 13
    //   2495: aload 7
    //   2497: aload 14
    //   2499: putfield 534	ct/ae:e	Lorg/apache/http/HttpResponse;
    //   2502: aload_3
    //   2503: astore 4
    //   2505: aload 14
    //   2507: ifnull +90 -> 2597
    //   2510: aload_2
    //   2511: astore 10
    //   2513: aload_3
    //   2514: astore 12
    //   2516: aload 5
    //   2518: astore 6
    //   2520: aload_3
    //   2521: astore 4
    //   2523: aload_2
    //   2524: astore 11
    //   2526: aload_3
    //   2527: astore 9
    //   2529: aload 5
    //   2531: astore 8
    //   2533: iload 26
    //   2535: istore 23
    //   2537: aload_3
    //   2538: astore 13
    //   2540: aload 14
    //   2542: ldc_w 536
    //   2545: invokeinterface 540 2 0
    //   2550: ifnull +47 -> 2597
    //   2553: aload_2
    //   2554: astore 10
    //   2556: aload_3
    //   2557: astore 12
    //   2559: aload 5
    //   2561: astore 6
    //   2563: aload_2
    //   2564: astore 11
    //   2566: aload_3
    //   2567: astore 9
    //   2569: aload 5
    //   2571: astore 8
    //   2573: iload 26
    //   2575: istore 23
    //   2577: aload_3
    //   2578: astore 13
    //   2580: aload 14
    //   2582: ldc_w 536
    //   2585: invokeinterface 540 2 0
    //   2590: invokeinterface 545 1 0
    //   2595: astore 4
    //   2597: aload_2
    //   2598: astore 10
    //   2600: aload 4
    //   2602: astore 12
    //   2604: aload 5
    //   2606: astore 6
    //   2608: aload_2
    //   2609: astore 11
    //   2611: aload 4
    //   2613: astore 9
    //   2615: aload 5
    //   2617: astore 8
    //   2619: iload 26
    //   2621: istore 23
    //   2623: aload 4
    //   2625: astore 13
    //   2627: aload 16
    //   2629: aload 7
    //   2631: getfield 518	ct/ae:c	I
    //   2634: putfield 547	ct/af:h	I
    //   2637: bipush 7
    //   2639: istore 23
    //   2641: iload 27
    //   2643: lookupswitch	default:+3376->6019, 200:+421->3064, 204:+2581->5224, 301:+2086->4729, 302:+2086->4729, 303:+2086->4729, 307:+2086->4729, 408:+2581->5224, 502:+2581->5224, 503:+2581->5224, 504:+2581->5224
    //   2732: aload_2
    //   2733: astore 10
    //   2735: aload 4
    //   2737: astore 12
    //   2739: aload 5
    //   2741: astore 6
    //   2743: aload_2
    //   2744: astore 11
    //   2746: aload 4
    //   2748: astore 9
    //   2750: aload 5
    //   2752: astore 8
    //   2754: aload 4
    //   2756: astore 13
    //   2758: aload 7
    //   2760: iload 27
    //   2762: putfield 421	ct/ae:a	I
    //   2765: iload 37
    //   2767: istore 39
    //   2769: iload 38
    //   2771: istore 37
    //   2773: iload 39
    //   2775: istore 38
    //   2777: aload 16
    //   2779: new 78	java/lang/StringBuilder
    //   2782: dup
    //   2783: invokespecial 329	java/lang/StringBuilder:<init>	()V
    //   2786: aload_1
    //   2787: getfield 427	ct/ad:q	Ljava/lang/String;
    //   2790: invokevirtual 85	java/lang/StringBuilder:append	(Ljava/lang/String;)Ljava/lang/StringBuilder;
    //   2793: ldc_w 429
    //   2796: invokevirtual 85	java/lang/StringBuilder:append	(Ljava/lang/String;)Ljava/lang/StringBuilder;
    //   2799: iload 24
    //   2801: invokevirtual 326	java/lang/StringBuilder:append	(I)Ljava/lang/StringBuilder;
    //   2804: invokevirtual 88	java/lang/StringBuilder:toString	()Ljava/lang/String;
    //   2807: putfield 431	ct/af:p	Ljava/lang/String;
    //   2810: aload 16
    //   2812: iload 24
    //   2814: putfield 434	ct/af:s	I
    //   2817: aload_2
    //   2818: invokestatic 48	android/text/TextUtils:isEmpty	(Ljava/lang/CharSequence;)Z
    //   2821: ifeq +2451 -> 5272
    //   2824: iload 24
    //   2826: iconst_1
    //   2827: iadd
    //   2828: istore 24
    //   2830: iconst_0
    //   2831: istore 23
    //   2833: invokestatic 438	ct/p:b	()Ljava/lang/String;
    //   2836: invokestatic 48	android/text/TextUtils:isEmpty	(Ljava/lang/CharSequence;)Z
    //   2839: ifne +161 -> 3000
    //   2842: aload 7
    //   2844: getfield 421	ct/ae:a	I
    //   2847: bipush -21
    //   2849: if_icmpeq +151 -> 3000
    //   2852: aload 7
    //   2854: invokestatic 230	java/lang/System:currentTimeMillis	()J
    //   2857: aload_1
    //   2858: getfield 262	ct/ad:k	J
    //   2861: lsub
    //   2862: l2i
    //   2863: putfield 440	ct/ae:f	I
    //   2866: aload 16
    //   2868: aload 7
    //   2870: getfield 421	ct/ae:a	I
    //   2873: putfield 442	ct/af:k	I
    //   2876: aload 16
    //   2878: aload 4
    //   2880: putfield 445	ct/af:C	Ljava/lang/String;
    //   2883: aload 16
    //   2885: aload 7
    //   2887: getfield 440	ct/ae:f	I
    //   2890: putfield 448	ct/af:l	I
    //   2893: aload 16
    //   2895: invokestatic 230	java/lang/System:currentTimeMillis	()J
    //   2898: lload 33
    //   2900: lsub
    //   2901: l2i
    //   2902: putfield 449	ct/af:m	I
    //   2905: aload 16
    //   2907: aload_2
    //   2908: putfield 450	ct/af:f	Ljava/lang/String;
    //   2911: aload_1
    //   2912: getfield 73	ct/ad:j	[B
    //   2915: ifnull +2389 -> 5304
    //   2918: aload 16
    //   2920: aload_1
    //   2921: getfield 73	ct/ad:j	[B
    //   2924: arraylength
    //   2925: i2l
    //   2926: putfield 452	ct/af:n	J
    //   2929: aload 16
    //   2931: iload 38
    //   2933: putfield 455	ct/af:z	Z
    //   2936: iload 38
    //   2938: ifeq +17 -> 2955
    //   2941: aload 16
    //   2943: getfield 442	ct/af:k	I
    //   2946: ifeq +9 -> 2955
    //   2949: aload 16
    //   2951: iconst_1
    //   2952: putfield 458	ct/af:w	I
    //   2955: aload 16
    //   2957: aload_1
    //   2958: getfield 460	ct/ad:h	Z
    //   2961: putfield 463	ct/af:B	Z
    //   2964: invokestatic 468	ct/o:a	()Lct/o;
    //   2967: new 470	ct/ag
    //   2970: dup
    //   2971: aload 16
    //   2973: invokespecial 473	ct/ag:<init>	(Lct/af;)V
    //   2976: invokevirtual 476	ct/o:a	(Ljava/lang/Runnable;)V
    //   2979: aload_1
    //   2980: aload 16
    //   2982: invokevirtual 478	ct/ad:a	(Lct/af;)V
    //   2985: aload 16
    //   2987: invokevirtual 479	ct/af:toString	()Ljava/lang/String;
    //   2990: pop
    //   2991: aload 16
    //   2993: invokevirtual 479	ct/af:toString	()Ljava/lang/String;
    //   2996: pop
    //   2997: invokestatic 481	ct/bc:b	()V
    //   3000: aload 5
    //   3002: ifnull +9 -> 3011
    //   3005: aload_1
    //   3006: getfield 269	ct/ad:p	Z
    //   3009: istore 38
    //   3011: lload 33
    //   3013: invokestatic 483	ct/x:a	(J)Z
    //   3016: istore 38
    //   3018: aload 7
    //   3020: getfield 421	ct/ae:a	I
    //   3023: bipush -4
    //   3025: if_icmpeq -1768 -> 1257
    //   3028: aload 7
    //   3030: getfield 421	ct/ae:a	I
    //   3033: bipush -17
    //   3035: if_icmpeq -1778 -> 1257
    //   3038: iload 38
    //   3040: ifne -1783 -> 1257
    //   3043: aload 7
    //   3045: astore 6
    //   3047: aload_2
    //   3048: astore 5
    //   3050: iload 37
    //   3052: istore 38
    //   3054: aload 4
    //   3056: astore_3
    //   3057: iload 23
    //   3059: istore 25
    //   3061: goto -2978 -> 83
    //   3064: aload_2
    //   3065: astore 10
    //   3067: aload 4
    //   3069: astore 12
    //   3071: aload 5
    //   3073: astore 6
    //   3075: aload_2
    //   3076: astore 11
    //   3078: aload 4
    //   3080: astore 9
    //   3082: aload 5
    //   3084: astore 8
    //   3086: aload 4
    //   3088: astore 13
    //   3090: aload 14
    //   3092: invokeinterface 551 1 0
    //   3097: invokeinterface 557 1 0
    //   3102: astore_3
    //   3103: iconst_1
    //   3104: istore 39
    //   3106: bipush 8
    //   3108: istore 26
    //   3110: iload 26
    //   3112: istore 23
    //   3114: aload_1
    //   3115: getfield 559	ct/ad:g	Z
    //   3118: ifeq +1574 -> 4692
    //   3121: iconst_0
    //   3122: istore 27
    //   3124: iload 26
    //   3126: istore 23
    //   3128: aload_1
    //   3129: getfield 560	ct/ad:l	I
    //   3132: istore 31
    //   3134: iload 26
    //   3136: istore 23
    //   3138: iload 31
    //   3140: newarray <illegal type>
    //   3142: astore 6
    //   3144: iload 26
    //   3146: istore 23
    //   3148: invokestatic 230	java/lang/System:currentTimeMillis	()J
    //   3151: lstore 35
    //   3153: iload 27
    //   3155: iload 31
    //   3157: if_icmpge +441 -> 3598
    //   3160: iload 26
    //   3162: istore 23
    //   3164: aload_3
    //   3165: aload 6
    //   3167: iload 27
    //   3169: iload 31
    //   3171: iload 27
    //   3173: isub
    //   3174: invokevirtual 566	java/io/InputStream:read	([BII)I
    //   3177: istore 32
    //   3179: iload 32
    //   3181: iconst_m1
    //   3182: if_icmpeq +416 -> 3598
    //   3185: iload 27
    //   3187: iload 32
    //   3189: iadd
    //   3190: istore 27
    //   3192: goto -39 -> 3153
    //   3195: astore 6
    //   3197: iload 26
    //   3199: istore 23
    //   3201: aload 6
    //   3203: invokevirtual 567	java/lang/OutOfMemoryError:printStackTrace	()V
    //   3206: aload_3
    //   3207: invokevirtual 570	java/io/InputStream:close	()V
    //   3210: iload 26
    //   3212: istore 23
    //   3214: aload 7
    //   3216: bipush -8
    //   3218: putfield 421	ct/ae:a	I
    //   3221: iload 26
    //   3223: istore 23
    //   3225: aload 16
    //   3227: new 78	java/lang/StringBuilder
    //   3230: dup
    //   3231: ldc_w 572
    //   3234: invokespecial 81	java/lang/StringBuilder:<init>	(Ljava/lang/String;)V
    //   3237: iload 31
    //   3239: invokevirtual 326	java/lang/StringBuilder:append	(I)Ljava/lang/StringBuilder;
    //   3242: invokevirtual 88	java/lang/StringBuilder:toString	()Ljava/lang/String;
    //   3245: putfield 415	ct/af:r	Ljava/lang/String;
    //   3248: iload 26
    //   3250: istore 23
    //   3252: aload 16
    //   3254: iload 31
    //   3256: i2l
    //   3257: putfield 575	ct/af:o	J
    //   3260: aload 16
    //   3262: new 78	java/lang/StringBuilder
    //   3265: dup
    //   3266: invokespecial 329	java/lang/StringBuilder:<init>	()V
    //   3269: aload_1
    //   3270: getfield 427	ct/ad:q	Ljava/lang/String;
    //   3273: invokevirtual 85	java/lang/StringBuilder:append	(Ljava/lang/String;)Ljava/lang/StringBuilder;
    //   3276: ldc_w 429
    //   3279: invokevirtual 85	java/lang/StringBuilder:append	(Ljava/lang/String;)Ljava/lang/StringBuilder;
    //   3282: iload 24
    //   3284: invokevirtual 326	java/lang/StringBuilder:append	(I)Ljava/lang/StringBuilder;
    //   3287: invokevirtual 88	java/lang/StringBuilder:toString	()Ljava/lang/String;
    //   3290: putfield 431	ct/af:p	Ljava/lang/String;
    //   3293: aload 16
    //   3295: iload 24
    //   3297: putfield 434	ct/af:s	I
    //   3300: aload_2
    //   3301: invokestatic 48	android/text/TextUtils:isEmpty	(Ljava/lang/CharSequence;)Z
    //   3304: ifne +19 -> 3323
    //   3307: iload 25
    //   3309: iconst_1
    //   3310: iadd
    //   3311: bipush 6
    //   3313: if_icmple +10 -> 3323
    //   3316: aload 7
    //   3318: bipush -5
    //   3320: putfield 421	ct/ae:a	I
    //   3323: invokestatic 438	ct/p:b	()Ljava/lang/String;
    //   3326: invokestatic 48	android/text/TextUtils:isEmpty	(Ljava/lang/CharSequence;)Z
    //   3329: ifne +155 -> 3484
    //   3332: aload 7
    //   3334: getfield 421	ct/ae:a	I
    //   3337: bipush -21
    //   3339: if_icmpeq +145 -> 3484
    //   3342: aload 7
    //   3344: invokestatic 230	java/lang/System:currentTimeMillis	()J
    //   3347: aload_1
    //   3348: getfield 262	ct/ad:k	J
    //   3351: lsub
    //   3352: l2i
    //   3353: putfield 440	ct/ae:f	I
    //   3356: aload 16
    //   3358: aload 7
    //   3360: getfield 421	ct/ae:a	I
    //   3363: putfield 442	ct/af:k	I
    //   3366: aload 16
    //   3368: aload 4
    //   3370: putfield 445	ct/af:C	Ljava/lang/String;
    //   3373: aload 16
    //   3375: aload 7
    //   3377: getfield 440	ct/ae:f	I
    //   3380: putfield 448	ct/af:l	I
    //   3383: aload 16
    //   3385: invokestatic 230	java/lang/System:currentTimeMillis	()J
    //   3388: lload 33
    //   3390: lsub
    //   3391: l2i
    //   3392: putfield 449	ct/af:m	I
    //   3395: aload 16
    //   3397: aload_2
    //   3398: putfield 450	ct/af:f	Ljava/lang/String;
    //   3401: aload_1
    //   3402: getfield 73	ct/ad:j	[B
    //   3405: ifnull +176 -> 3581
    //   3408: aload 16
    //   3410: aload_1
    //   3411: getfield 73	ct/ad:j	[B
    //   3414: arraylength
    //   3415: i2l
    //   3416: putfield 452	ct/af:n	J
    //   3419: aload 16
    //   3421: iconst_1
    //   3422: putfield 455	ct/af:z	Z
    //   3425: aload 16
    //   3427: getfield 442	ct/af:k	I
    //   3430: ifeq +9 -> 3439
    //   3433: aload 16
    //   3435: iconst_1
    //   3436: putfield 458	ct/af:w	I
    //   3439: aload 16
    //   3441: aload_1
    //   3442: getfield 460	ct/ad:h	Z
    //   3445: putfield 463	ct/af:B	Z
    //   3448: invokestatic 468	ct/o:a	()Lct/o;
    //   3451: new 470	ct/ag
    //   3454: dup
    //   3455: aload 16
    //   3457: invokespecial 473	ct/ag:<init>	(Lct/af;)V
    //   3460: invokevirtual 476	ct/o:a	(Ljava/lang/Runnable;)V
    //   3463: aload_1
    //   3464: aload 16
    //   3466: invokevirtual 478	ct/ad:a	(Lct/af;)V
    //   3469: aload 16
    //   3471: invokevirtual 479	ct/af:toString	()Ljava/lang/String;
    //   3474: pop
    //   3475: aload 16
    //   3477: invokevirtual 479	ct/af:toString	()Ljava/lang/String;
    //   3480: pop
    //   3481: invokestatic 481	ct/bc:b	()V
    //   3484: aload 5
    //   3486: ifnull +9 -> 3495
    //   3489: aload_1
    //   3490: getfield 269	ct/ad:p	Z
    //   3493: istore 37
    //   3495: lload 33
    //   3497: invokestatic 483	ct/x:a	(J)Z
    //   3500: istore 37
    //   3502: aload 7
    //   3504: getfield 421	ct/ae:a	I
    //   3507: bipush -4
    //   3509: if_icmpeq -2252 -> 1257
    //   3512: aload 7
    //   3514: getfield 421	ct/ae:a	I
    //   3517: bipush -17
    //   3519: if_icmpeq -2262 -> 1257
    //   3522: iload 37
    //   3524: ifeq -2267 -> 1257
    //   3527: aload 7
    //   3529: areturn
    //   3530: astore_3
    //   3531: iload 26
    //   3533: istore 23
    //   3535: aload_3
    //   3536: invokevirtual 217	java/lang/Exception:printStackTrace	()V
    //   3539: goto -329 -> 3210
    //   3542: astore_3
    //   3543: iload 23
    //   3545: istore 26
    //   3547: aload_2
    //   3548: astore 8
    //   3550: iconst_1
    //   3551: istore 37
    //   3553: aload 5
    //   3555: astore 6
    //   3557: iload 22
    //   3559: istore 23
    //   3561: aload 4
    //   3563: astore_2
    //   3564: aload 8
    //   3566: astore 4
    //   3568: aload_3
    //   3569: astore 5
    //   3571: aload 6
    //   3573: astore_3
    //   3574: iload 26
    //   3576: istore 22
    //   3578: goto -2683 -> 895
    //   3581: aload 16
    //   3583: lconst_0
    //   3584: putfield 452	ct/af:n	J
    //   3587: goto -168 -> 3419
    //   3590: astore_2
    //   3591: aload_2
    //   3592: invokevirtual 576	java/lang/Throwable:printStackTrace	()V
    //   3595: goto -111 -> 3484
    //   3598: bipush 9
    //   3600: istore 26
    //   3602: iload 26
    //   3604: istore 23
    //   3606: aload 7
    //   3608: invokestatic 230	java/lang/System:currentTimeMillis	()J
    //   3611: lload 35
    //   3613: lsub
    //   3614: l2i
    //   3615: putfield 578	ct/ae:d	I
    //   3618: iload 26
    //   3620: istore 23
    //   3622: aload 16
    //   3624: aload 7
    //   3626: getfield 578	ct/ae:d	I
    //   3629: putfield 580	ct/af:j	I
    //   3632: iload 26
    //   3634: istore 23
    //   3636: aload 16
    //   3638: iload 27
    //   3640: i2l
    //   3641: putfield 575	ct/af:o	J
    //   3644: iload 27
    //   3646: iload 31
    //   3648: if_icmplt +346 -> 3994
    //   3651: iload 26
    //   3653: istore 23
    //   3655: aload 16
    //   3657: new 78	java/lang/StringBuilder
    //   3660: dup
    //   3661: ldc_w 582
    //   3664: invokespecial 81	java/lang/StringBuilder:<init>	(Ljava/lang/String;)V
    //   3667: iload 27
    //   3669: invokevirtual 326	java/lang/StringBuilder:append	(I)Ljava/lang/StringBuilder;
    //   3672: invokevirtual 88	java/lang/StringBuilder:toString	()Ljava/lang/String;
    //   3675: putfield 415	ct/af:r	Ljava/lang/String;
    //   3678: iload 26
    //   3680: istore 23
    //   3682: aload 7
    //   3684: iconst_m1
    //   3685: putfield 421	ct/ae:a	I
    //   3688: aload_3
    //   3689: invokevirtual 570	java/io/InputStream:close	()V
    //   3692: iload 26
    //   3694: istore 23
    //   3696: aload 7
    //   3698: getfield 421	ct/ae:a	I
    //   3701: ifne +2307 -> 6008
    //   3704: iload 26
    //   3706: istore 23
    //   3708: aload_1
    //   3709: getfield 269	ct/ad:p	Z
    //   3712: istore 37
    //   3714: iload 26
    //   3716: istore 23
    //   3718: aload 16
    //   3720: iconst_0
    //   3721: putfield 458	ct/af:w	I
    //   3724: aload 16
    //   3726: new 78	java/lang/StringBuilder
    //   3729: dup
    //   3730: invokespecial 329	java/lang/StringBuilder:<init>	()V
    //   3733: aload_1
    //   3734: getfield 427	ct/ad:q	Ljava/lang/String;
    //   3737: invokevirtual 85	java/lang/StringBuilder:append	(Ljava/lang/String;)Ljava/lang/StringBuilder;
    //   3740: ldc_w 429
    //   3743: invokevirtual 85	java/lang/StringBuilder:append	(Ljava/lang/String;)Ljava/lang/StringBuilder;
    //   3746: iload 24
    //   3748: invokevirtual 326	java/lang/StringBuilder:append	(I)Ljava/lang/StringBuilder;
    //   3751: invokevirtual 88	java/lang/StringBuilder:toString	()Ljava/lang/String;
    //   3754: putfield 431	ct/af:p	Ljava/lang/String;
    //   3757: aload 16
    //   3759: iload 24
    //   3761: putfield 434	ct/af:s	I
    //   3764: aload_2
    //   3765: invokestatic 48	android/text/TextUtils:isEmpty	(Ljava/lang/CharSequence;)Z
    //   3768: ifne +19 -> 3787
    //   3771: iload 25
    //   3773: iconst_1
    //   3774: iadd
    //   3775: bipush 6
    //   3777: if_icmple +10 -> 3787
    //   3780: aload 7
    //   3782: bipush -5
    //   3784: putfield 421	ct/ae:a	I
    //   3787: invokestatic 438	ct/p:b	()Ljava/lang/String;
    //   3790: invokestatic 48	android/text/TextUtils:isEmpty	(Ljava/lang/CharSequence;)Z
    //   3793: ifne +155 -> 3948
    //   3796: aload 7
    //   3798: getfield 421	ct/ae:a	I
    //   3801: bipush -21
    //   3803: if_icmpeq +145 -> 3948
    //   3806: aload 7
    //   3808: invokestatic 230	java/lang/System:currentTimeMillis	()J
    //   3811: aload_1
    //   3812: getfield 262	ct/ad:k	J
    //   3815: lsub
    //   3816: l2i
    //   3817: putfield 440	ct/ae:f	I
    //   3820: aload 16
    //   3822: aload 7
    //   3824: getfield 421	ct/ae:a	I
    //   3827: putfield 442	ct/af:k	I
    //   3830: aload 16
    //   3832: aload 4
    //   3834: putfield 445	ct/af:C	Ljava/lang/String;
    //   3837: aload 16
    //   3839: aload 7
    //   3841: getfield 440	ct/ae:f	I
    //   3844: putfield 448	ct/af:l	I
    //   3847: aload 16
    //   3849: invokestatic 230	java/lang/System:currentTimeMillis	()J
    //   3852: lload 33
    //   3854: lsub
    //   3855: l2i
    //   3856: putfield 449	ct/af:m	I
    //   3859: aload 16
    //   3861: aload_2
    //   3862: putfield 450	ct/af:f	Ljava/lang/String;
    //   3865: aload_1
    //   3866: getfield 73	ct/ad:j	[B
    //   3869: ifnull +843 -> 4712
    //   3872: aload 16
    //   3874: aload_1
    //   3875: getfield 73	ct/ad:j	[B
    //   3878: arraylength
    //   3879: i2l
    //   3880: putfield 452	ct/af:n	J
    //   3883: aload 16
    //   3885: iconst_1
    //   3886: putfield 455	ct/af:z	Z
    //   3889: aload 16
    //   3891: getfield 442	ct/af:k	I
    //   3894: ifeq +9 -> 3903
    //   3897: aload 16
    //   3899: iconst_1
    //   3900: putfield 458	ct/af:w	I
    //   3903: aload 16
    //   3905: aload_1
    //   3906: getfield 460	ct/ad:h	Z
    //   3909: putfield 463	ct/af:B	Z
    //   3912: invokestatic 468	ct/o:a	()Lct/o;
    //   3915: new 470	ct/ag
    //   3918: dup
    //   3919: aload 16
    //   3921: invokespecial 473	ct/ag:<init>	(Lct/af;)V
    //   3924: invokevirtual 476	ct/o:a	(Ljava/lang/Runnable;)V
    //   3927: aload_1
    //   3928: aload 16
    //   3930: invokevirtual 478	ct/ad:a	(Lct/af;)V
    //   3933: aload 16
    //   3935: invokevirtual 479	ct/af:toString	()Ljava/lang/String;
    //   3938: pop
    //   3939: aload 16
    //   3941: invokevirtual 479	ct/af:toString	()Ljava/lang/String;
    //   3944: pop
    //   3945: invokestatic 481	ct/bc:b	()V
    //   3948: aload 5
    //   3950: ifnull +9 -> 3959
    //   3953: aload_1
    //   3954: getfield 269	ct/ad:p	Z
    //   3957: istore 37
    //   3959: lload 33
    //   3961: invokestatic 483	ct/x:a	(J)Z
    //   3964: istore 37
    //   3966: aload 7
    //   3968: getfield 421	ct/ae:a	I
    //   3971: bipush -4
    //   3973: if_icmpeq -2716 -> 1257
    //   3976: aload 7
    //   3978: getfield 421	ct/ae:a	I
    //   3981: bipush -17
    //   3983: if_icmpeq -2726 -> 1257
    //   3986: iload 37
    //   3988: ifeq -2731 -> 1257
    //   3991: aload 7
    //   3993: areturn
    //   3994: iload 26
    //   3996: istore 23
    //   3998: aload 7
    //   4000: iload 27
    //   4002: newarray <illegal type>
    //   4004: putfield 584	ct/ae:b	[B
    //   4007: iload 26
    //   4009: istore 23
    //   4011: aload 6
    //   4013: iconst_0
    //   4014: aload 7
    //   4016: getfield 584	ct/ae:b	[B
    //   4019: iconst_0
    //   4020: iload 27
    //   4022: invokestatic 588	java/lang/System:arraycopy	(Ljava/lang/Object;ILjava/lang/Object;II)V
    //   4025: iload 26
    //   4027: istore 23
    //   4029: aload 7
    //   4031: iconst_0
    //   4032: putfield 421	ct/ae:a	I
    //   4035: goto -347 -> 3688
    //   4038: astore 6
    //   4040: iload 26
    //   4042: istore 23
    //   4044: aload 6
    //   4046: invokevirtual 567	java/lang/OutOfMemoryError:printStackTrace	()V
    //   4049: aload_3
    //   4050: invokevirtual 570	java/io/InputStream:close	()V
    //   4053: iload 26
    //   4055: istore 23
    //   4057: aload 7
    //   4059: bipush -8
    //   4061: putfield 421	ct/ae:a	I
    //   4064: iload 26
    //   4066: istore 23
    //   4068: aload 16
    //   4070: new 78	java/lang/StringBuilder
    //   4073: dup
    //   4074: ldc_w 572
    //   4077: invokespecial 81	java/lang/StringBuilder:<init>	(Ljava/lang/String;)V
    //   4080: iload 31
    //   4082: invokevirtual 326	java/lang/StringBuilder:append	(I)Ljava/lang/StringBuilder;
    //   4085: invokevirtual 88	java/lang/StringBuilder:toString	()Ljava/lang/String;
    //   4088: putfield 415	ct/af:r	Ljava/lang/String;
    //   4091: aload 16
    //   4093: new 78	java/lang/StringBuilder
    //   4096: dup
    //   4097: invokespecial 329	java/lang/StringBuilder:<init>	()V
    //   4100: aload_1
    //   4101: getfield 427	ct/ad:q	Ljava/lang/String;
    //   4104: invokevirtual 85	java/lang/StringBuilder:append	(Ljava/lang/String;)Ljava/lang/StringBuilder;
    //   4107: ldc_w 429
    //   4110: invokevirtual 85	java/lang/StringBuilder:append	(Ljava/lang/String;)Ljava/lang/StringBuilder;
    //   4113: iload 24
    //   4115: invokevirtual 326	java/lang/StringBuilder:append	(I)Ljava/lang/StringBuilder;
    //   4118: invokevirtual 88	java/lang/StringBuilder:toString	()Ljava/lang/String;
    //   4121: putfield 431	ct/af:p	Ljava/lang/String;
    //   4124: aload 16
    //   4126: iload 24
    //   4128: putfield 434	ct/af:s	I
    //   4131: aload_2
    //   4132: invokestatic 48	android/text/TextUtils:isEmpty	(Ljava/lang/CharSequence;)Z
    //   4135: ifne +19 -> 4154
    //   4138: iload 25
    //   4140: iconst_1
    //   4141: iadd
    //   4142: bipush 6
    //   4144: if_icmple +10 -> 4154
    //   4147: aload 7
    //   4149: bipush -5
    //   4151: putfield 421	ct/ae:a	I
    //   4154: invokestatic 438	ct/p:b	()Ljava/lang/String;
    //   4157: invokestatic 48	android/text/TextUtils:isEmpty	(Ljava/lang/CharSequence;)Z
    //   4160: ifne +155 -> 4315
    //   4163: aload 7
    //   4165: getfield 421	ct/ae:a	I
    //   4168: bipush -21
    //   4170: if_icmpeq +145 -> 4315
    //   4173: aload 7
    //   4175: invokestatic 230	java/lang/System:currentTimeMillis	()J
    //   4178: aload_1
    //   4179: getfield 262	ct/ad:k	J
    //   4182: lsub
    //   4183: l2i
    //   4184: putfield 440	ct/ae:f	I
    //   4187: aload 16
    //   4189: aload 7
    //   4191: getfield 421	ct/ae:a	I
    //   4194: putfield 442	ct/af:k	I
    //   4197: aload 16
    //   4199: aload 4
    //   4201: putfield 445	ct/af:C	Ljava/lang/String;
    //   4204: aload 16
    //   4206: aload 7
    //   4208: getfield 440	ct/ae:f	I
    //   4211: putfield 448	ct/af:l	I
    //   4214: aload 16
    //   4216: invokestatic 230	java/lang/System:currentTimeMillis	()J
    //   4219: lload 33
    //   4221: lsub
    //   4222: l2i
    //   4223: putfield 449	ct/af:m	I
    //   4226: aload 16
    //   4228: aload_2
    //   4229: putfield 450	ct/af:f	Ljava/lang/String;
    //   4232: aload_1
    //   4233: getfield 73	ct/ad:j	[B
    //   4236: ifnull +427 -> 4663
    //   4239: aload 16
    //   4241: aload_1
    //   4242: getfield 73	ct/ad:j	[B
    //   4245: arraylength
    //   4246: i2l
    //   4247: putfield 452	ct/af:n	J
    //   4250: aload 16
    //   4252: iconst_1
    //   4253: putfield 455	ct/af:z	Z
    //   4256: aload 16
    //   4258: getfield 442	ct/af:k	I
    //   4261: ifeq +9 -> 4270
    //   4264: aload 16
    //   4266: iconst_1
    //   4267: putfield 458	ct/af:w	I
    //   4270: aload 16
    //   4272: aload_1
    //   4273: getfield 460	ct/ad:h	Z
    //   4276: putfield 463	ct/af:B	Z
    //   4279: invokestatic 468	ct/o:a	()Lct/o;
    //   4282: new 470	ct/ag
    //   4285: dup
    //   4286: aload 16
    //   4288: invokespecial 473	ct/ag:<init>	(Lct/af;)V
    //   4291: invokevirtual 476	ct/o:a	(Ljava/lang/Runnable;)V
    //   4294: aload_1
    //   4295: aload 16
    //   4297: invokevirtual 478	ct/ad:a	(Lct/af;)V
    //   4300: aload 16
    //   4302: invokevirtual 479	ct/af:toString	()Ljava/lang/String;
    //   4305: pop
    //   4306: aload 16
    //   4308: invokevirtual 479	ct/af:toString	()Ljava/lang/String;
    //   4311: pop
    //   4312: invokestatic 481	ct/bc:b	()V
    //   4315: aload 5
    //   4317: ifnull +9 -> 4326
    //   4320: aload_1
    //   4321: getfield 269	ct/ad:p	Z
    //   4324: istore 37
    //   4326: lload 33
    //   4328: invokestatic 483	ct/x:a	(J)Z
    //   4331: istore 37
    //   4333: aload 7
    //   4335: getfield 421	ct/ae:a	I
    //   4338: bipush -4
    //   4340: if_icmpeq -3083 -> 1257
    //   4343: aload 7
    //   4345: getfield 421	ct/ae:a	I
    //   4348: bipush -17
    //   4350: if_icmpeq -3093 -> 1257
    //   4353: iload 37
    //   4355: ifeq -3098 -> 1257
    //   4358: aload 7
    //   4360: areturn
    //   4361: astore_3
    //   4362: iload 26
    //   4364: istore 23
    //   4366: aload_3
    //   4367: invokevirtual 217	java/lang/Exception:printStackTrace	()V
    //   4370: goto -317 -> 4053
    //   4373: astore 8
    //   4375: iconst_1
    //   4376: istore 37
    //   4378: aload 4
    //   4380: astore_3
    //   4381: aload_2
    //   4382: astore 6
    //   4384: aload 8
    //   4386: astore_2
    //   4387: aload 16
    //   4389: new 78	java/lang/StringBuilder
    //   4392: dup
    //   4393: invokespecial 329	java/lang/StringBuilder:<init>	()V
    //   4396: aload_1
    //   4397: getfield 427	ct/ad:q	Ljava/lang/String;
    //   4400: invokevirtual 85	java/lang/StringBuilder:append	(Ljava/lang/String;)Ljava/lang/StringBuilder;
    //   4403: ldc_w 429
    //   4406: invokevirtual 85	java/lang/StringBuilder:append	(Ljava/lang/String;)Ljava/lang/StringBuilder;
    //   4409: iload 24
    //   4411: invokevirtual 326	java/lang/StringBuilder:append	(I)Ljava/lang/StringBuilder;
    //   4414: invokevirtual 88	java/lang/StringBuilder:toString	()Ljava/lang/String;
    //   4417: putfield 431	ct/af:p	Ljava/lang/String;
    //   4420: aload 16
    //   4422: iload 24
    //   4424: putfield 434	ct/af:s	I
    //   4427: aload 6
    //   4429: invokestatic 48	android/text/TextUtils:isEmpty	(Ljava/lang/CharSequence;)Z
    //   4432: ifne +19 -> 4451
    //   4435: iload 25
    //   4437: iconst_1
    //   4438: iadd
    //   4439: bipush 6
    //   4441: if_icmple +10 -> 4451
    //   4444: aload 7
    //   4446: bipush -5
    //   4448: putfield 421	ct/ae:a	I
    //   4451: invokestatic 438	ct/p:b	()Ljava/lang/String;
    //   4454: invokestatic 48	android/text/TextUtils:isEmpty	(Ljava/lang/CharSequence;)Z
    //   4457: ifne +161 -> 4618
    //   4460: aload 7
    //   4462: getfield 421	ct/ae:a	I
    //   4465: bipush -21
    //   4467: if_icmpeq +151 -> 4618
    //   4470: aload 7
    //   4472: invokestatic 230	java/lang/System:currentTimeMillis	()J
    //   4475: aload_1
    //   4476: getfield 262	ct/ad:k	J
    //   4479: lsub
    //   4480: l2i
    //   4481: putfield 440	ct/ae:f	I
    //   4484: aload 16
    //   4486: aload 7
    //   4488: getfield 421	ct/ae:a	I
    //   4491: putfield 442	ct/af:k	I
    //   4494: aload 16
    //   4496: aload_3
    //   4497: putfield 445	ct/af:C	Ljava/lang/String;
    //   4500: aload 16
    //   4502: aload 7
    //   4504: getfield 440	ct/ae:f	I
    //   4507: putfield 448	ct/af:l	I
    //   4510: aload 16
    //   4512: invokestatic 230	java/lang/System:currentTimeMillis	()J
    //   4515: lload 33
    //   4517: lsub
    //   4518: l2i
    //   4519: putfield 449	ct/af:m	I
    //   4522: aload 16
    //   4524: aload 6
    //   4526: putfield 450	ct/af:f	Ljava/lang/String;
    //   4529: aload_1
    //   4530: getfield 73	ct/ad:j	[B
    //   4533: ifnull +1073 -> 5606
    //   4536: aload 16
    //   4538: aload_1
    //   4539: getfield 73	ct/ad:j	[B
    //   4542: arraylength
    //   4543: i2l
    //   4544: putfield 452	ct/af:n	J
    //   4547: aload 16
    //   4549: iload 37
    //   4551: putfield 455	ct/af:z	Z
    //   4554: iload 37
    //   4556: ifeq +17 -> 4573
    //   4559: aload 16
    //   4561: getfield 442	ct/af:k	I
    //   4564: ifeq +9 -> 4573
    //   4567: aload 16
    //   4569: iconst_1
    //   4570: putfield 458	ct/af:w	I
    //   4573: aload 16
    //   4575: aload_1
    //   4576: getfield 460	ct/ad:h	Z
    //   4579: putfield 463	ct/af:B	Z
    //   4582: invokestatic 468	ct/o:a	()Lct/o;
    //   4585: new 470	ct/ag
    //   4588: dup
    //   4589: aload 16
    //   4591: invokespecial 473	ct/ag:<init>	(Lct/af;)V
    //   4594: invokevirtual 476	ct/o:a	(Ljava/lang/Runnable;)V
    //   4597: aload_1
    //   4598: aload 16
    //   4600: invokevirtual 478	ct/ad:a	(Lct/af;)V
    //   4603: aload 16
    //   4605: invokevirtual 479	ct/af:toString	()Ljava/lang/String;
    //   4608: pop
    //   4609: aload 16
    //   4611: invokevirtual 479	ct/af:toString	()Ljava/lang/String;
    //   4614: pop
    //   4615: invokestatic 481	ct/bc:b	()V
    //   4618: aload 5
    //   4620: ifnull +9 -> 4629
    //   4623: aload_1
    //   4624: getfield 269	ct/ad:p	Z
    //   4627: istore 37
    //   4629: lload 33
    //   4631: invokestatic 483	ct/x:a	(J)Z
    //   4634: istore 37
    //   4636: aload 7
    //   4638: getfield 421	ct/ae:a	I
    //   4641: bipush -4
    //   4643: if_icmpeq -3386 -> 1257
    //   4646: aload 7
    //   4648: getfield 421	ct/ae:a	I
    //   4651: bipush -17
    //   4653: if_icmpeq -3396 -> 1257
    //   4656: iload 37
    //   4658: ifne -3401 -> 1257
    //   4661: aload_2
    //   4662: athrow
    //   4663: aload 16
    //   4665: lconst_0
    //   4666: putfield 452	ct/af:n	J
    //   4669: goto -419 -> 4250
    //   4672: astore_2
    //   4673: aload_2
    //   4674: invokevirtual 576	java/lang/Throwable:printStackTrace	()V
    //   4677: goto -362 -> 4315
    //   4680: astore_3
    //   4681: iload 26
    //   4683: istore 23
    //   4685: aload_3
    //   4686: invokevirtual 217	java/lang/Exception:printStackTrace	()V
    //   4689: goto -997 -> 3692
    //   4692: iload 26
    //   4694: istore 23
    //   4696: invokestatic 481	ct/bc:b	()V
    //   4699: iload 26
    //   4701: istore 23
    //   4703: aload 7
    //   4705: iconst_0
    //   4706: putfield 421	ct/ae:a	I
    //   4709: goto -1017 -> 3692
    //   4712: aload 16
    //   4714: lconst_0
    //   4715: putfield 452	ct/af:n	J
    //   4718: goto -835 -> 3883
    //   4721: astore_2
    //   4722: aload_2
    //   4723: invokevirtual 576	java/lang/Throwable:printStackTrace	()V
    //   4726: goto -778 -> 3948
    //   4729: aload_2
    //   4730: astore 10
    //   4732: aload 4
    //   4734: astore 12
    //   4736: aload 5
    //   4738: astore 6
    //   4740: aload_2
    //   4741: astore 11
    //   4743: aload 4
    //   4745: astore 9
    //   4747: aload 5
    //   4749: astore 8
    //   4751: aload 4
    //   4753: astore 13
    //   4755: aload 7
    //   4757: bipush -21
    //   4759: putfield 421	ct/ae:a	I
    //   4762: aload_2
    //   4763: astore 10
    //   4765: aload 4
    //   4767: astore 12
    //   4769: aload 5
    //   4771: astore 6
    //   4773: aload_2
    //   4774: astore 11
    //   4776: aload 4
    //   4778: astore 9
    //   4780: aload 5
    //   4782: astore 8
    //   4784: aload_2
    //   4785: astore_3
    //   4786: aload 14
    //   4788: ldc_w 590
    //   4791: invokeinterface 540 2 0
    //   4796: astore 13
    //   4798: aload 13
    //   4800: ifnull +1205 -> 6005
    //   4803: aload_2
    //   4804: astore 10
    //   4806: aload 4
    //   4808: astore 12
    //   4810: aload 5
    //   4812: astore 6
    //   4814: aload_2
    //   4815: astore 11
    //   4817: aload 4
    //   4819: astore 9
    //   4821: aload 5
    //   4823: astore 8
    //   4825: aload_2
    //   4826: astore_3
    //   4827: aload 13
    //   4829: invokeinterface 545 1 0
    //   4834: astore_2
    //   4835: aload_2
    //   4836: astore 13
    //   4838: aload_2
    //   4839: astore 10
    //   4841: aload 4
    //   4843: astore 12
    //   4845: aload 5
    //   4847: astore 6
    //   4849: aload_2
    //   4850: astore 11
    //   4852: aload 4
    //   4854: astore 9
    //   4856: aload 5
    //   4858: astore 8
    //   4860: aload_2
    //   4861: astore_3
    //   4862: invokestatic 481	ct/bc:b	()V
    //   4865: aload 13
    //   4867: astore_2
    //   4868: aload 16
    //   4870: iconst_1
    //   4871: putfield 592	ct/af:e	Z
    //   4874: aload_2
    //   4875: invokestatic 48	android/text/TextUtils:isEmpty	(Ljava/lang/CharSequence;)Z
    //   4878: istore 38
    //   4880: iload 38
    //   4882: ifeq +26 -> 4908
    //   4885: aload 7
    //   4887: bipush -6
    //   4889: putfield 421	ct/ae:a	I
    //   4892: aconst_null
    //   4893: astore_2
    //   4894: iconst_1
    //   4895: istore 39
    //   4897: iload 37
    //   4899: istore 38
    //   4901: iload 39
    //   4903: istore 37
    //   4905: goto -2128 -> 2777
    //   4908: aload_1
    //   4909: getfield 594	ct/ad:o	Z
    //   4912: ifne +1079 -> 5991
    //   4915: invokestatic 481	ct/bc:b	()V
    //   4918: aload 7
    //   4920: bipush -7
    //   4922: putfield 421	ct/ae:a	I
    //   4925: aload_1
    //   4926: getfield 269	ct/ad:p	Z
    //   4929: istore 38
    //   4931: aload 16
    //   4933: new 78	java/lang/StringBuilder
    //   4936: dup
    //   4937: invokespecial 329	java/lang/StringBuilder:<init>	()V
    //   4940: aload_1
    //   4941: getfield 427	ct/ad:q	Ljava/lang/String;
    //   4944: invokevirtual 85	java/lang/StringBuilder:append	(Ljava/lang/String;)Ljava/lang/StringBuilder;
    //   4947: ldc_w 429
    //   4950: invokevirtual 85	java/lang/StringBuilder:append	(Ljava/lang/String;)Ljava/lang/StringBuilder;
    //   4953: iload 24
    //   4955: invokevirtual 326	java/lang/StringBuilder:append	(I)Ljava/lang/StringBuilder;
    //   4958: invokevirtual 88	java/lang/StringBuilder:toString	()Ljava/lang/String;
    //   4961: putfield 431	ct/af:p	Ljava/lang/String;
    //   4964: aload 16
    //   4966: iload 24
    //   4968: putfield 434	ct/af:s	I
    //   4971: aload_2
    //   4972: invokestatic 48	android/text/TextUtils:isEmpty	(Ljava/lang/CharSequence;)Z
    //   4975: ifne +19 -> 4994
    //   4978: iload 25
    //   4980: iconst_1
    //   4981: iadd
    //   4982: bipush 6
    //   4984: if_icmple +10 -> 4994
    //   4987: aload 7
    //   4989: bipush -5
    //   4991: putfield 421	ct/ae:a	I
    //   4994: invokestatic 438	ct/p:b	()Ljava/lang/String;
    //   4997: invokestatic 48	android/text/TextUtils:isEmpty	(Ljava/lang/CharSequence;)Z
    //   5000: ifne +161 -> 5161
    //   5003: aload 7
    //   5005: getfield 421	ct/ae:a	I
    //   5008: bipush -21
    //   5010: if_icmpeq +151 -> 5161
    //   5013: aload 7
    //   5015: invokestatic 230	java/lang/System:currentTimeMillis	()J
    //   5018: aload_1
    //   5019: getfield 262	ct/ad:k	J
    //   5022: lsub
    //   5023: l2i
    //   5024: putfield 440	ct/ae:f	I
    //   5027: aload 16
    //   5029: aload 7
    //   5031: getfield 421	ct/ae:a	I
    //   5034: putfield 442	ct/af:k	I
    //   5037: aload 16
    //   5039: aload 4
    //   5041: putfield 445	ct/af:C	Ljava/lang/String;
    //   5044: aload 16
    //   5046: aload 7
    //   5048: getfield 440	ct/ae:f	I
    //   5051: putfield 448	ct/af:l	I
    //   5054: aload 16
    //   5056: invokestatic 230	java/lang/System:currentTimeMillis	()J
    //   5059: lload 33
    //   5061: lsub
    //   5062: l2i
    //   5063: putfield 449	ct/af:m	I
    //   5066: aload 16
    //   5068: aload_2
    //   5069: putfield 450	ct/af:f	Ljava/lang/String;
    //   5072: aload_1
    //   5073: getfield 73	ct/ad:j	[B
    //   5076: ifnull +131 -> 5207
    //   5079: aload 16
    //   5081: aload_1
    //   5082: getfield 73	ct/ad:j	[B
    //   5085: arraylength
    //   5086: i2l
    //   5087: putfield 452	ct/af:n	J
    //   5090: aload 16
    //   5092: iload 37
    //   5094: putfield 455	ct/af:z	Z
    //   5097: iload 37
    //   5099: ifeq +17 -> 5116
    //   5102: aload 16
    //   5104: getfield 442	ct/af:k	I
    //   5107: ifeq +9 -> 5116
    //   5110: aload 16
    //   5112: iconst_1
    //   5113: putfield 458	ct/af:w	I
    //   5116: aload 16
    //   5118: aload_1
    //   5119: getfield 460	ct/ad:h	Z
    //   5122: putfield 463	ct/af:B	Z
    //   5125: invokestatic 468	ct/o:a	()Lct/o;
    //   5128: new 470	ct/ag
    //   5131: dup
    //   5132: aload 16
    //   5134: invokespecial 473	ct/ag:<init>	(Lct/af;)V
    //   5137: invokevirtual 476	ct/o:a	(Ljava/lang/Runnable;)V
    //   5140: aload_1
    //   5141: aload 16
    //   5143: invokevirtual 478	ct/ad:a	(Lct/af;)V
    //   5146: aload 16
    //   5148: invokevirtual 479	ct/af:toString	()Ljava/lang/String;
    //   5151: pop
    //   5152: aload 16
    //   5154: invokevirtual 479	ct/af:toString	()Ljava/lang/String;
    //   5157: pop
    //   5158: invokestatic 481	ct/bc:b	()V
    //   5161: aload 5
    //   5163: ifnull +9 -> 5172
    //   5166: aload_1
    //   5167: getfield 269	ct/ad:p	Z
    //   5170: istore 37
    //   5172: lload 33
    //   5174: invokestatic 483	ct/x:a	(J)Z
    //   5177: istore 37
    //   5179: aload 7
    //   5181: getfield 421	ct/ae:a	I
    //   5184: bipush -4
    //   5186: if_icmpeq -3929 -> 1257
    //   5189: aload 7
    //   5191: getfield 421	ct/ae:a	I
    //   5194: bipush -17
    //   5196: if_icmpeq -3939 -> 1257
    //   5199: iload 37
    //   5201: ifeq -3944 -> 1257
    //   5204: aload 7
    //   5206: areturn
    //   5207: aload 16
    //   5209: lconst_0
    //   5210: putfield 452	ct/af:n	J
    //   5213: goto -123 -> 5090
    //   5216: astore_2
    //   5217: aload_2
    //   5218: invokevirtual 576	java/lang/Throwable:printStackTrace	()V
    //   5221: goto -60 -> 5161
    //   5224: aload_2
    //   5225: astore 10
    //   5227: aload 4
    //   5229: astore 12
    //   5231: aload 5
    //   5233: astore 6
    //   5235: aload_2
    //   5236: astore 11
    //   5238: aload 4
    //   5240: astore 9
    //   5242: aload 5
    //   5244: astore 8
    //   5246: aload 4
    //   5248: astore 13
    //   5250: aload 7
    //   5252: iload 27
    //   5254: putfield 421	ct/ae:a	I
    //   5257: iload 38
    //   5259: istore 39
    //   5261: iload 37
    //   5263: istore 38
    //   5265: iload 39
    //   5267: istore 37
    //   5269: goto -2492 -> 2777
    //   5272: iload 25
    //   5274: iconst_1
    //   5275: iadd
    //   5276: istore 23
    //   5278: iload 23
    //   5280: bipush 6
    //   5282: if_icmple +706 -> 5988
    //   5285: iload 24
    //   5287: iconst_1
    //   5288: iadd
    //   5289: istore 24
    //   5291: iconst_0
    //   5292: istore 23
    //   5294: aload 7
    //   5296: bipush -5
    //   5298: putfield 421	ct/ae:a	I
    //   5301: goto -2468 -> 2833
    //   5304: aload 16
    //   5306: lconst_0
    //   5307: putfield 452	ct/af:n	J
    //   5310: goto -2381 -> 2929
    //   5313: astore_3
    //   5314: aload_3
    //   5315: invokevirtual 576	java/lang/Throwable:printStackTrace	()V
    //   5318: goto -2318 -> 3000
    //   5321: aload 5
    //   5323: instanceof 596
    //   5326: ifeq +10 -> 5336
    //   5329: bipush -11
    //   5331: istore 22
    //   5333: goto -4370 -> 963
    //   5336: aload 5
    //   5338: instanceof 598
    //   5341: ifeq +10 -> 5351
    //   5344: bipush -13
    //   5346: istore 22
    //   5348: goto -4385 -> 963
    //   5351: aload 5
    //   5353: instanceof 600
    //   5356: ifeq +10 -> 5366
    //   5359: bipush -14
    //   5361: istore 22
    //   5363: goto -4400 -> 963
    //   5366: aload 5
    //   5368: instanceof 602
    //   5371: ifeq +10 -> 5381
    //   5374: bipush -15
    //   5376: istore 22
    //   5378: goto -4415 -> 963
    //   5381: aload 5
    //   5383: instanceof 604
    //   5386: ifeq +10 -> 5396
    //   5389: bipush -16
    //   5391: istore 22
    //   5393: goto -4430 -> 963
    //   5396: aload 5
    //   5398: instanceof 606
    //   5401: ifeq +10 -> 5411
    //   5404: bipush -22
    //   5406: istore 22
    //   5408: goto -4445 -> 963
    //   5411: aload 5
    //   5413: instanceof 608
    //   5416: ifeq +10 -> 5426
    //   5419: bipush -12
    //   5421: istore 22
    //   5423: goto -4460 -> 963
    //   5426: aload 5
    //   5428: instanceof 610
    //   5431: istore 39
    //   5433: iload 39
    //   5435: ifeq +10 -> 5445
    //   5438: bipush -24
    //   5440: istore 22
    //   5442: goto -4479 -> 963
    //   5445: bipush -3
    //   5447: istore 22
    //   5449: goto -4486 -> 963
    //   5452: bipush -4
    //   5454: istore 22
    //   5456: goto -4493 -> 963
    //   5459: iload 25
    //   5461: iconst_1
    //   5462: iadd
    //   5463: istore 26
    //   5465: iload 26
    //   5467: istore 22
    //   5469: iload 24
    //   5471: istore 25
    //   5473: iload 26
    //   5475: bipush 6
    //   5477: if_icmple -4429 -> 1048
    //   5480: iload 24
    //   5482: iconst_1
    //   5483: iadd
    //   5484: istore 25
    //   5486: iconst_0
    //   5487: istore 22
    //   5489: aload 7
    //   5491: bipush -5
    //   5493: putfield 421	ct/ae:a	I
    //   5496: goto -4448 -> 1048
    //   5499: aload 16
    //   5501: lconst_0
    //   5502: putfield 452	ct/af:n	J
    //   5505: goto -4361 -> 1144
    //   5508: astore 5
    //   5510: aload 5
    //   5512: invokevirtual 576	java/lang/Throwable:printStackTrace	()V
    //   5515: goto -4300 -> 1215
    //   5518: iload 22
    //   5520: istore 26
    //   5522: iload 23
    //   5524: istore 22
    //   5526: aload 7
    //   5528: astore 6
    //   5530: aload 4
    //   5532: astore 5
    //   5534: iload 25
    //   5536: istore 24
    //   5538: aload_2
    //   5539: astore_3
    //   5540: iload 26
    //   5542: istore 25
    //   5544: goto -5461 -> 83
    //   5547: iload 25
    //   5549: iconst_1
    //   5550: iadd
    //   5551: istore 26
    //   5553: iload 26
    //   5555: istore 23
    //   5557: iload 24
    //   5559: istore 25
    //   5561: iload 26
    //   5563: bipush 6
    //   5565: if_icmple -3778 -> 1787
    //   5568: iload 24
    //   5570: iconst_1
    //   5571: iadd
    //   5572: istore 25
    //   5574: iconst_0
    //   5575: istore 23
    //   5577: aload 7
    //   5579: bipush -5
    //   5581: putfield 421	ct/ae:a	I
    //   5584: goto -3797 -> 1787
    //   5587: aload 16
    //   5589: lconst_0
    //   5590: putfield 452	ct/af:n	J
    //   5593: goto -3711 -> 1882
    //   5596: astore 4
    //   5598: aload 4
    //   5600: invokevirtual 576	java/lang/Throwable:printStackTrace	()V
    //   5603: goto -3650 -> 1953
    //   5606: aload 16
    //   5608: lconst_0
    //   5609: putfield 452	ct/af:n	J
    //   5612: goto -1065 -> 4547
    //   5615: astore_3
    //   5616: aload_3
    //   5617: invokevirtual 576	java/lang/Throwable:printStackTrace	()V
    //   5620: goto -1002 -> 4618
    //   5623: aload_1
    //   5624: getfield 269	ct/ad:p	Z
    //   5627: istore 37
    //   5629: aload 6
    //   5631: areturn
    //   5632: astore_2
    //   5633: aload 11
    //   5635: astore 6
    //   5637: aload 9
    //   5639: astore_3
    //   5640: aload 8
    //   5642: astore 5
    //   5644: goto -1257 -> 4387
    //   5647: astore_3
    //   5648: aload_2
    //   5649: astore 6
    //   5651: aload_3
    //   5652: astore_2
    //   5653: aload 4
    //   5655: astore_3
    //   5656: goto -1269 -> 4387
    //   5659: astore_2
    //   5660: aconst_null
    //   5661: astore 6
    //   5663: aload 4
    //   5665: astore_3
    //   5666: goto -1279 -> 4387
    //   5669: astore_2
    //   5670: aload 5
    //   5672: astore 6
    //   5674: aload 8
    //   5676: astore 5
    //   5678: goto -1291 -> 4387
    //   5681: astore 6
    //   5683: aload_3
    //   5684: astore 5
    //   5686: aload_2
    //   5687: astore_3
    //   5688: aload 6
    //   5690: astore_2
    //   5691: aload 4
    //   5693: astore 6
    //   5695: goto -1308 -> 4387
    //   5698: astore_3
    //   5699: iconst_1
    //   5700: istore 38
    //   5702: aload_2
    //   5703: astore_3
    //   5704: aload 4
    //   5706: astore_2
    //   5707: goto -3976 -> 1731
    //   5710: astore_2
    //   5711: iconst_1
    //   5712: istore 38
    //   5714: aconst_null
    //   5715: astore_3
    //   5716: aload 4
    //   5718: astore_2
    //   5719: goto -3988 -> 1731
    //   5722: astore_2
    //   5723: aload_3
    //   5724: astore_2
    //   5725: aload 5
    //   5727: astore_3
    //   5728: aload 6
    //   5730: astore 5
    //   5732: goto -4001 -> 1731
    //   5735: astore_2
    //   5736: iload 23
    //   5738: istore 22
    //   5740: aload_3
    //   5741: astore_2
    //   5742: aload 5
    //   5744: astore_3
    //   5745: aload 6
    //   5747: astore 5
    //   5749: goto -4018 -> 1731
    //   5752: astore_3
    //   5753: aload_2
    //   5754: astore 4
    //   5756: aload 5
    //   5758: astore 6
    //   5760: iload 23
    //   5762: istore 26
    //   5764: aload 13
    //   5766: astore_2
    //   5767: iload 22
    //   5769: istore 23
    //   5771: aload_3
    //   5772: astore 5
    //   5774: aload 6
    //   5776: astore_3
    //   5777: iload 26
    //   5779: istore 22
    //   5781: goto -4886 -> 895
    //   5784: astore 6
    //   5786: aload 4
    //   5788: astore_2
    //   5789: bipush 10
    //   5791: istore 26
    //   5793: aload 5
    //   5795: astore 8
    //   5797: iload 22
    //   5799: istore 23
    //   5801: aload_3
    //   5802: astore 4
    //   5804: aload 6
    //   5806: astore 5
    //   5808: aload 8
    //   5810: astore_3
    //   5811: iload 26
    //   5813: istore 22
    //   5815: goto -4920 -> 895
    //   5818: astore_3
    //   5819: iconst_1
    //   5820: istore 38
    //   5822: aload 5
    //   5824: astore 6
    //   5826: aload_2
    //   5827: astore 5
    //   5829: aload 4
    //   5831: astore_2
    //   5832: bipush 10
    //   5834: istore 26
    //   5836: iload 22
    //   5838: istore 23
    //   5840: aload 5
    //   5842: astore 4
    //   5844: aload_3
    //   5845: astore 5
    //   5847: aload 6
    //   5849: astore_3
    //   5850: iload 26
    //   5852: istore 22
    //   5854: goto -4959 -> 895
    //   5857: astore_3
    //   5858: iconst_1
    //   5859: istore 38
    //   5861: aload 5
    //   5863: astore 6
    //   5865: aconst_null
    //   5866: astore 5
    //   5868: aload 4
    //   5870: astore_2
    //   5871: bipush 10
    //   5873: istore 26
    //   5875: iload 22
    //   5877: istore 23
    //   5879: aload 5
    //   5881: astore 4
    //   5883: aload_3
    //   5884: astore 5
    //   5886: aload 6
    //   5888: astore_3
    //   5889: iload 26
    //   5891: istore 22
    //   5893: goto -4998 -> 895
    //   5896: astore 6
    //   5898: aconst_null
    //   5899: astore 8
    //   5901: aload_3
    //   5902: astore_2
    //   5903: iconst_2
    //   5904: istore 26
    //   5906: iload 22
    //   5908: istore 23
    //   5910: aload 5
    //   5912: astore 4
    //   5914: aload 6
    //   5916: astore 5
    //   5918: aload 8
    //   5920: astore_3
    //   5921: iload 26
    //   5923: istore 22
    //   5925: goto -5030 -> 895
    //   5928: astore 4
    //   5930: aload_3
    //   5931: astore_2
    //   5932: iconst_2
    //   5933: istore 22
    //   5935: aload 4
    //   5937: astore_3
    //   5938: iload 26
    //   5940: istore 23
    //   5942: aconst_null
    //   5943: astore 6
    //   5945: aload 5
    //   5947: astore 4
    //   5949: aload_3
    //   5950: astore 5
    //   5952: aload 6
    //   5954: astore_3
    //   5955: goto -5060 -> 895
    //   5958: astore 5
    //   5960: aload_2
    //   5961: astore 4
    //   5963: aconst_null
    //   5964: astore 6
    //   5966: iconst_4
    //   5967: istore 26
    //   5969: aload_3
    //   5970: astore_2
    //   5971: iload 22
    //   5973: istore 23
    //   5975: aload 6
    //   5977: astore_3
    //   5978: iload 26
    //   5980: istore 22
    //   5982: goto -5087 -> 895
    //   5985: goto -5663 -> 322
    //   5988: goto -3155 -> 2833
    //   5991: iconst_1
    //   5992: istore 39
    //   5994: iload 37
    //   5996: istore 38
    //   5998: iload 39
    //   6000: istore 37
    //   6002: goto -3225 -> 2777
    //   6005: goto -1137 -> 4868
    //   6008: iload 38
    //   6010: istore 37
    //   6012: iload 39
    //   6014: istore 38
    //   6016: goto -3239 -> 2777
    //   6019: goto -3287 -> 2732
    //   6022: astore_3
    //   6023: aload_2
    //   6024: astore_3
    //   6025: iconst_1
    //   6026: istore 37
    //   6028: aload 4
    //   6030: astore_2
    //   6031: goto -4300 -> 1731
    // Local variable table:
    //   start	length	slot	name	signature
    //   0	6034	0	this	x
    //   0	6034	1	paramad	ad
    //   413	1274	2	localObject1	Object
    //   1720	1	2	localThrowable1	Throwable
    //   1723	1841	2	localObject2	Object
    //   3590	792	2	localThrowable2	Throwable
    //   4386	276	2	localObject3	Object
    //   4672	2	2	localThrowable3	Throwable
    //   4721	105	2	localThrowable4	Throwable
    //   4834	235	2	localObject4	Object
    //   5216	323	2	localThrowable5	Throwable
    //   5632	17	2	localObject5	Object
    //   5652	1	2	localObject6	Object
    //   5659	1	2	localObject7	Object
    //   5669	18	2	localObject8	Object
    //   5690	17	2	localObject9	Object
    //   5710	1	2	localThrowable6	Throwable
    //   5718	1	2	localObject10	Object
    //   5722	1	2	localThrowable7	Throwable
    //   5724	1	2	localObject11	Object
    //   5735	1	2	localThrowable8	Throwable
    //   5741	290	2	localObject12	Object
    //   76	3131	3	localObject13	Object
    //   3530	6	3	localException1	Exception
    //   3542	27	3	localException2	Exception
    //   3573	477	3	localObject14	Object
    //   4361	6	3	localException3	Exception
    //   4380	117	3	localObject15	Object
    //   4680	6	3	localException4	Exception
    //   4785	77	3	localObject16	Object
    //   5313	2	3	localThrowable9	Throwable
    //   5539	1	3	localObject17	Object
    //   5615	2	3	localThrowable10	Throwable
    //   5639	1	3	localObject18	Object
    //   5647	5	3	localObject19	Object
    //   5655	33	3	localObject20	Object
    //   5698	1	3	localThrowable11	Throwable
    //   5703	42	3	localObject21	Object
    //   5752	20	3	localException5	Exception
    //   5776	35	3	localObject22	Object
    //   5818	27	3	localException6	Exception
    //   5849	1	3	localObject23	Object
    //   5857	27	3	localException7	Exception
    //   5888	90	3	localObject24	Object
    //   6022	1	3	localThrowable12	Throwable
    //   6024	1	3	localObject25	Object
    //   429	5102	4	localObject26	Object
    //   5596	121	4	localThrowable13	Throwable
    //   5754	159	4	localObject27	Object
    //   5928	8	4	localException8	Exception
    //   5947	82	4	localObject28	Object
    //   57	795	5	localObject29	Object
    //   871	830	5	localException9	Exception
    //   1729	3698	5	localObject30	Object
    //   5508	3	5	localThrowable14	Throwable
    //   5532	419	5	localObject31	Object
    //   5958	1	5	localException10	Exception
    //   7	3159	6	localObject32	Object
    //   3195	7	6	localOutOfMemoryError1	OutOfMemoryError
    //   3555	457	6	localObject33	Object
    //   4038	7	6	localOutOfMemoryError2	OutOfMemoryError
    //   4382	1291	6	localObject34	Object
    //   5681	8	6	localObject35	Object
    //   5693	82	6	localObject36	Object
    //   5784	21	6	localException11	Exception
    //   5824	63	6	localObject37	Object
    //   5896	19	6	localException12	Exception
    //   5943	33	6	localObject38	Object
    //   115	5463	7	localae	ae
    //   154	3411	8	localObject39	Object
    //   4373	12	8	localObject40	Object
    //   4749	1170	8	localObject41	Object
    //   426	5212	9	localObject42	Object
    //   514	4712	10	localObject43	Object
    //   524	5110	11	localObject44	Object
    //   517	4713	12	localObject45	Object
    //   233	5532	13	localObject46	Object
    //   160	4627	14	localHttpResponse	org.apache.http.HttpResponse
    //   157	2031	15	localObject47	Object
    //   124	5483	16	localaf	af
    //   17	126	17	localab	ab
    //   24	265	18	localList	java.util.List
    //   31	98	19	str1	String
    //   634	1668	20	localHttpPost	org.apache.http.client.methods.HttpPost
    //   825	878	21	str2	String
    //   81	5900	22	i	int
    //   182	5792	23	j	int
    //   52	5520	24	k	int
    //   78	5495	25	m	int
    //   311	5668	26	n	int
    //   2466	2787	27	i1	int
    //   40	150	28	i2	int
    //   49	133	29	i3	int
    //   71	65	30	i4	int
    //   3132	949	31	i5	int
    //   3177	13	32	i6	int
    //   100	5073	33	l1	long
    //   2270	1342	35	l2	long
    //   106	5921	37	bool1	boolean
    //   60	5955	38	bool2	boolean
    //   2767	3246	39	bool3	boolean
    // Exception table:
    //   from	to	target	type
    //   533	582	871	java/lang/Exception
    //   602	605	871	java/lang/Exception
    //   625	636	871	java/lang/Exception
    //   656	665	871	java/lang/Exception
    //   685	696	871	java/lang/Exception
    //   716	726	871	java/lang/Exception
    //   751	765	871	java/lang/Exception
    //   785	795	871	java/lang/Exception
    //   815	827	871	java/lang/Exception
    //   847	868	871	java/lang/Exception
    //   1462	1468	871	java/lang/Exception
    //   1488	1502	871	java/lang/Exception
    //   1522	1575	871	java/lang/Exception
    //   1600	1614	871	java/lang/Exception
    //   1634	1644	871	java/lang/Exception
    //   1664	1676	871	java/lang/Exception
    //   1696	1717	871	java/lang/Exception
    //   2036	2042	871	java/lang/Exception
    //   2062	2077	871	java/lang/Exception
    //   2097	2103	871	java/lang/Exception
    //   2128	2134	871	java/lang/Exception
    //   2154	2171	871	java/lang/Exception
    //   533	582	1720	java/lang/Throwable
    //   602	605	1720	java/lang/Throwable
    //   625	636	1720	java/lang/Throwable
    //   656	665	1720	java/lang/Throwable
    //   685	696	1720	java/lang/Throwable
    //   716	726	1720	java/lang/Throwable
    //   751	765	1720	java/lang/Throwable
    //   785	795	1720	java/lang/Throwable
    //   815	827	1720	java/lang/Throwable
    //   847	868	1720	java/lang/Throwable
    //   1462	1468	1720	java/lang/Throwable
    //   1488	1502	1720	java/lang/Throwable
    //   1522	1575	1720	java/lang/Throwable
    //   1600	1614	1720	java/lang/Throwable
    //   1634	1644	1720	java/lang/Throwable
    //   1664	1676	1720	java/lang/Throwable
    //   1696	1717	1720	java/lang/Throwable
    //   2036	2042	1720	java/lang/Throwable
    //   2062	2077	1720	java/lang/Throwable
    //   2097	2103	1720	java/lang/Throwable
    //   2128	2134	1720	java/lang/Throwable
    //   2154	2171	1720	java/lang/Throwable
    //   2191	2198	1720	java/lang/Throwable
    //   2228	2240	1720	java/lang/Throwable
    //   2267	2272	1720	java/lang/Throwable
    //   2299	2308	1720	java/lang/Throwable
    //   2335	2347	1720	java/lang/Throwable
    //   2378	2397	1720	java/lang/Throwable
    //   2424	2427	1720	java/lang/Throwable
    //   2454	2468	1720	java/lang/Throwable
    //   2495	2502	1720	java/lang/Throwable
    //   2540	2553	1720	java/lang/Throwable
    //   2580	2597	1720	java/lang/Throwable
    //   2627	2637	1720	java/lang/Throwable
    //   2758	2765	1720	java/lang/Throwable
    //   3090	3103	1720	java/lang/Throwable
    //   4755	4762	1720	java/lang/Throwable
    //   4786	4798	1720	java/lang/Throwable
    //   4827	4835	1720	java/lang/Throwable
    //   4862	4865	1720	java/lang/Throwable
    //   5250	5257	1720	java/lang/Throwable
    //   3138	3144	3195	java/lang/OutOfMemoryError
    //   3206	3210	3530	java/lang/Exception
    //   3114	3121	3542	java/lang/Exception
    //   3128	3134	3542	java/lang/Exception
    //   3138	3144	3542	java/lang/Exception
    //   3148	3153	3542	java/lang/Exception
    //   3164	3179	3542	java/lang/Exception
    //   3201	3206	3542	java/lang/Exception
    //   3214	3221	3542	java/lang/Exception
    //   3225	3248	3542	java/lang/Exception
    //   3252	3260	3542	java/lang/Exception
    //   3535	3539	3542	java/lang/Exception
    //   3606	3618	3542	java/lang/Exception
    //   3622	3632	3542	java/lang/Exception
    //   3636	3644	3542	java/lang/Exception
    //   3655	3678	3542	java/lang/Exception
    //   3682	3688	3542	java/lang/Exception
    //   3696	3704	3542	java/lang/Exception
    //   3708	3714	3542	java/lang/Exception
    //   3718	3724	3542	java/lang/Exception
    //   3998	4007	3542	java/lang/Exception
    //   4011	4025	3542	java/lang/Exception
    //   4029	4035	3542	java/lang/Exception
    //   4044	4049	3542	java/lang/Exception
    //   4057	4064	3542	java/lang/Exception
    //   4068	4091	3542	java/lang/Exception
    //   4366	4370	3542	java/lang/Exception
    //   4685	4689	3542	java/lang/Exception
    //   4696	4699	3542	java/lang/Exception
    //   4703	4709	3542	java/lang/Exception
    //   3448	3484	3590	java/lang/Throwable
    //   3998	4007	4038	java/lang/OutOfMemoryError
    //   4049	4053	4361	java/lang/Exception
    //   3114	3121	4373	finally
    //   3128	3134	4373	finally
    //   3138	3144	4373	finally
    //   3148	3153	4373	finally
    //   3164	3179	4373	finally
    //   3201	3206	4373	finally
    //   3206	3210	4373	finally
    //   3214	3221	4373	finally
    //   3225	3248	4373	finally
    //   3252	3260	4373	finally
    //   3535	3539	4373	finally
    //   3606	3618	4373	finally
    //   3622	3632	4373	finally
    //   3636	3644	4373	finally
    //   3655	3678	4373	finally
    //   3682	3688	4373	finally
    //   3688	3692	4373	finally
    //   3696	3704	4373	finally
    //   3708	3714	4373	finally
    //   3718	3724	4373	finally
    //   3998	4007	4373	finally
    //   4011	4025	4373	finally
    //   4029	4035	4373	finally
    //   4044	4049	4373	finally
    //   4049	4053	4373	finally
    //   4057	4064	4373	finally
    //   4068	4091	4373	finally
    //   4366	4370	4373	finally
    //   4685	4689	4373	finally
    //   4696	4699	4373	finally
    //   4703	4709	4373	finally
    //   4279	4315	4672	java/lang/Throwable
    //   3688	3692	4680	java/lang/Exception
    //   3912	3948	4721	java/lang/Throwable
    //   5125	5161	5216	java/lang/Throwable
    //   2964	3000	5313	java/lang/Throwable
    //   1179	1215	5508	java/lang/Throwable
    //   1917	1953	5596	java/lang/Throwable
    //   4582	4618	5615	java/lang/Throwable
    //   533	582	5632	finally
    //   602	605	5632	finally
    //   625	636	5632	finally
    //   656	665	5632	finally
    //   685	696	5632	finally
    //   716	726	5632	finally
    //   751	765	5632	finally
    //   785	795	5632	finally
    //   815	827	5632	finally
    //   847	868	5632	finally
    //   1462	1468	5632	finally
    //   1488	1502	5632	finally
    //   1522	1575	5632	finally
    //   1600	1614	5632	finally
    //   1634	1644	5632	finally
    //   1664	1676	5632	finally
    //   1696	1717	5632	finally
    //   2036	2042	5632	finally
    //   2062	2077	5632	finally
    //   2097	2103	5632	finally
    //   2128	2134	5632	finally
    //   2154	2171	5632	finally
    //   2191	2198	5632	finally
    //   2228	2240	5632	finally
    //   2267	2272	5632	finally
    //   2299	2308	5632	finally
    //   2335	2347	5632	finally
    //   2378	2397	5632	finally
    //   2424	2427	5632	finally
    //   2454	2468	5632	finally
    //   2495	2502	5632	finally
    //   2540	2553	5632	finally
    //   2580	2597	5632	finally
    //   2627	2637	5632	finally
    //   2758	2765	5632	finally
    //   3090	3103	5632	finally
    //   4755	4762	5632	finally
    //   4786	4798	5632	finally
    //   4827	4835	5632	finally
    //   4862	4865	5632	finally
    //   5250	5257	5632	finally
    //   4868	4880	5647	finally
    //   4908	4931	5647	finally
    //   4885	4892	5659	finally
    //   193	221	5669	finally
    //   221	307	5669	finally
    //   316	322	5669	finally
    //   330	338	5669	finally
    //   346	353	5669	finally
    //   361	370	5669	finally
    //   378	414	5669	finally
    //   422	428	5669	finally
    //   439	447	5669	finally
    //   455	466	5669	finally
    //   474	495	5669	finally
    //   503	510	5669	finally
    //   1268	1290	5669	finally
    //   1301	1310	5669	finally
    //   1318	1345	5669	finally
    //   1356	1377	5669	finally
    //   1388	1415	5669	finally
    //   1426	1433	5669	finally
    //   895	959	5681	finally
    //   963	991	5681	finally
    //   5321	5329	5681	finally
    //   5336	5344	5681	finally
    //   5351	5359	5681	finally
    //   5366	5374	5681	finally
    //   5381	5389	5681	finally
    //   5396	5404	5681	finally
    //   5411	5419	5681	finally
    //   5426	5433	5681	finally
    //   4868	4880	5698	java/lang/Throwable
    //   4908	4931	5698	java/lang/Throwable
    //   4885	4892	5710	java/lang/Throwable
    //   193	221	5722	java/lang/Throwable
    //   221	307	5722	java/lang/Throwable
    //   316	322	5735	java/lang/Throwable
    //   330	338	5735	java/lang/Throwable
    //   346	353	5735	java/lang/Throwable
    //   361	370	5735	java/lang/Throwable
    //   378	414	5735	java/lang/Throwable
    //   422	428	5735	java/lang/Throwable
    //   439	447	5735	java/lang/Throwable
    //   455	466	5735	java/lang/Throwable
    //   474	495	5735	java/lang/Throwable
    //   503	510	5735	java/lang/Throwable
    //   1268	1290	5735	java/lang/Throwable
    //   1301	1310	5735	java/lang/Throwable
    //   1318	1345	5735	java/lang/Throwable
    //   1356	1377	5735	java/lang/Throwable
    //   1388	1415	5735	java/lang/Throwable
    //   1426	1433	5735	java/lang/Throwable
    //   2228	2240	5752	java/lang/Exception
    //   2267	2272	5752	java/lang/Exception
    //   2299	2308	5752	java/lang/Exception
    //   2335	2347	5752	java/lang/Exception
    //   2378	2397	5752	java/lang/Exception
    //   2424	2427	5752	java/lang/Exception
    //   2454	2468	5752	java/lang/Exception
    //   2495	2502	5752	java/lang/Exception
    //   2540	2553	5752	java/lang/Exception
    //   2580	2597	5752	java/lang/Exception
    //   2627	2637	5752	java/lang/Exception
    //   2758	2765	5752	java/lang/Exception
    //   3090	3103	5752	java/lang/Exception
    //   4755	4762	5752	java/lang/Exception
    //   5250	5257	5752	java/lang/Exception
    //   4786	4798	5784	java/lang/Exception
    //   4827	4835	5784	java/lang/Exception
    //   4862	4865	5784	java/lang/Exception
    //   4868	4880	5818	java/lang/Exception
    //   4908	4931	5818	java/lang/Exception
    //   4885	4892	5857	java/lang/Exception
    //   193	221	5896	java/lang/Exception
    //   221	307	5896	java/lang/Exception
    //   316	322	5928	java/lang/Exception
    //   330	338	5928	java/lang/Exception
    //   346	353	5928	java/lang/Exception
    //   361	370	5928	java/lang/Exception
    //   378	414	5928	java/lang/Exception
    //   422	428	5928	java/lang/Exception
    //   439	447	5928	java/lang/Exception
    //   455	466	5928	java/lang/Exception
    //   474	495	5928	java/lang/Exception
    //   503	510	5928	java/lang/Exception
    //   1268	1290	5928	java/lang/Exception
    //   1301	1310	5928	java/lang/Exception
    //   1318	1345	5928	java/lang/Exception
    //   1356	1377	5928	java/lang/Exception
    //   1388	1415	5928	java/lang/Exception
    //   1426	1433	5928	java/lang/Exception
    //   2191	2198	5958	java/lang/Exception
    //   3114	3121	6022	java/lang/Throwable
    //   3128	3134	6022	java/lang/Throwable
    //   3138	3144	6022	java/lang/Throwable
    //   3148	3153	6022	java/lang/Throwable
    //   3164	3179	6022	java/lang/Throwable
    //   3201	3206	6022	java/lang/Throwable
    //   3206	3210	6022	java/lang/Throwable
    //   3214	3221	6022	java/lang/Throwable
    //   3225	3248	6022	java/lang/Throwable
    //   3252	3260	6022	java/lang/Throwable
    //   3535	3539	6022	java/lang/Throwable
    //   3606	3618	6022	java/lang/Throwable
    //   3622	3632	6022	java/lang/Throwable
    //   3636	3644	6022	java/lang/Throwable
    //   3655	3678	6022	java/lang/Throwable
    //   3682	3688	6022	java/lang/Throwable
    //   3688	3692	6022	java/lang/Throwable
    //   3696	3704	6022	java/lang/Throwable
    //   3708	3714	6022	java/lang/Throwable
    //   3718	3724	6022	java/lang/Throwable
    //   3998	4007	6022	java/lang/Throwable
    //   4011	4025	6022	java/lang/Throwable
    //   4029	4035	6022	java/lang/Throwable
    //   4044	4049	6022	java/lang/Throwable
    //   4049	4053	6022	java/lang/Throwable
    //   4057	4064	6022	java/lang/Throwable
    //   4068	4091	6022	java/lang/Throwable
    //   4366	4370	6022	java/lang/Throwable
    //   4685	4689	6022	java/lang/Throwable
    //   4696	4699	6022	java/lang/Throwable
    //   4703	4709	6022	java/lang/Throwable
  }
  
  public final aa a(z paramz)
  {
    try
    {
      ad localad = (ad)paramz;
      localad.k = System.currentTimeMillis();
      new StringBuilder("doRequest... key:").append(paramz.b());
      bc.b();
      ae localae = b(localad);
      long l1 = System.currentTimeMillis();
      long l2 = localad.k;
      new StringBuilder("endRequest... key:").append(paramz.b()).append("costTime: ").append(l1 - l2);
      bc.b();
      return localae;
    }
    catch (Throwable paramz)
    {
      paramz = new ae();
      paramz.a = -19;
    }
    return paramz;
  }
}


/* Location:              E:\apk\QQ_91\classes3-dex2jar.jar!\ct\x.class
 * Java compiler version: 6 (50.0)
 * JD-Core Version:       0.7.1
 */