import com.tencent.mobileqq.activity.richmedia.NewFlowCameraActivity;
import com.tencent.mobileqq.hotpatch.NotVerifyClass;

public class pbk
  implements Runnable
{
  public pbk(NewFlowCameraActivity paramNewFlowCameraActivity)
  {
    boolean bool = NotVerifyClass.DO_VERIFY_CLASS;
  }
  
  /* Error */
  public void run()
  {
    // Byte code:
    //   0: invokestatic 31	java/lang/System:currentTimeMillis	()J
    //   3: lstore 6
    //   5: ldc 33
    //   7: iconst_2
    //   8: new 35	java/lang/StringBuilder
    //   11: dup
    //   12: invokespecial 36	java/lang/StringBuilder:<init>	()V
    //   15: ldc 38
    //   17: invokevirtual 42	java/lang/StringBuilder:append	(Ljava/lang/String;)Ljava/lang/StringBuilder;
    //   20: lload 6
    //   22: invokevirtual 45	java/lang/StringBuilder:append	(J)Ljava/lang/StringBuilder;
    //   25: invokevirtual 49	java/lang/StringBuilder:toString	()Ljava/lang/String;
    //   28: invokestatic 55	com/tencent/qphone/base/util/QLog:d	(Ljava/lang/String;ILjava/lang/String;)V
    //   31: ldc 57
    //   33: iconst_2
    //   34: new 35	java/lang/StringBuilder
    //   37: dup
    //   38: invokespecial 36	java/lang/StringBuilder:<init>	()V
    //   41: ldc 59
    //   43: invokevirtual 42	java/lang/StringBuilder:append	(Ljava/lang/String;)Ljava/lang/StringBuilder;
    //   46: aload_0
    //   47: getfield 12	pbk:a	Lcom/tencent/mobileqq/activity/richmedia/NewFlowCameraActivity;
    //   50: invokestatic 65	com/tencent/mobileqq/activity/richmedia/NewFlowCameraActivity:g	(Lcom/tencent/mobileqq/activity/richmedia/NewFlowCameraActivity;)I
    //   53: invokevirtual 68	java/lang/StringBuilder:append	(I)Ljava/lang/StringBuilder;
    //   56: invokevirtual 49	java/lang/StringBuilder:toString	()Ljava/lang/String;
    //   59: invokestatic 55	com/tencent/qphone/base/util/QLog:d	(Ljava/lang/String;ILjava/lang/String;)V
    //   62: aload_0
    //   63: getfield 12	pbk:a	Lcom/tencent/mobileqq/activity/richmedia/NewFlowCameraActivity;
    //   66: invokestatic 65	com/tencent/mobileqq/activity/richmedia/NewFlowCameraActivity:g	(Lcom/tencent/mobileqq/activity/richmedia/NewFlowCameraActivity;)I
    //   69: aload_0
    //   70: getfield 12	pbk:a	Lcom/tencent/mobileqq/activity/richmedia/NewFlowCameraActivity;
    //   73: invokestatic 71	com/tencent/mobileqq/activity/richmedia/NewFlowCameraActivity:h	(Lcom/tencent/mobileqq/activity/richmedia/NewFlowCameraActivity;)I
    //   76: if_icmple +382 -> 458
    //   79: aload_0
    //   80: getfield 12	pbk:a	Lcom/tencent/mobileqq/activity/richmedia/NewFlowCameraActivity;
    //   83: aload_0
    //   84: getfield 12	pbk:a	Lcom/tencent/mobileqq/activity/richmedia/NewFlowCameraActivity;
    //   87: invokestatic 65	com/tencent/mobileqq/activity/richmedia/NewFlowCameraActivity:g	(Lcom/tencent/mobileqq/activity/richmedia/NewFlowCameraActivity;)I
    //   90: aload_0
    //   91: getfield 12	pbk:a	Lcom/tencent/mobileqq/activity/richmedia/NewFlowCameraActivity;
    //   94: invokestatic 71	com/tencent/mobileqq/activity/richmedia/NewFlowCameraActivity:h	(Lcom/tencent/mobileqq/activity/richmedia/NewFlowCameraActivity;)I
    //   97: idiv
    //   98: iconst_1
    //   99: iadd
    //   100: invokestatic 74	com/tencent/mobileqq/activity/richmedia/NewFlowCameraActivity:h	(Lcom/tencent/mobileqq/activity/richmedia/NewFlowCameraActivity;I)I
    //   103: pop
    //   104: new 76	java/io/File
    //   107: dup
    //   108: invokestatic 79	com/tencent/mobileqq/activity/richmedia/NewFlowCameraActivity:e	()Ljava/lang/String;
    //   111: invokespecial 82	java/io/File:<init>	(Ljava/lang/String;)V
    //   114: astore_1
    //   115: aload_0
    //   116: getfield 12	pbk:a	Lcom/tencent/mobileqq/activity/richmedia/NewFlowCameraActivity;
    //   119: ldc 84
    //   121: invokestatic 87	com/tencent/mobileqq/activity/richmedia/NewFlowCameraActivity:e	(Lcom/tencent/mobileqq/activity/richmedia/NewFlowCameraActivity;Ljava/lang/String;)Ljava/lang/String;
    //   124: pop
    //   125: iconst_0
    //   126: istore 4
    //   128: iload 4
    //   130: aload_0
    //   131: getfield 12	pbk:a	Lcom/tencent/mobileqq/activity/richmedia/NewFlowCameraActivity;
    //   134: invokestatic 90	com/tencent/mobileqq/activity/richmedia/NewFlowCameraActivity:i	(Lcom/tencent/mobileqq/activity/richmedia/NewFlowCameraActivity;)I
    //   137: if_icmpge +50 -> 187
    //   140: aload_0
    //   141: getfield 12	pbk:a	Lcom/tencent/mobileqq/activity/richmedia/NewFlowCameraActivity;
    //   144: new 35	java/lang/StringBuilder
    //   147: dup
    //   148: invokespecial 36	java/lang/StringBuilder:<init>	()V
    //   151: ldc 92
    //   153: invokevirtual 42	java/lang/StringBuilder:append	(Ljava/lang/String;)Ljava/lang/StringBuilder;
    //   156: aload_0
    //   157: getfield 12	pbk:a	Lcom/tencent/mobileqq/activity/richmedia/NewFlowCameraActivity;
    //   160: invokestatic 95	com/tencent/mobileqq/activity/richmedia/NewFlowCameraActivity:a	(Lcom/tencent/mobileqq/activity/richmedia/NewFlowCameraActivity;)Ljava/lang/String;
    //   163: invokevirtual 42	java/lang/StringBuilder:append	(Ljava/lang/String;)Ljava/lang/StringBuilder;
    //   166: ldc 97
    //   168: invokevirtual 42	java/lang/StringBuilder:append	(Ljava/lang/String;)Ljava/lang/StringBuilder;
    //   171: invokevirtual 49	java/lang/StringBuilder:toString	()Ljava/lang/String;
    //   174: invokestatic 100	com/tencent/mobileqq/activity/richmedia/NewFlowCameraActivity:a	(Lcom/tencent/mobileqq/activity/richmedia/NewFlowCameraActivity;Ljava/lang/Object;)Ljava/lang/String;
    //   177: pop
    //   178: iload 4
    //   180: iconst_1
    //   181: iadd
    //   182: istore 4
    //   184: goto -56 -> 128
    //   187: ldc 57
    //   189: iconst_2
    //   190: new 35	java/lang/StringBuilder
    //   193: dup
    //   194: invokespecial 36	java/lang/StringBuilder:<init>	()V
    //   197: ldc 102
    //   199: invokevirtual 42	java/lang/StringBuilder:append	(Ljava/lang/String;)Ljava/lang/StringBuilder;
    //   202: aload_0
    //   203: getfield 12	pbk:a	Lcom/tencent/mobileqq/activity/richmedia/NewFlowCameraActivity;
    //   206: invokestatic 105	com/tencent/mobileqq/activity/richmedia/NewFlowCameraActivity:b	(Lcom/tencent/mobileqq/activity/richmedia/NewFlowCameraActivity;)Ljava/lang/String;
    //   209: invokevirtual 42	java/lang/StringBuilder:append	(Ljava/lang/String;)Ljava/lang/StringBuilder;
    //   212: invokevirtual 49	java/lang/StringBuilder:toString	()Ljava/lang/String;
    //   215: invokestatic 55	com/tencent/qphone/base/util/QLog:d	(Ljava/lang/String;ILjava/lang/String;)V
    //   218: aload_1
    //   219: invokevirtual 109	java/io/File:exists	()Z
    //   222: ifne +591 -> 813
    //   225: ldc 57
    //   227: iconst_2
    //   228: ldc 111
    //   230: invokestatic 55	com/tencent/qphone/base/util/QLog:d	(Ljava/lang/String;ILjava/lang/String;)V
    //   233: aload_1
    //   234: invokevirtual 113	java/io/File:createNewFile	()Z
    //   237: pop
    //   238: new 115	java/io/FileOutputStream
    //   241: dup
    //   242: invokestatic 79	com/tencent/mobileqq/activity/richmedia/NewFlowCameraActivity:e	()Ljava/lang/String;
    //   245: invokespecial 116	java/io/FileOutputStream:<init>	(Ljava/lang/String;)V
    //   248: astore_2
    //   249: aload_2
    //   250: astore_1
    //   251: aload_2
    //   252: aload_0
    //   253: getfield 12	pbk:a	Lcom/tencent/mobileqq/activity/richmedia/NewFlowCameraActivity;
    //   256: invokestatic 105	com/tencent/mobileqq/activity/richmedia/NewFlowCameraActivity:b	(Lcom/tencent/mobileqq/activity/richmedia/NewFlowCameraActivity;)Ljava/lang/String;
    //   259: invokevirtual 122	java/lang/String:getBytes	()[B
    //   262: invokevirtual 126	java/io/FileOutputStream:write	([B)V
    //   265: aload_2
    //   266: astore_1
    //   267: ldc 57
    //   269: iconst_2
    //   270: ldc -128
    //   272: invokestatic 55	com/tencent/qphone/base/util/QLog:d	(Ljava/lang/String;ILjava/lang/String;)V
    //   275: aload_2
    //   276: invokevirtual 131	java/io/FileOutputStream:close	()V
    //   279: ldc 57
    //   281: iconst_2
    //   282: ldc -123
    //   284: invokestatic 55	com/tencent/qphone/base/util/QLog:d	(Ljava/lang/String;ILjava/lang/String;)V
    //   287: bipush 9
    //   289: anewarray 118	java/lang/String
    //   292: astore_1
    //   293: aload_1
    //   294: iconst_0
    //   295: ldc -121
    //   297: aastore
    //   298: aload_1
    //   299: iconst_1
    //   300: ldc -119
    //   302: aastore
    //   303: aload_1
    //   304: iconst_2
    //   305: ldc -117
    //   307: aastore
    //   308: aload_1
    //   309: iconst_3
    //   310: ldc -115
    //   312: aastore
    //   313: aload_1
    //   314: iconst_4
    //   315: invokestatic 79	com/tencent/mobileqq/activity/richmedia/NewFlowCameraActivity:e	()Ljava/lang/String;
    //   318: aastore
    //   319: aload_1
    //   320: iconst_5
    //   321: ldc -113
    //   323: aastore
    //   324: aload_1
    //   325: bipush 6
    //   327: ldc -111
    //   329: aastore
    //   330: aload_1
    //   331: bipush 7
    //   333: ldc -121
    //   335: aastore
    //   336: aload_1
    //   337: bipush 8
    //   339: invokestatic 148	com/tencent/mobileqq/activity/richmedia/NewFlowCameraActivity:f	()Ljava/lang/String;
    //   342: aastore
    //   343: ldc 57
    //   345: iconst_2
    //   346: aload_1
    //   347: invokestatic 151	com/tencent/qphone/base/util/QLog:d	(Ljava/lang/String;I[Ljava/lang/Object;)V
    //   350: ldc 57
    //   352: iconst_2
    //   353: new 35	java/lang/StringBuilder
    //   356: dup
    //   357: invokespecial 36	java/lang/StringBuilder:<init>	()V
    //   360: ldc -103
    //   362: invokevirtual 42	java/lang/StringBuilder:append	(Ljava/lang/String;)Ljava/lang/StringBuilder;
    //   365: invokestatic 79	com/tencent/mobileqq/activity/richmedia/NewFlowCameraActivity:e	()Ljava/lang/String;
    //   368: invokevirtual 42	java/lang/StringBuilder:append	(Ljava/lang/String;)Ljava/lang/StringBuilder;
    //   371: invokevirtual 49	java/lang/StringBuilder:toString	()Ljava/lang/String;
    //   374: invokestatic 55	com/tencent/qphone/base/util/QLog:d	(Ljava/lang/String;ILjava/lang/String;)V
    //   377: ldc 57
    //   379: iconst_2
    //   380: new 35	java/lang/StringBuilder
    //   383: dup
    //   384: invokespecial 36	java/lang/StringBuilder:<init>	()V
    //   387: ldc -101
    //   389: invokevirtual 42	java/lang/StringBuilder:append	(Ljava/lang/String;)Ljava/lang/StringBuilder;
    //   392: invokestatic 148	com/tencent/mobileqq/activity/richmedia/NewFlowCameraActivity:f	()Ljava/lang/String;
    //   395: invokevirtual 42	java/lang/StringBuilder:append	(Ljava/lang/String;)Ljava/lang/StringBuilder;
    //   398: invokevirtual 49	java/lang/StringBuilder:toString	()Ljava/lang/String;
    //   401: invokestatic 55	com/tencent/qphone/base/util/QLog:d	(Ljava/lang/String;ILjava/lang/String;)V
    //   404: iconst_m1
    //   405: istore 4
    //   407: aload_1
    //   408: invokestatic 161	com/tencent/maxvideo/trim/TrimNative:trim	([Ljava/lang/String;)I
    //   411: istore 5
    //   413: iload 5
    //   415: istore 4
    //   417: aload_0
    //   418: getfield 12	pbk:a	Lcom/tencent/mobileqq/activity/richmedia/NewFlowCameraActivity;
    //   421: invokestatic 148	com/tencent/mobileqq/activity/richmedia/NewFlowCameraActivity:f	()Ljava/lang/String;
    //   424: invokestatic 163	com/tencent/mobileqq/activity/richmedia/NewFlowCameraActivity:f	(Lcom/tencent/mobileqq/activity/richmedia/NewFlowCameraActivity;Ljava/lang/String;)Ljava/lang/String;
    //   427: pop
    //   428: iload 5
    //   430: istore 4
    //   432: ldc 57
    //   434: iconst_2
    //   435: new 35	java/lang/StringBuilder
    //   438: dup
    //   439: invokespecial 36	java/lang/StringBuilder:<init>	()V
    //   442: ldc -91
    //   444: invokevirtual 42	java/lang/StringBuilder:append	(Ljava/lang/String;)Ljava/lang/StringBuilder;
    //   447: iload 4
    //   449: invokevirtual 68	java/lang/StringBuilder:append	(I)Ljava/lang/StringBuilder;
    //   452: invokevirtual 49	java/lang/StringBuilder:toString	()Ljava/lang/String;
    //   455: invokestatic 55	com/tencent/qphone/base/util/QLog:d	(Ljava/lang/String;ILjava/lang/String;)V
    //   458: bipush 8
    //   460: anewarray 118	java/lang/String
    //   463: dup
    //   464: iconst_0
    //   465: ldc -121
    //   467: aastore
    //   468: dup
    //   469: iconst_1
    //   470: ldc -115
    //   472: aastore
    //   473: dup
    //   474: iconst_2
    //   475: aload_0
    //   476: getfield 12	pbk:a	Lcom/tencent/mobileqq/activity/richmedia/NewFlowCameraActivity;
    //   479: getfield 169	com/tencent/mobileqq/activity/richmedia/NewFlowCameraActivity:m	Ljava/lang/String;
    //   482: aastore
    //   483: dup
    //   484: iconst_3
    //   485: ldc -85
    //   487: aastore
    //   488: dup
    //   489: iconst_4
    //   490: ldc -111
    //   492: aastore
    //   493: dup
    //   494: iconst_5
    //   495: ldc -83
    //   497: aastore
    //   498: dup
    //   499: bipush 6
    //   501: ldc -121
    //   503: aastore
    //   504: dup
    //   505: bipush 7
    //   507: invokestatic 175	com/tencent/mobileqq/activity/richmedia/NewFlowCameraActivity:g	()Ljava/lang/String;
    //   510: aastore
    //   511: invokestatic 161	com/tencent/maxvideo/trim/TrimNative:trim	([Ljava/lang/String;)I
    //   514: istore 4
    //   516: iload 4
    //   518: ifne +384 -> 902
    //   521: bipush 13
    //   523: anewarray 118	java/lang/String
    //   526: dup
    //   527: iconst_0
    //   528: ldc -121
    //   530: aastore
    //   531: dup
    //   532: iconst_1
    //   533: ldc -115
    //   535: aastore
    //   536: dup
    //   537: iconst_2
    //   538: invokestatic 175	com/tencent/mobileqq/activity/richmedia/NewFlowCameraActivity:g	()Ljava/lang/String;
    //   541: aastore
    //   542: dup
    //   543: iconst_3
    //   544: ldc -115
    //   546: aastore
    //   547: dup
    //   548: iconst_4
    //   549: aload_0
    //   550: getfield 12	pbk:a	Lcom/tencent/mobileqq/activity/richmedia/NewFlowCameraActivity;
    //   553: invokestatic 95	com/tencent/mobileqq/activity/richmedia/NewFlowCameraActivity:a	(Lcom/tencent/mobileqq/activity/richmedia/NewFlowCameraActivity;)Ljava/lang/String;
    //   556: aastore
    //   557: dup
    //   558: iconst_5
    //   559: ldc -79
    //   561: aastore
    //   562: dup
    //   563: bipush 6
    //   565: new 35	java/lang/StringBuilder
    //   568: dup
    //   569: invokespecial 36	java/lang/StringBuilder:<init>	()V
    //   572: aload_0
    //   573: getfield 12	pbk:a	Lcom/tencent/mobileqq/activity/richmedia/NewFlowCameraActivity;
    //   576: invokestatic 179	com/tencent/mobileqq/activity/richmedia/NewFlowCameraActivity:e	(Lcom/tencent/mobileqq/activity/richmedia/NewFlowCameraActivity;)I
    //   579: i2l
    //   580: invokestatic 182	com/tencent/mobileqq/activity/richmedia/NewFlowCameraActivity:a	(J)Ljava/lang/String;
    //   583: invokevirtual 42	java/lang/StringBuilder:append	(Ljava/lang/String;)Ljava/lang/StringBuilder;
    //   586: ldc 84
    //   588: invokevirtual 42	java/lang/StringBuilder:append	(Ljava/lang/String;)Ljava/lang/StringBuilder;
    //   591: invokevirtual 49	java/lang/StringBuilder:toString	()Ljava/lang/String;
    //   594: aastore
    //   595: dup
    //   596: bipush 7
    //   598: ldc -85
    //   600: aastore
    //   601: dup
    //   602: bipush 8
    //   604: ldc -111
    //   606: aastore
    //   607: dup
    //   608: bipush 9
    //   610: ldc -72
    //   612: aastore
    //   613: dup
    //   614: bipush 10
    //   616: ldc -111
    //   618: aastore
    //   619: dup
    //   620: bipush 11
    //   622: ldc -121
    //   624: aastore
    //   625: dup
    //   626: bipush 12
    //   628: invokestatic 186	com/tencent/mobileqq/activity/richmedia/NewFlowCameraActivity:h	()Ljava/lang/String;
    //   631: aastore
    //   632: invokestatic 161	com/tencent/maxvideo/trim/TrimNative:trim	([Ljava/lang/String;)I
    //   635: istore 4
    //   637: new 35	java/lang/StringBuilder
    //   640: dup
    //   641: invokespecial 36	java/lang/StringBuilder:<init>	()V
    //   644: invokestatic 189	com/tencent/mobileqq/activity/richmedia/NewFlowCameraActivity:c	()Ljava/lang/String;
    //   647: invokevirtual 42	java/lang/StringBuilder:append	(Ljava/lang/String;)Ljava/lang/StringBuilder;
    //   650: ldc -65
    //   652: invokevirtual 42	java/lang/StringBuilder:append	(Ljava/lang/String;)Ljava/lang/StringBuilder;
    //   655: invokestatic 31	java/lang/System:currentTimeMillis	()J
    //   658: invokevirtual 45	java/lang/StringBuilder:append	(J)Ljava/lang/StringBuilder;
    //   661: ldc -63
    //   663: invokevirtual 42	java/lang/StringBuilder:append	(Ljava/lang/String;)Ljava/lang/StringBuilder;
    //   666: invokevirtual 49	java/lang/StringBuilder:toString	()Ljava/lang/String;
    //   669: astore_1
    //   670: new 76	java/io/File
    //   673: dup
    //   674: invokestatic 186	com/tencent/mobileqq/activity/richmedia/NewFlowCameraActivity:h	()Ljava/lang/String;
    //   677: invokespecial 82	java/io/File:<init>	(Ljava/lang/String;)V
    //   680: new 76	java/io/File
    //   683: dup
    //   684: aload_1
    //   685: invokespecial 82	java/io/File:<init>	(Ljava/lang/String;)V
    //   688: invokestatic 198	com/tencent/mobileqq/utils/FileUtils:a	(Ljava/io/File;Ljava/io/File;)Z
    //   691: ifeq +204 -> 895
    //   694: ldc 33
    //   696: iconst_2
    //   697: new 35	java/lang/StringBuilder
    //   700: dup
    //   701: invokespecial 36	java/lang/StringBuilder:<init>	()V
    //   704: ldc -56
    //   706: invokevirtual 42	java/lang/StringBuilder:append	(Ljava/lang/String;)Ljava/lang/StringBuilder;
    //   709: aload_0
    //   710: getfield 12	pbk:a	Lcom/tencent/mobileqq/activity/richmedia/NewFlowCameraActivity;
    //   713: getfield 169	com/tencent/mobileqq/activity/richmedia/NewFlowCameraActivity:m	Ljava/lang/String;
    //   716: invokevirtual 42	java/lang/StringBuilder:append	(Ljava/lang/String;)Ljava/lang/StringBuilder;
    //   719: invokevirtual 49	java/lang/StringBuilder:toString	()Ljava/lang/String;
    //   722: invokestatic 55	com/tencent/qphone/base/util/QLog:d	(Ljava/lang/String;ILjava/lang/String;)V
    //   725: ldc 33
    //   727: iconst_2
    //   728: new 35	java/lang/StringBuilder
    //   731: dup
    //   732: invokespecial 36	java/lang/StringBuilder:<init>	()V
    //   735: ldc -54
    //   737: invokevirtual 42	java/lang/StringBuilder:append	(Ljava/lang/String;)Ljava/lang/StringBuilder;
    //   740: invokestatic 31	java/lang/System:currentTimeMillis	()J
    //   743: invokevirtual 45	java/lang/StringBuilder:append	(J)Ljava/lang/StringBuilder;
    //   746: invokevirtual 49	java/lang/StringBuilder:toString	()Ljava/lang/String;
    //   749: invokestatic 55	com/tencent/qphone/base/util/QLog:d	(Ljava/lang/String;ILjava/lang/String;)V
    //   752: ldc 33
    //   754: iconst_2
    //   755: new 35	java/lang/StringBuilder
    //   758: dup
    //   759: invokespecial 36	java/lang/StringBuilder:<init>	()V
    //   762: ldc -52
    //   764: invokevirtual 42	java/lang/StringBuilder:append	(Ljava/lang/String;)Ljava/lang/StringBuilder;
    //   767: invokestatic 31	java/lang/System:currentTimeMillis	()J
    //   770: lload 6
    //   772: lsub
    //   773: invokevirtual 45	java/lang/StringBuilder:append	(J)Ljava/lang/StringBuilder;
    //   776: invokevirtual 49	java/lang/StringBuilder:toString	()Ljava/lang/String;
    //   779: invokestatic 55	com/tencent/qphone/base/util/QLog:d	(Ljava/lang/String;ILjava/lang/String;)V
    //   782: aload_0
    //   783: getfield 12	pbk:a	Lcom/tencent/mobileqq/activity/richmedia/NewFlowCameraActivity;
    //   786: getfield 207	com/tencent/mobileqq/activity/richmedia/NewFlowCameraActivity:a	Landroid/os/Handler;
    //   789: new 209	pbl
    //   792: dup
    //   793: aload_0
    //   794: iload 4
    //   796: aload_1
    //   797: invokespecial 212	pbl:<init>	(Lpbk;ILjava/lang/String;)V
    //   800: invokevirtual 218	android/os/Handler:post	(Ljava/lang/Runnable;)Z
    //   803: pop
    //   804: return
    //   805: astore_1
    //   806: aload_1
    //   807: invokevirtual 221	java/lang/Exception:printStackTrace	()V
    //   810: goto -572 -> 238
    //   813: ldc 57
    //   815: iconst_2
    //   816: ldc -33
    //   818: invokestatic 55	com/tencent/qphone/base/util/QLog:d	(Ljava/lang/String;ILjava/lang/String;)V
    //   821: goto -583 -> 238
    //   824: astore_1
    //   825: aload_1
    //   826: invokevirtual 221	java/lang/Exception:printStackTrace	()V
    //   829: goto -550 -> 279
    //   832: astore_3
    //   833: aconst_null
    //   834: astore_2
    //   835: aload_2
    //   836: astore_1
    //   837: ldc 57
    //   839: iconst_2
    //   840: ldc -31
    //   842: invokestatic 55	com/tencent/qphone/base/util/QLog:d	(Ljava/lang/String;ILjava/lang/String;)V
    //   845: aload_2
    //   846: astore_1
    //   847: aload_3
    //   848: invokevirtual 221	java/lang/Exception:printStackTrace	()V
    //   851: aload_2
    //   852: invokevirtual 131	java/io/FileOutputStream:close	()V
    //   855: goto -576 -> 279
    //   858: astore_1
    //   859: aload_1
    //   860: invokevirtual 221	java/lang/Exception:printStackTrace	()V
    //   863: goto -584 -> 279
    //   866: astore_2
    //   867: aconst_null
    //   868: astore_1
    //   869: aload_1
    //   870: invokevirtual 131	java/io/FileOutputStream:close	()V
    //   873: aload_2
    //   874: athrow
    //   875: astore_1
    //   876: aload_1
    //   877: invokevirtual 221	java/lang/Exception:printStackTrace	()V
    //   880: goto -7 -> 873
    //   883: astore_1
    //   884: ldc 57
    //   886: iconst_2
    //   887: ldc -29
    //   889: invokestatic 229	com/tencent/qphone/base/util/QLog:e	(Ljava/lang/String;ILjava/lang/String;)V
    //   892: goto -460 -> 432
    //   895: invokestatic 186	com/tencent/mobileqq/activity/richmedia/NewFlowCameraActivity:h	()Ljava/lang/String;
    //   898: astore_1
    //   899: goto -174 -> 725
    //   902: aload_0
    //   903: getfield 12	pbk:a	Lcom/tencent/mobileqq/activity/richmedia/NewFlowCameraActivity;
    //   906: ldc -25
    //   908: iconst_1
    //   909: invokestatic 236	com/tencent/mobileqq/widget/QQToast:a	(Landroid/content/Context;Ljava/lang/CharSequence;I)Lcom/tencent/mobileqq/widget/QQToast;
    //   912: invokevirtual 239	com/tencent/mobileqq/widget/QQToast:a	()Landroid/widget/Toast;
    //   915: pop
    //   916: aload_0
    //   917: getfield 12	pbk:a	Lcom/tencent/mobileqq/activity/richmedia/NewFlowCameraActivity;
    //   920: ldc -15
    //   922: ldc -13
    //   924: ldc -11
    //   926: iconst_1
    //   927: invokestatic 248	com/tencent/mobileqq/activity/richmedia/NewFlowCameraActivity:a	(Lcom/tencent/mobileqq/activity/richmedia/NewFlowCameraActivity;Ljava/lang/String;Ljava/lang/String;Ljava/lang/String;Z)V
    //   930: ldc 33
    //   932: iconst_2
    //   933: new 35	java/lang/StringBuilder
    //   936: dup
    //   937: invokespecial 36	java/lang/StringBuilder:<init>	()V
    //   940: ldc -6
    //   942: invokevirtual 42	java/lang/StringBuilder:append	(Ljava/lang/String;)Ljava/lang/StringBuilder;
    //   945: iload 4
    //   947: invokevirtual 68	java/lang/StringBuilder:append	(I)Ljava/lang/StringBuilder;
    //   950: invokevirtual 49	java/lang/StringBuilder:toString	()Ljava/lang/String;
    //   953: invokestatic 55	com/tencent/qphone/base/util/QLog:d	(Ljava/lang/String;ILjava/lang/String;)V
    //   956: return
    //   957: astore_2
    //   958: goto -89 -> 869
    //   961: astore_3
    //   962: goto -127 -> 835
    // Local variable table:
    //   start	length	slot	name	signature
    //   0	965	0	this	pbk
    //   114	683	1	localObject1	Object
    //   805	2	1	localException1	Exception
    //   824	2	1	localException2	Exception
    //   836	11	1	localObject2	Object
    //   858	2	1	localException3	Exception
    //   868	2	1	localObject3	Object
    //   875	2	1	localException4	Exception
    //   883	1	1	localException5	Exception
    //   898	1	1	str	String
    //   248	604	2	localFileOutputStream	java.io.FileOutputStream
    //   866	8	2	localObject4	Object
    //   957	1	2	localObject5	Object
    //   832	16	3	localException6	Exception
    //   961	1	3	localException7	Exception
    //   126	820	4	i	int
    //   411	18	5	j	int
    //   3	768	6	l	long
    // Exception table:
    //   from	to	target	type
    //   225	238	805	java/lang/Exception
    //   275	279	824	java/lang/Exception
    //   238	249	832	java/lang/Exception
    //   851	855	858	java/lang/Exception
    //   238	249	866	finally
    //   869	873	875	java/lang/Exception
    //   407	413	883	java/lang/Exception
    //   417	428	883	java/lang/Exception
    //   251	265	957	finally
    //   267	275	957	finally
    //   837	845	957	finally
    //   847	851	957	finally
    //   251	265	961	java/lang/Exception
    //   267	275	961	java/lang/Exception
  }
}


/* Location:              E:\apk\QQ_91\classes3-dex2jar.jar!\pbk.class
 * Java compiler version: 6 (50.0)
 * JD-Core Version:       0.7.1
 */