package com.tencent.upload.network.b;

final class c
  implements Runnable
{
  c(String paramString, byte[] paramArrayOfByte, b.a parama) {}
  
  /* Error */
  public final void run()
  {
    // Byte code:
    //   0: aload_0
    //   1: getfield 16	com/tencent/upload/network/b/c:a	Ljava/lang/String;
    //   4: invokestatic 37	java/net/InetAddress:getByName	(Ljava/lang/String;)Ljava/net/InetAddress;
    //   7: invokevirtual 41	java/net/InetAddress:getHostAddress	()Ljava/lang/String;
    //   10: astore_1
    //   11: ldc 43
    //   13: new 45	java/lang/StringBuilder
    //   16: dup
    //   17: ldc 47
    //   19: invokespecial 50	java/lang/StringBuilder:<init>	(Ljava/lang/String;)V
    //   22: aload_1
    //   23: invokevirtual 54	java/lang/StringBuilder:append	(Ljava/lang/String;)Ljava/lang/StringBuilder;
    //   26: ldc 56
    //   28: invokevirtual 54	java/lang/StringBuilder:append	(Ljava/lang/String;)Ljava/lang/StringBuilder;
    //   31: aload_0
    //   32: getfield 16	com/tencent/upload/network/b/c:a	Ljava/lang/String;
    //   35: invokevirtual 54	java/lang/StringBuilder:append	(Ljava/lang/String;)Ljava/lang/StringBuilder;
    //   38: invokevirtual 59	java/lang/StringBuilder:toString	()Ljava/lang/String;
    //   41: invokestatic 64	com/tencent/upload/a/b:c	(Ljava/lang/String;Ljava/lang/String;)V
    //   44: aload_0
    //   45: getfield 18	com/tencent/upload/network/b/c:b	[B
    //   48: astore_2
    //   49: aload_2
    //   50: monitorenter
    //   51: aload_0
    //   52: getfield 20	com/tencent/upload/network/b/c:c	Lcom/tencent/upload/network/b/b$a;
    //   55: aload_1
    //   56: putfield 67	com/tencent/upload/network/b/b$a:a	Ljava/lang/String;
    //   59: aload_0
    //   60: getfield 18	com/tencent/upload/network/b/c:b	[B
    //   63: invokevirtual 70	java/lang/Object:notify	()V
    //   66: aload_2
    //   67: monitorexit
    //   68: return
    //   69: astore_2
    //   70: aconst_null
    //   71: astore_1
    //   72: ldc 43
    //   74: new 45	java/lang/StringBuilder
    //   77: dup
    //   78: ldc 72
    //   80: invokespecial 50	java/lang/StringBuilder:<init>	(Ljava/lang/String;)V
    //   83: aload_2
    //   84: invokevirtual 75	java/lang/StringBuilder:append	(Ljava/lang/Object;)Ljava/lang/StringBuilder;
    //   87: invokevirtual 59	java/lang/StringBuilder:toString	()Ljava/lang/String;
    //   90: invokestatic 78	com/tencent/upload/a/b:d	(Ljava/lang/String;Ljava/lang/String;)V
    //   93: goto -49 -> 44
    //   96: astore_2
    //   97: aconst_null
    //   98: astore_1
    //   99: ldc 43
    //   101: new 45	java/lang/StringBuilder
    //   104: dup
    //   105: ldc 80
    //   107: invokespecial 50	java/lang/StringBuilder:<init>	(Ljava/lang/String;)V
    //   110: aload_2
    //   111: invokevirtual 75	java/lang/StringBuilder:append	(Ljava/lang/Object;)Ljava/lang/StringBuilder;
    //   114: invokevirtual 59	java/lang/StringBuilder:toString	()Ljava/lang/String;
    //   117: invokestatic 78	com/tencent/upload/a/b:d	(Ljava/lang/String;Ljava/lang/String;)V
    //   120: goto -76 -> 44
    //   123: astore_2
    //   124: aconst_null
    //   125: astore_1
    //   126: ldc 43
    //   128: new 45	java/lang/StringBuilder
    //   131: dup
    //   132: ldc 82
    //   134: invokespecial 50	java/lang/StringBuilder:<init>	(Ljava/lang/String;)V
    //   137: aload_2
    //   138: invokevirtual 75	java/lang/StringBuilder:append	(Ljava/lang/Object;)Ljava/lang/StringBuilder;
    //   141: invokevirtual 59	java/lang/StringBuilder:toString	()Ljava/lang/String;
    //   144: invokestatic 78	com/tencent/upload/a/b:d	(Ljava/lang/String;Ljava/lang/String;)V
    //   147: goto -103 -> 44
    //   150: astore_1
    //   151: aload_2
    //   152: monitorexit
    //   153: aload_1
    //   154: athrow
    //   155: astore_2
    //   156: goto -30 -> 126
    //   159: astore_2
    //   160: goto -61 -> 99
    //   163: astore_2
    //   164: goto -92 -> 72
    // Local variable table:
    //   start	length	slot	name	signature
    //   0	167	0	this	c
    //   10	116	1	str	String
    //   150	4	1	localObject	Object
    //   69	15	2	localUnknownHostException1	java.net.UnknownHostException
    //   96	15	2	localException1	Exception
    //   123	29	2	localError1	Error
    //   155	1	2	localError2	Error
    //   159	1	2	localException2	Exception
    //   163	1	2	localUnknownHostException2	java.net.UnknownHostException
    // Exception table:
    //   from	to	target	type
    //   0	11	69	java/net/UnknownHostException
    //   0	11	96	java/lang/Exception
    //   0	11	123	java/lang/Error
    //   51	68	150	finally
    //   11	44	155	java/lang/Error
    //   11	44	159	java/lang/Exception
    //   11	44	163	java/net/UnknownHostException
  }
}


/* Location:              E:\apk\QQ_91\classes3-dex2jar.jar!\com\tencent\upload\network\b\c.class
 * Java compiler version: 6 (50.0)
 * JD-Core Version:       0.7.1
 */